Workbook

Sheet TdB
B1: Mois | C1: =EOMONTH(E1,-2)+1 -> 46174 | E1: =EOMONTH(G1,-2)+1 -> 46204 | G1: =DATE(YEAR(TODAY()),Month(TODAY()),1) -> 46235 | I1: =EOMONTH(G1,0)+1 -> 46266 | K1: =EOMONTH(I1,0)+1 -> 46296 | M1: =EOMONTH(K1,0)+1 -> 46327 | O1: =EOMONTH(M1,0)+1 -> 46357 | Q1: =EOMONTH(O1,0)+1 -> 46388 | S1: =EOMONTH(Q1,0)+1 -> 46419 | U1: =EOMONTH(S1,0)+1 -> 46447 | W1: =EOMONTH(U1,0)+1 -> 46478 | Y1: =EOMONTH(W1,0)+1 -> 46508 | AA1: =EOMONTH(Y1,0)+1 -> 46539 | AC1: =EOMONTH(AA1,0)+1 -> 46569 | AE1: =EOMONTH(AC1,0)+1 -> 46600 | AG1: =EOMONTH(AE1,0)+1 -> 46631
A2: Total | B2: CA nuitée | C2: =SUMIFS(dataMail!$R:$R,dataMail!$C:$C,"<>Annulation",dataMail!$G:$G,"<"&E$1,dataMail!$G:$G,">="&C$1) -> 38109.178 | E2: =SUMIFS(dataMail!$R:$R,dataMail!$C:$C,"<>Annulation",dataMail!$G:$G,"<"&G$1,dataMail!$G:$G,">="&E$1) -> 29567.798 | G2: =SUMIFS(dataMail!$R:$R,dataMail!$C:$C,"<>Annulation",dataMail!$G:$G,"<"&I$1,dataMail!$G:$G,">="&G$1) -> 30273.667 | I2: =SUMIFS(dataMail!$R:$R,dataMail!$C:$C,"<>Annulation",dataMail!$G:$G,"<"&K$1,dataMail!$G:$G,">="&I$1) -> 32476.561 | K2: =SUMIFS(dataMail!$R:$R,dataMail!$C:$C,"<>Annulation",dataMail!$G:$G,"<"&M$1,dataMail!$G:$G,">="&K$1) -> 45567.947 | M2: =SUMIFS(dataMail!$R:$R,dataMail!$C:$C,"<>Annulation",dataMail!$G:$G,"<"&O$1,dataMail!$G:$G,">="&M$1) -> 29328.625 | O2: =SUMIFS(dataMail!$R:$R,dataMail!$C:$C,"<>Annulation",dataMail!$G:$G,"<"&Q$1,dataMail!$G:$G,">="&O$1) -> 21874.036 | Q2: =SUMIFS(dataMail!$R:$R,dataMail!$C:$C,"<>Annulation",dataMail!$G:$G,"<"&S$1,dataMail!$G:$G,">="&Q$1) -> 15940.112 | S2: =SUMIFS(dataMail!$R:$R,dataMail!$C:$C,"<>Annulation",dataMail!$G:$G,"<"&U$1,dataMail!$G:$G,">="&S$1) -> 11937.696 | U2: =SUMIFS(dataMail!$R:$R,dataMail!$C:$C,"<>Annulation",dataMail!$G:$G,"<"&W$1,dataMail!$G:$G,">="&U$1) -> 4395.712 | W2: =SUMIFS(dataMail!$R:$R,dataMail!$C:$C,"<>Annulation",dataMail!$G:$G,"<"&Y$1,dataMail!$G:$G,">="&W$1) -> 5596.9216 | Y2: =SUMIFS(dataMail!$R:$R,dataMail!$C:$C,"<>Annulation",dataMail!$G:$G,"<"&AC$1,dataMail!$G:$G,">="&Y$1) -> 11413.76 | AA2: =SUMIFS(dataMail!$R:$R,dataMail!$C:$C,"<>Annulation",dataMail!$G:$G,"<"&AC$1,dataMail!$G:$G,">="&AA$1) -> 1656.832 | AC2: =SUMIFS(dataMail!$R:$R,dataMail!$C:$C,"<>Annulation",dataMail!$G:$G,"<"&AE$1,dataMail!$G:$G,">="&AC$1) -> 1080.24 | AE2: =SUMIFS(dataMail!$R:$R,dataMail!$C:$C,"<>Annulation",dataMail!$G:$G,"<"&AI$1,dataMail!$G:$G,">="&AE$1) -> 0 | AG2: =SUMIFS(dataMail!$R:$R,dataMail!$C:$C,"<>Annulation",dataMail!$G:$G,"<"&AK$1,dataMail!$G:$G,">="&AG$1) -> 0
B3: nb Nuitée | C3: =IFERROR(SUMIFS(dataMail!$I:$I,dataMail!$C:$C,"<>Annulation",dataMail!$G:$G,"<"&E$1,dataMail!$G:$G,">="&C$1),"-") -> 281 | E3: =IFERROR(SUMIFS(dataMail!$I:$I,dataMail!$C:$C,"<>Annulation",dataMail!$G:$G,"<"&G$1,dataMail!$G:$G,">="&E$1),"-") -> 241 | G3: =IFERROR(SUMIFS(dataMail!$I:$I,dataMail!$C:$C,"<>Annulation",dataMail!$G:$G,"<"&I$1,dataMail!$G:$G,">="&G$1),"-") -> 280 | I3: =IFERROR(SUMIFS(dataMail!$I:$I,dataMail!$C:$C,"<>Annulation",dataMail!$G:$G,"<"&K$1,dataMail!$G:$G,">="&I$1),"-") -> 248 | K3: =IFERROR(SUMIFS(dataMail!$I:$I,dataMail!$C:$C,"<>Annulation",dataMail!$G:$G,"<"&M$1,dataMail!$G:$G,">="&K$1),"-") -> 275 | M3: =IFERROR(SUMIFS(dataMail!$I:$I,dataMail!$C:$C,"<>Annulation",dataMail!$G:$G,"<"&O$1,dataMail!$G:$G,">="&M$1),"-") -> 184 | O3: =IFERROR(SUMIFS(dataMail!$I:$I,dataMail!$C:$C,"<>Annulation",dataMail!$G:$G,"<"&Q$1,dataMail!$G:$G,">="&O$1),"-") -> 127 | Q3: =IFERROR(SUMIFS(dataMail!$I:$I,dataMail!$C:$C,"<>Annulation",dataMail!$G:$G,"<"&S$1,dataMail!$G:$G,">="&Q$1),"-") -> 75 | S3: =IFERROR(SUMIFS(dataMail!$I:$I,dataMail!$C:$C,"<>Annulation",dataMail!$G:$G,"<"&U$1,dataMail!$G:$G,">="&S$1),"-") -> 65 | U3: =IFERROR(SUMIFS(dataMail!$I:$I,dataMail!$C:$C,"<>Annulation",dataMail!$G:$G,"<"&W$1,dataMail!$G:$G,">="&U$1),"-") -> 36 | W3: =IFERROR(SUMIFS(dataMail!$I:$I,dataMail!$C:$C,"<>Annulation",dataMail!$G:$G,"<"&Y$1,dataMail!$G:$G,">="&W$1),"-") -> 35 | Y3: =IFERROR(SUMIFS(dataMail!$I:$I,dataMail!$C:$C,"<>Annulation",dataMail!$G:$G,"<"&AC$1,dataMail!$G:$G,">="&Y$1),"-") -> 68 | AA3: =IFERROR(SUMIFS(dataMail!$I:$I,dataMail!$C:$C,"<>Annulation",dataMail!$G:$G,"<"&AC$1,dataMail!$G:$G,">="&AA$1),"-") -> 19 | AC3: =IFERROR(SUMIFS(dataMail!$I:$I,dataMail!$C:$C,"<>Annulation",dataMail!$G:$G,"<"&AE$1,dataMail!$G:$G,">="&AC$1),"-") -> 13 | AE3: =IFERROR(SUMIFS(dataMail!$I:$I,dataMail!$C:$C,"<>Annulation",dataMail!$G:$G,"<"&AI$1,dataMail!$G:$G,">="&AE$1),"-") -> 0 | AG3: =IFERROR(SUMIFS(dataMail!$I:$I,dataMail!$C:$C,"<>Annulation",dataMail!$G:$G,"<"&AK$1,dataMail!$G:$G,">="&AG$1),"-") -> 0
B4: Taux Yield | C4: =C3/(12*DAY(EOMONTH(C1,0))) -> 0.78055556 | E4: =E3/(12*DAY(EOMONTH(E1,0))) -> 0.64784946 | G4: =G3/(12*DAY(EOMONTH(G1,0))) -> 0.75268817 | I4: =I3/(12*DAY(EOMONTH(I1,0))) -> 0.68888889 | K4: =K3/(12*DAY(EOMONTH(K1,0))) -> 0.73924731 | M4: =M3/(12*DAY(EOMONTH(M1,0))) -> 0.51111111 | O4: =O3/(12*DAY(EOMONTH(O1,0))) -> 0.34139785 | Q4: =Q3/(12*DAY(EOMONTH(Q1,0))) -> 0.2016129 | S4: =S3/(12*DAY(EOMONTH(S1,0))) -> 0.19345238 | U4: =U3/(12*DAY(EOMONTH(U1,0))) -> 0.096774194 | W4: =W3/(12*DAY(EOMONTH(W1,0))) -> 0.097222222 | Y4: =Y3/(12*DAY(EOMONTH(Y1,0))) -> 0.1827957 | AA4: =AA3/(12*DAY(EOMONTH(AA1,0))) -> 0.052777778 | AC4: =AC3/(12*DAY(EOMONTH(AC1,0))) -> 0.034946237 | AE4: =AE3/(12*DAY(EOMONTH(AE1,0))) -> 0 | AG4: =AG3/(12*DAY(EOMONTH(AG1,0))) -> 0
B5: Moyenne | C5: =C2/C3 -> 135.61985 | E5: =E2/E3 -> 122.68796 | G5: =G2/G3 -> 108.12024 | I5: =I2/I3 -> 130.95388 | K5: =K2/K3 -> 165.70163 | M5: =M2/M3 -> 159.3947 | O5: =O2/O3 -> 172.2365 | Q5: =Q2/Q3 -> 212.53483 | S5: =S2/S3 -> 183.65686 | U5: =U2/U3 -> 122.10311 | W5: =W2/W3 -> 159.91205 | Y5: =Y2/Y3 -> 167.84941 | AA5: =AA2/AA3 -> 87.201684 | AC5: =AC2/AC3 -> 83.095385 | AE5: =AE2/AE3 -> #DIV/0! | AG5: =AG2/AG3 -> #DIV/0!
B6: Taux Reel | C6: =1-SUM(D11:D41)/(12*DAY(EOMONTH(C3,0))) -> 0.82526882 | E6: =1-SUM(F11:F41)/(12*DAY(EOMONTH(E3,0))) -> 0.78763441 | G6: =1-SUM(H11:H41)/(12*DAY(EOMONTH(G3,0))) -> 0.81989247 | I6: =1-SUM(J11:J41)/(12*DAY(EOMONTH(I3,0))) -> 0.84722222 | K6: =1-SUM(L11:L41)/(12*DAY(EOMONTH(K3,0))) -> 0.87096774 | M6: =1-SUM(N11:N41)/(12*DAY(EOMONTH(M3,0))) -> 0.61827957 | O6: =1-SUM(P11:P41)/(12*DAY(EOMONTH(O3,0))) -> 0.41666667 | Q6: =1-SUM(R11:R41)/(12*DAY(EOMONTH(Q3,0))) -> 0.2983871 | S6: =1-SUM(T11:T41)/(12*DAY(EOMONTH(S3,0))) -> 0.27419355 | U6: =1-SUM(V11:V41)/(12*DAY(EOMONTH(U3,0))) -> 0.074404762 | W6: =1-SUM(X11:X41)/(12*DAY(EOMONTH(W3,0))) -> 0.13988095 | Y6: =1-SUM(Z11:Z41)/(12*DAY(EOMONTH(Y3,0))) -> 0.21505376 | AA6: =1-SUM(AB11:AB41)/(12*DAY(EOMONTH(AA3,0))) -> 0.16397849 | AC6: =1-SUM(AD11:AD41)/(12*DAY(EOMONTH(AC3,0))) -> 0.11827957 | AE6: =1-SUM(AF11:AF41)/(12*DAY(EOMONTH(AE3,0))) -> 0.17473118 | AG6: =1-SUM(AH11:AH41)/(12*DAY(EOMONTH(AG3,0))) -> 0.12903226
B7: CA Sup | C7: =SUMIFS(dataMail!$S:$S,dataMail!$C:$C,"<>Annulation",dataMail!$G:$G,"<"&E$1,dataMail!$G:$G,">="&C$1) -> 36 | E7: =SUMIFS(dataMail!$S:$S,dataMail!$C:$C,"<>Annulation",dataMail!$G:$G,"<"&G$1,dataMail!$G:$G,">="&E$1) -> 558 | G7: =SUMIFS(dataMail!$S:$S,dataMail!$C:$C,"<>Annulation",dataMail!$G:$G,"<"&I$1,dataMail!$G:$G,">="&G$1) -> 0 | I7: =SUMIFS(dataMail!$S:$S,dataMail!$C:$C,"<>Annulation",dataMail!$G:$G,"<"&K$1,dataMail!$G:$G,">="&I$1) -> 720 | K7: =SUMIFS(dataMail!$S:$S,dataMail!$C:$C,"<>Annulation",dataMail!$G:$G,"<"&M$1,dataMail!$G:$G,">="&K$1) -> 630 | M7: =SUMIFS(dataMail!$S:$S,dataMail!$C:$C,"<>Annulation",dataMail!$G:$G,"<"&O$1,dataMail!$G:$G,">="&M$1) -> 396 | O7: =SUMIFS(dataMail!$S:$S,dataMail!$C:$C,"<>Annulation",dataMail!$G:$G,"<"&Q$1,dataMail!$G:$G,">="&O$1) -> 108 | Q7: =SUMIFS(dataMail!$S:$S,dataMail!$C:$C,"<>Annulation",dataMail!$G:$G,"<"&S$1,dataMail!$G:$G,">="&Q$1) -> 36 | S7: =SUMIFS(dataMail!$S:$S,dataMail!$C:$C,"<>Annulation",dataMail!$G:$G,"<"&U$1,dataMail!$G:$G,">="&S$1) -> 72 | U7: =SUMIFS(dataMail!$S:$S,dataMail!$C:$C,"<>Annulation",dataMail!$G:$G,"<"&W$1,dataMail!$G:$G,">="&U$1) -> 216 | W7: =SUMIFS(dataMail!$S:$S,dataMail!$C:$C,"<>Annulation",dataMail!$G:$G,"<"&Y$1,dataMail!$G:$G,">="&W$1) -> 72 | Y7: =SUMIFS(dataMail!$S:$S,dataMail!$C:$C,"<>Annulation",dataMail!$G:$G,"<"&AC$1,dataMail!$G:$G,">="&Y$1) -> 0 | AA7: =SUMIFS(dataMail!$S:$S,dataMail!$C:$C,"<>Annulation",dataMail!$G:$G,"<"&AC$1,dataMail!$G:$G,">="&AA$1) -> 0 | AC7: =SUMIFS(dataMail!$S:$S,dataMail!$C:$C,"<>Annulation",dataMail!$G:$G,"<"&AE$1,dataMail!$G:$G,">="&AC$1) -> 0 | AE7: =SUMIFS(dataMail!$S:$S,dataMail!$C:$C,"<>Annulation",dataMail!$G:$G,"<"&AI$1,dataMail!$G:$G,">="&AE$1) -> 0 | AG7: =SUMIFS(dataMail!$S:$S,dataMail!$C:$C,"<>Annulation",dataMail!$G:$G,"<"&AK$1,dataMail!$G:$G,">="&AG$1) -> 0
A8: HotelBeds | B8: CA Total | C8: =SUMIFS(dataMail!$R:$R,dataMail!$C:$C,"<>Annulation",dataMail!$G:$G,"<"&E$1,dataMail!$G:$G,">="&C$1,dataMail!$D:$D,$A8) +SUMIFS(dataMail!$S:$S,dataMail!$C:$C,"<>Annulation",dataMail!$G:$G,"<"&E$1,dataMail!$G:$G,">="&C$1,dataMail!$D:$D,$A8) -> 0 | E8: =SUMIFS(dataMail!$R:$R,dataMail!$C:$C,"<>Annulation",dataMail!$G:$G,"<"&G$1,dataMail!$G:$G,">="&E$1,dataMail!$D:$D,$A8) +SUMIFS(dataMail!$S:$S,dataMail!$C:$C,"<>Annulation",dataMail!$G:$G,"<"&G$1,dataMail!$G:$G,">="&E$1,dataMail!$D:$D,$A8) -> 0 | G8: =SUMIFS(dataMail!$R:$R,dataMail!$C:$C,"<>Annulation",dataMail!$G:$G,"<"&I$1,dataMail!$G:$G,">="&G$1,dataMail!$D:$D,$A8) +SUMIFS(dataMail!$S:$S,dataMail!$C:$C,"<>Annulation",dataMail!$G:$G,"<"&I$1,dataMail!$G:$G,">="&G$1,dataMail!$D:$D,$A8) -> 0 | I8: =SUMIFS(dataMail!$R:$R,dataMail!$C:$C,"<>Annulation",dataMail!$G:$G,"<"&K$1,dataMail!$G:$G,">="&I$1,dataMail!$D:$D,$A8) +SUMIFS(dataMail!$S:$S,dataMail!$C:$C,"<>Annulation",dataMail!$G:$G,"<"&K$1,dataMail!$G:$G,">="&I$1,dataMail!$D:$D,$A8) -> 287.72 | K8: =SUMIFS(dataMail!$R:$R,dataMail!$C:$C,"<>Annulation",dataMail!$G:$G,"<"&M$1,dataMail!$G:$G,">="&K$1,dataMail!$D:$D,$A8) +SUMIFS(dataMail!$S:$S,dataMail!$C:$C,"<>Annulation",dataMail!$G:$G,"<"&M$1,dataMail!$G:$G,">="&K$1,dataMail!$D:$D,$A8) -> 2253.824 | M8: =SUMIFS(dataMail!$R:$R,dataMail!$C:$C,"<>Annulation",dataMail!$G:$G,"<"&O$1,dataMail!$G:$G,">="&M$1,dataMail!$D:$D,$A8) +SUMIFS(dataMail!$S:$S,dataMail!$C:$C,"<>Annulation",dataMail!$G:$G,"<"&O$1,dataMail!$G:$G,">="&M$1,dataMail!$D:$D,$A8) -> 612.992 | O8: =SUMIFS(dataMail!$R:$R,dataMail!$C:$C,"<>Annulation",dataMail!$G:$G,"<"&Q$1,dataMail!$G:$G,">="&O$1,dataMail!$D:$D,$A8) +SUMIFS(dataMail!$S:$S,dataMail!$C:$C,"<>Annulation",dataMail!$G:$G,"<"&Q$1,dataMail!$G:$G,">="&O$1,dataMail!$D:$D,$A8) -> 0 | Q8: =SUMIFS(dataMail!$R:$R,dataMail!$C:$C,"<>Annulation",dataMail!$G:$G,"<"&S$1,dataMail!$G:$G,">="&Q$1,dataMail!$D:$D,$A8) +SUMIFS(dataMail!$S:$S,dataMail!$C:$C,"<>Annulation",dataMail!$G:$G,"<"&S$1,dataMail!$G:$G,">="&Q$1,dataMail!$D:$D,$A8) -> 0 | S8: =SUMIFS(dataMail!$R:$R,dataMail!$C:$C,"<>Annulation",dataMail!$G:$G,"<"&U$1,dataMail!$G:$G,">="&S$1,dataMail!$D:$D,$A8) +SUMIFS(dataMail!$S:$S,dataMail!$C:$C,"<>Annulation",dataMail!$G:$G,"<"&U$1,dataMail!$G:$G,">="&S$1,dataMail!$D:$D,$A8) -> 0 | U8: =SUMIFS(dataMail!$R:$R,dataMail!$C:$C,"<>Annulation",dataMail!$G:$G,"<"&W$1,dataMail!$G:$G,">="&U$1,dataMail!$D:$D,$A8) +SUMIFS(dataMail!$S:$S,dataMail!$C:$C,"<>Annulation",dataMail!$G:$G,"<"&W$1,dataMail!$G:$G,">="&U$1,dataMail!$D:$D,$A8) -> 0 | W8: =SUMIFS(dataMail!$R:$R,dataMail!$C:$C,"<>Annulation",dataMail!$G:$G,"<"&Y$1,dataMail!$G:$G,">="&W$1,dataMail!$D:$D,$A8) +SUMIFS(dataMail!$S:$S,dataMail!$C:$C,"<>Annulation",dataMail!$G:$G,"<"&Y$1,dataMail!$G:$G,">="&W$1,dataMail!$D:$D,$A8) -> 0 | Y8: =SUMIFS(dataMail!$R:$R,dataMail!$C:$C,"<>Annulation",dataMail!$G:$G,"<"&AC$1,dataMail!$G:$G,">="&Y$1,dataMail!$D:$D,$A8) +SUMIFS(dataMail!$S:$S,dataMail!$C:$C,"<>Annulation",dataMail!$G:$G,"<"&AC$1,dataMail!$G:$G,">="&Y$1,dataMail!$D:$D,$A8) -> 0 | AA8: =SUMIFS(dataMail!$R:$R,dataMail!$C:$C,"<>Annulation",dataMail!$G:$G,"<"&AC$1,dataMail!$G:$G,">="&AA$1,dataMail!$D:$D,$A8) +SUMIFS(dataMail!$S:$S,dataMail!$C:$C,"<>Annulation",dataMail!$G:$G,"<"&AC$1,dataMail!$G:$G,">="&AA$1,dataMail!$D:$D,$A8) -> 0 | AC8: =SUMIFS(dataMail!$R:$R,dataMail!$C:$C,"<>Annulation",dataMail!$G:$G,"<"&AE$1,dataMail!$G:$G,">="&AC$1,dataMail!$D:$D,$A8) +SUMIFS(dataMail!$S:$S,dataMail!$C:$C,"<>Annulation",dataMail!$G:$G,"<"&AE$1,dataMail!$G:$G,">="&AC$1,dataMail!$D:$D,$A8) -> 0 | AE8: =SUMIFS(dataMail!$R:$R,dataMail!$C:$C,"<>Annulation",dataMail!$G:$G,"<"&AI$1,dataMail!$G:$G,">="&AE$1,dataMail!$D:$D,$A8) +SUMIFS(dataMail!$S:$S,dataMail!$C:$C,"<>Annulation",dataMail!$G:$G,"<"&AI$1,dataMail!$G:$G,">="&AE$1,dataMail!$D:$D,$A8) -> 0 | AG8: =SUMIFS(dataMail!$R:$R,dataMail!$C:$C,"<>Annulation",dataMail!$G:$G,"<"&AK$1,dataMail!$G:$G,">="&AG$1,dataMail!$D:$D,$A8) +SUMIFS(dataMail!$S:$S,dataMail!$C:$C,"<>Annulation",dataMail!$G:$G,"<"&AK$1,dataMail!$G:$G,">="&AG$1,dataMail!$D:$D,$A8) -> 0
B9: Moyenne | C9: =IFERROR(AVERAGEIFS(dataMail!$P:$P,dataMail!$C:$C,"<>Annulation",dataMail!$G:$G,"<"&E$1,dataMail!$G:$G,">="&C$1,dataMail!$D:$D,$A8),"-") -> - | E9: =IFERROR(AVERAGEIFS(dataMail!$P:$P,dataMail!$C:$C,"<>Annulation",dataMail!$G:$G,"<"&G$1,dataMail!$G:$G,">="&E$1,dataMail!$D:$D,$A8),"-") -> - | G9: =IFERROR(AVERAGEIFS(dataMail!$P:$P,dataMail!$C:$C,"<>Annulation",dataMail!$G:$G,"<"&I$1,dataMail!$G:$G,">="&G$1,dataMail!$D:$D,$A8),"-") -> - | I9: =IFERROR(AVERAGEIFS(dataMail!$P:$P,dataMail!$C:$C,"<>Annulation",dataMail!$G:$G,"<"&K$1,dataMail!$G:$G,">="&I$1,dataMail!$D:$D,$A8),"-") -> 143.86 | K9: =IFERROR(AVERAGEIFS(dataMail!$P:$P,dataMail!$C:$C,"<>Annulation",dataMail!$G:$G,"<"&M$1,dataMail!$G:$G,">="&K$1,dataMail!$D:$D,$A8),"-") -> 301.92 | M9: =IFERROR(AVERAGEIFS(dataMail!$P:$P,dataMail!$C:$C,"<>Annulation",dataMail!$G:$G,"<"&O$1,dataMail!$G:$G,">="&M$1,dataMail!$D:$D,$A8),"-") -> 153.248 | O9: =IFERROR(AVERAGEIFS(dataMail!$P:$P,dataMail!$C:$C,"<>Annulation",dataMail!$G:$G,"<"&Q$1,dataMail!$G:$G,">="&O$1,dataMail!$D:$D,$A8),"-") -> - | Q9: =IFERROR(AVERAGEIFS(dataMail!$P:$P,dataMail!$C:$C,"<>Annulation",dataMail!$G:$G,"<"&S$1,dataMail!$G:$G,">="&Q$1,dataMail!$D:$D,$A8),"-") -> - | S9: =IFERROR(AVERAGEIFS(dataMail!$P:$P,dataMail!$C:$C,"<>Annulation",dataMail!$G:$G,"<"&U$1,dataMail!$G:$G,">="&S$1,dataMail!$D:$D,$A8),"-") -> - | U9: =IFERROR(AVERAGEIFS(dataMail!$P:$P,dataMail!$C:$C,"<>Annulation",dataMail!$G:$G,"<"&W$1,dataMail!$G:$G,">="&U$1,dataMail!$D:$D,$A8),"-") -> - | W9: =IFERROR(AVERAGEIFS(dataMail!$P:$P,dataMail!$C:$C,"<>Annulation",dataMail!$G:$G,"<"&Y$1,dataMail!$G:$G,">="&W$1,dataMail!$D:$D,$A8),"-") -> - | Y9: =IFERROR(AVERAGEIFS(dataMail!$P:$P,dataMail!$C:$C,"<>Annulation",dataMail!$G:$G,"<"&AC$1,dataMail!$G:$G,">="&Y$1,dataMail!$D:$D,$A8),"-") -> - | AA9: =IFERROR(AVERAGEIFS(dataMail!$P:$P,dataMail!$C:$C,"<>Annulation",dataMail!$G:$G,"<"&AC$1,dataMail!$G:$G,">="&AA$1,dataMail!$D:$D,$A8),"-") -> - | AC9: =IFERROR(AVERAGEIFS(dataMail!$P:$P,dataMail!$C:$C,"<>Annulation",dataMail!$G:$G,"<"&AE$1,dataMail!$G:$G,">="&AC$1,dataMail!$D:$D,$A8),"-") -> - | AE9: =IFERROR(AVERAGEIFS(dataMail!$P:$P,dataMail!$C:$C,"<>Annulation",dataMail!$G:$G,"<"&AI$1,dataMail!$G:$G,">="&AE$1,dataMail!$D:$D,$A8),"-") -> - | AG9: =IFERROR(AVERAGEIFS(dataMail!$P:$P,dataMail!$C:$C,"<>Annulation",dataMail!$G:$G,"<"&AK$1,dataMail!$G:$G,">="&AG$1,dataMail!$D:$D,$A8),"-") -> -
B11: 1 | C11: =IF(DAY(EOMONTH(C$1,0))>=$B11,IFERROR(AVERAGEIFS(dataMail!$P:$P,dataMail!$C:$C,"Confirmation",dataMail!$G:$G,"<="&(C$1+$B11-1),dataMail!$H:$H,">"&(C$1+$B11-1)),"-"),"-") -> 122.48875 | D11: =IF(DAY(EOMONTH(C$1,0))>=$B11, 11-COUNTIFS(dataMail!$C:$C,"<>Annulation",dataMail!$G:$G,"<="&(C$1+$B11-1),dataMail!$H:$H,">"&(C$1+$B11-1)),"-") -> 2 | E11: =IF(DAY(EOMONTH(E$1,0))>=$B11,IFERROR(AVERAGEIFS(dataMail!$P:$P,dataMail!$C:$C,"Confirmation",dataMail!$G:$G,"<="&(E$1+$B11-1),dataMail!$H:$H,">"&(E$1+$B11-1)),"-"),"-") -> 161.85927 | F11: =IF(DAY(EOMONTH(E$1,0))>=$B11, 11-COUNTIFS(dataMail!$C:$C,"<>Annulation",dataMail!$G:$G,"<="&(E$1+$B11-1),dataMail!$H:$H,">"&(E$1+$B11-1)),"-") -> 3 | G11: =IF(DAY(EOMONTH(G$1,0))>=$B11,IFERROR(AVERAGEIFS(dataMail!$P:$P,dataMail!$C:$C,"Confirmation",dataMail!$G:$G,"<="&(G$1+$B11-1),dataMail!$H:$H,">"&(G$1+$B11-1)),"-"),"-") -> 96.6784 | H11: =IF(DAY(EOMONTH(G$1,0))>=$B11, 11-COUNTIFS(dataMail!$C:$C,"<>Annulation",dataMail!$G:$G,"<="&(G$1+$B11-1),dataMail!$H:$H,">"&(G$1+$B11-1)),"-") -> 1 | I11: =IF(DAY(EOMONTH(I$1,0))>=$B11,IFERROR(AVERAGEIFS(dataMail!$P:$P,dataMail!$C:$C,"Confirmation",dataMail!$G:$G,"<="&(I$1+$B11-1),dataMail!$H:$H,">"&(I$1+$B11-1)),"-"),"-") -> 126.1462 | J11: =IF(DAY(EOMONTH(I$1,0))>=$B11, 11-COUNTIFS(dataMail!$C:$C,"<>Annulation",dataMail!$G:$G,"<="&(I$1+$B11-1),dataMail!$H:$H,">"&(I$1+$B11-1)),"-") -> 1 | K11: =IF(DAY(EOMONTH(K$1,0))>=$B11,IFERROR(AVERAGEIFS(dataMail!$P:$P,dataMail!$C:$C,"Confirmation",dataMail!$G:$G,"<="&(K$1+$B11-1),dataMail!$H:$H,">"&(K$1+$B11-1)),"-"),"-") -> 132.7 | L11: =IF(DAY(EOMONTH(K$1,0))>=$B11, 11-COUNTIFS(dataMail!$C:$C,"<>Annulation",dataMail!$G:$G,"<="&(K$1+$B11-1),dataMail!$H:$H,">"&(K$1+$B11-1)),"-") -> -4 | M11: =IF(DAY(EOMONTH(M$1,0))>=$B11,IFERROR(AVERAGEIFS(dataMail!$P:$P,dataMail!$C:$C,"Confirmation",dataMail!$G:$G,"<="&(M$1+$B11-1),dataMail!$H:$H,">"&(M$1+$B11-1)),"-"),"-") -> 181.86667 | N11: =IF(DAY(EOMONTH(M$1,0))>=$B11, 11-COUNTIFS(dataMail!$C:$C,"<>Annulation",dataMail!$G:$G,"<="&(M$1+$B11-1),dataMail!$H:$H,">"&(M$1+$B11-1)),"-") -> 8 | O11: =IF(DAY(EOMONTH(O$1,0))>=$B11,IFERROR(AVERAGEIFS(dataMail!$P:$P,dataMail!$C:$C,"Confirmation",dataMail!$G:$G,"<="&(O$1+$B11-1),dataMail!$H:$H,">"&(O$1+$B11-1)),"-"),"-") -> 134.456 | P11: =IF(DAY(EOMONTH(O$1,0))>=$B11, 11-COUNTIFS(dataMail!$C:$C,"<>Annulation",dataMail!$G:$G,"<="&(O$1+$B11-1),dataMail!$H:$H,">"&(O$1+$B11-1)),"-") -> 9 | Q11: =IF(DAY(EOMONTH(Q$1,0))>=$B11,IFERROR(AVERAGEIFS(dataMail!$P:$P,dataMail!$C:$C,"Confirmation",dataMail!$G:$G,"<="&(Q$1+$B11-1),dataMail!$H:$H,">"&(Q$1+$B11-1)),"-"),"-") -> 190.13917 | R11: =IF(DAY(EOMONTH(Q$1,0))>=$B11, 11-COUNTIFS(dataMail!$C:$C,"<>Annulation",dataMail!$G:$G,"<="&(Q$1+$B11-1),dataMail!$H:$H,">"&(Q$1+$B11-1)),"-") -> 8 | S11: =IF(DAY(EOMONTH(S$1,0))>=$B11,IFERROR(AVERAGEIFS(dataMail!$P:$P,dataMail!$C:$C,"Confirmation",dataMail!$G:$G,"<="&(S$1+$B11-1),dataMail!$H:$H,">"&(S$1+$B11-1)),"-"),"-") -> 120.576 | T11: =IF(DAY(EOMONTH(S$1,0))>=$B11, 11-COUNTIFS(dataMail!$C:$C,"<>Annulation",dataMail!$G:$G,"<="&(S$1+$B11-1),dataMail!$H:$H,">"&(S$1+$B11-1)),"-") -> 10 | U11: =IF(DAY(EOMONTH(U$1,0))>=$B11,IFERROR(AVERAGEIFS(dataMail!$P:$P,dataMail!$C:$C,"Confirmation",dataMail!$G:$G,"<="&(U$1+$B11-1),dataMail!$H:$H,">"&(U$1+$B11-1)),"-"),"-") -> - | V11: =IF(DAY(EOMONTH(U$1,0))>=$B11, 11-COUNTIFS(dataMail!$C:$C,"<>Annulation",dataMail!$G:$G,"<="&(U$1+$B11-1),dataMail!$H:$H,">"&(U$1+$B11-1)),"-") -> 11 | W11: =IF(DAY(EOMONTH(W$1,0))>=$B11,IFERROR(AVERAGEIFS(dataMail!$P:$P,dataMail!$C:$C,"Confirmation",dataMail!$G:$G,"<="&(W$1+$B11-1),dataMail!$H:$H,">"&(W$1+$B11-1)),"-"),"-") -> 146.868 | X11: =IF(DAY(EOMONTH(W$1,0))>=$B11, 11-COUNTIFS(dataMail!$C:$C,"<>Annulation",dataMail!$G:$G,"<="&(W$1+$B11-1),dataMail!$H:$H,">"&(W$1+$B11-1)),"-") -> 9 | Y11: =IF(DAY(EOMONTH(Y$1,0))>=$B11,IFERROR(AVERAGEIFS(dataMail!$P:$P,dataMail!$C:$C,"Confirmation",dataMail!$G:$G,"<="&(Y$1+$B11-1),dataMail!$H:$H,">"&(Y$1+$B11-1)),"-"),"-") -> - | Z11: =IF(DAY(EOMONTH(Y$1,0))>=$B11, 11-COUNTIFS(dataMail!$C:$C,"<>Annulation",dataMail!$G:$G,"<="&(Y$1+$B11-1),dataMail!$H:$H,">"&(Y$1+$B11-1)),"-") -> 11 | AA11: =IF(DAY(EOMONTH(AA$1,0))>=$B11,IFERROR(AVERAGEIFS(dataMail!$P:$P,dataMail!$C:$C,"Confirmation",dataMail!$G:$G,"<="&(AA$1+$B11-1),dataMail!$H:$H,">"&(AA$1+$B11-1)),"-"),"-") -> - | AB11: =IF(DAY(EOMONTH(AA$1,0))>=$B11, 11-COUNTIFS(dataMail!$C:$C,"<>Annulation",dataMail!$G:$G,"<="&(AA$1+$B11-1),dataMail!$H:$H,">"&(AA$1+$B11-1)),"-") -> 11 | AC11: =IF(DAY(EOMONTH(AC$1,0))>=$B11,IFERROR(AVERAGEIFS(dataMail!$P:$P,dataMail!$C:$C,"Confirmation",dataMail!$G:$G,"<="&(AC$1+$B11-1),dataMail!$H:$H,">"&(AC$1+$B11-1)),"-"),"-") -> - | AD11: =IF(DAY(EOMONTH(AC$1,0))>=$B11, 11-COUNTIFS(dataMail!$C:$C,"<>Annulation",dataMail!$G:$G,"<="&(AC$1+$B11-1),dataMail!$H:$H,">"&(AC$1+$B11-1)),"-") -> 11 | AE11: =IF(DAY(EOMONTH(AE$1,0))>=$B11,IFERROR(AVERAGEIFS(dataMail!$P:$P,dataMail!$C:$C,"Confirmation",dataMail!$G:$G,"<="&(AE$1+$B11-1),dataMail!$H:$H,">"&(AE$1+$B11-1)),"-"),"-") -> - | AF11: =IF(DAY(EOMONTH(AE$1,0))>=$B11, 11-COUNTIFS(dataMail!$C:$C,"<>Annulation",dataMail!$G:$G,"<="&(AE$1+$B11-1),dataMail!$H:$H,">"&(AE$1+$B11-1)),"-") -> 11 | AG11: =IF(DAY(EOMONTH(AG$1,0))>=$B11,IFERROR(AVERAGEIFS(dataMail!$P:$P,dataMail!$C:$C,"Confirmation",dataMail!$G:$G,"<="&(AG$1+$B11-1),dataMail!$H:$H,">"&(AG$1+$B11-1)),"-"),"-") -> 115.312 | AH11: =IF(DAY(EOMONTH(AG$1,0))>=$B11, 11-COUNTIFS(dataMail!$C:$C,"<>Annulation",dataMail!$G:$G,"<="&(AG$1+$B11-1),dataMail!$H:$H,">"&(AG$1+$B11-1)),"-") -> 10
B12: 2 | C12: =IF(DAY(EOMONTH(C$1,0))>=$B12,IFERROR(AVERAGEIFS(dataMail!$P:$P,dataMail!$C:$C,"Confirmation",dataMail!$G:$G,"<="&(C$1+$B12-1),dataMail!$H:$H,">"&(C$1+$B12-1)),"-"),"-") -> 108.44118 | D12: =IF(DAY(EOMONTH(C$1,0))>=$B12, 11-COUNTIFS(dataMail!$C:$C,"<>Annulation",dataMail!$G:$G,"<="&(C$1+$B12-1),dataMail!$H:$H,">"&(C$1+$B12-1)),"-") -> 3 | E12: =IF(DAY(EOMONTH(E$1,0))>=$B12,IFERROR(AVERAGEIFS(dataMail!$P:$P,dataMail!$C:$C,"Confirmation",dataMail!$G:$G,"<="&(E$1+$B12-1),dataMail!$H:$H,">"&(E$1+$B12-1)),"-"),"-") -> 178.6824 | F12: =IF(DAY(EOMONTH(E$1,0))>=$B12, 11-COUNTIFS(dataMail!$C:$C,"<>Annulation",dataMail!$G:$G,"<="&(E$1+$B12-1),dataMail!$H:$H,">"&(E$1+$B12-1)),"-") -> 5 | G12: =IF(DAY(EOMONTH(G$1,0))>=$B12,IFERROR(AVERAGEIFS(dataMail!$P:$P,dataMail!$C:$C,"Confirmation",dataMail!$G:$G,"<="&(G$1+$B12-1),dataMail!$H:$H,">"&(G$1+$B12-1)),"-"),"-") -> 109.736 | H12: =IF(DAY(EOMONTH(G$1,0))>=$B12, 11-COUNTIFS(dataMail!$C:$C,"<>Annulation",dataMail!$G:$G,"<="&(G$1+$B12-1),dataMail!$H:$H,">"&(G$1+$B12-1)),"-") -> 4 | I12: =IF(DAY(EOMONTH(I$1,0))>=$B12,IFERROR(AVERAGEIFS(dataMail!$P:$P,dataMail!$C:$C,"Confirmation",dataMail!$G:$G,"<="&(I$1+$B12-1),dataMail!$H:$H,">"&(I$1+$B12-1)),"-"),"-") -> 130.3198 | J12: =IF(DAY(EOMONTH(I$1,0))>=$B12, 11-COUNTIFS(dataMail!$C:$C,"<>Annulation",dataMail!$G:$G,"<="&(I$1+$B12-1),dataMail!$H:$H,">"&(I$1+$B12-1)),"-") -> 0 | K12: =IF(DAY(EOMONTH(K$1,0))>=$B12,IFERROR(AVERAGEIFS(dataMail!$P:$P,dataMail!$C:$C,"Confirmation",dataMail!$G:$G,"<="&(K$1+$B12-1),dataMail!$H:$H,">"&(K$1+$B12-1)),"-"),"-") -> 133.504 | L12: =IF(DAY(EOMONTH(K$1,0))>=$B12, 11-COUNTIFS(dataMail!$C:$C,"<>Annulation",dataMail!$G:$G,"<="&(K$1+$B12-1),dataMail!$H:$H,">"&(K$1+$B12-1)),"-") -> -2 | M12: =IF(DAY(EOMONTH(M$1,0))>=$B12,IFERROR(AVERAGEIFS(dataMail!$P:$P,dataMail!$C:$C,"Confirmation",dataMail!$G:$G,"<="&(M$1+$B12-1),dataMail!$H:$H,">"&(M$1+$B12-1)),"-"),"-") -> 148.30743 | N12: =IF(DAY(EOMONTH(M$1,0))>=$B12, 11-COUNTIFS(dataMail!$C:$C,"<>Annulation",dataMail!$G:$G,"<="&(M$1+$B12-1),dataMail!$H:$H,">"&(M$1+$B12-1)),"-") -> 4 | O12: =IF(DAY(EOMONTH(O$1,0))>=$B12,IFERROR(AVERAGEIFS(dataMail!$P:$P,dataMail!$C:$C,"Confirmation",dataMail!$G:$G,"<="&(O$1+$B12-1),dataMail!$H:$H,">"&(O$1+$B12-1)),"-"),"-") -> 206.768 | P12: =IF(DAY(EOMONTH(O$1,0))>=$B12, 11-COUNTIFS(dataMail!$C:$C,"<>Annulation",dataMail!$G:$G,"<="&(O$1+$B12-1),dataMail!$H:$H,">"&(O$1+$B12-1)),"-") -> 7 | Q12: =IF(DAY(EOMONTH(Q$1,0))>=$B12,IFERROR(AVERAGEIFS(dataMail!$P:$P,dataMail!$C:$C,"Confirmation",dataMail!$G:$G,"<="&(Q$1+$B12-1),dataMail!$H:$H,">"&(Q$1+$B12-1)),"-"),"-") -> 214.67437 | R12: =IF(DAY(EOMONTH(Q$1,0))>=$B12, 11-COUNTIFS(dataMail!$C:$C,"<>Annulation",dataMail!$G:$G,"<="&(Q$1+$B12-1),dataMail!$H:$H,">"&(Q$1+$B12-1)),"-") -> 7 | S12: =IF(DAY(EOMONTH(S$1,0))>=$B12,IFERROR(AVERAGEIFS(dataMail!$P:$P,dataMail!$C:$C,"Confirmation",dataMail!$G:$G,"<="&(S$1+$B12-1),dataMail!$H:$H,">"&(S$1+$B12-1)),"-"),"-") -> 120.576 | T12: =IF(DAY(EOMONTH(S$1,0))>=$B12, 11-COUNTIFS(dataMail!$C:$C,"<>Annulation",dataMail!$G:$G,"<="&(S$1+$B12-1),dataMail!$H:$H,">"&(S$1+$B12-1)),"-") -> 9 | U12: =IF(DAY(EOMONTH(U$1,0))>=$B12,IFERROR(AVERAGEIFS(dataMail!$P:$P,dataMail!$C:$C,"Confirmation",dataMail!$G:$G,"<="&(U$1+$B12-1),dataMail!$H:$H,">"&(U$1+$B12-1)),"-"),"-") -> - | V12: =IF(DAY(EOMONTH(U$1,0))>=$B12, 11-COUNTIFS(dataMail!$C:$C,"<>Annulation",dataMail!$G:$G,"<="&(U$1+$B12-1),dataMail!$H:$H,">"&(U$1+$B12-1)),"-") -> 11 | W12: =IF(DAY(EOMONTH(W$1,0))>=$B12,IFERROR(AVERAGEIFS(dataMail!$P:$P,dataMail!$C:$C,"Confirmation",dataMail!$G:$G,"<="&(W$1+$B12-1),dataMail!$H:$H,">"&(W$1+$B12-1)),"-"),"-") -> 167.2912 | X12: =IF(DAY(EOMONTH(W$1,0))>=$B12, 11-COUNTIFS(dataMail!$C:$C,"<>Annulation",dataMail!$G:$G,"<="&(W$1+$B12-1),dataMail!$H:$H,">"&(W$1+$B12-1)),"-") -> 8 | Y12: =IF(DAY(EOMONTH(Y$1,0))>=$B12,IFERROR(AVERAGEIFS(dataMail!$P:$P,dataMail!$C:$C,"Confirmation",dataMail!$G:$G,"<="&(Y$1+$B12-1),dataMail!$H:$H,">"&(Y$1+$B12-1)),"-"),"-") -> - | Z12: =IF(DAY(EOMONTH(Y$1,0))>=$B12, 11-COUNTIFS(dataMail!$C:$C,"<>Annulation",dataMail!$G:$G,"<="&(Y$1+$B12-1),dataMail!$H:$H,">"&(Y$1+$B12-1)),"-") -> 11 | AA12: =IF(DAY(EOMONTH(AA$1,0))>=$B12,IFERROR(AVERAGEIFS(dataMail!$P:$P,dataMail!$C:$C,"Confirmation",dataMail!$G:$G,"<="&(AA$1+$B12-1),dataMail!$H:$H,">"&(AA$1+$B12-1)),"-"),"-") -> - | AB12: =IF(DAY(EOMONTH(AA$1,0))>=$B12, 11-COUNTIFS(dataMail!$C:$C,"<>Annulation",dataMail!$G:$G,"<="&(AA$1+$B12-1),dataMail!$H:$H,">"&(AA$1+$B12-1)),"-") -> 11 | AC12: =IF(DAY(EOMONTH(AC$1,0))>=$B12,IFERROR(AVERAGEIFS(dataMail!$P:$P,dataMail!$C:$C,"Confirmation",dataMail!$G:$G,"<="&(AC$1+$B12-1),dataMail!$H:$H,">"&(AC$1+$B12-1)),"-"),"-") -> - | AD12: =IF(DAY(EOMONTH(AC$1,0))>=$B12, 11-COUNTIFS(dataMail!$C:$C,"<>Annulation",dataMail!$G:$G,"<="&(AC$1+$B12-1),dataMail!$H:$H,">"&(AC$1+$B12-1)),"-") -> 11 | AE12: =IF(DAY(EOMONTH(AE$1,0))>=$B12,IFERROR(AVERAGEIFS(dataMail!$P:$P,dataMail!$C:$C,"Confirmation",dataMail!$G:$G,"<="&(AE$1+$B12-1),dataMail!$H:$H,">"&(AE$1+$B12-1)),"-"),"-") -> - | AF12: =IF(DAY(EOMONTH(AE$1,0))>=$B12, 11-COUNTIFS(dataMail!$C:$C,"<>Annulation",dataMail!$G:$G,"<="&(AE$1+$B12-1),dataMail!$H:$H,">"&(AE$1+$B12-1)),"-") -> 11 | AG12: =IF(DAY(EOMONTH(AG$1,0))>=$B12,IFERROR(AVERAGEIFS(dataMail!$P:$P,dataMail!$C:$C,"Confirmation",dataMail!$G:$G,"<="&(AG$1+$B12-1),dataMail!$H:$H,">"&(AG$1+$B12-1)),"-"),"-") -> - | AH12: =IF(DAY(EOMONTH(AG$1,0))>=$B12, 11-COUNTIFS(dataMail!$C:$C,"<>Annulation",dataMail!$G:$G,"<="&(AG$1+$B12-1),dataMail!$H:$H,">"&(AG$1+$B12-1)),"-") -> 11
B13: 3 | C13: =IF(DAY(EOMONTH(C$1,0))>=$B13,IFERROR(AVERAGEIFS(dataMail!$P:$P,dataMail!$C:$C,"Confirmation",dataMail!$G:$G,"<="&(C$1+$B13-1),dataMail!$H:$H,">"&(C$1+$B13-1)),"-"),"-") -> 108.90238 | D13: =IF(DAY(EOMONTH(C$1,0))>=$B13, 11-COUNTIFS(dataMail!$C:$C,"<>Annulation",dataMail!$G:$G,"<="&(C$1+$B13-1),dataMail!$H:$H,">"&(C$1+$B13-1)),"-") -> 2 | E13: =IF(DAY(EOMONTH(E$1,0))>=$B13,IFERROR(AVERAGEIFS(dataMail!$P:$P,dataMail!$C:$C,"Confirmation",dataMail!$G:$G,"<="&(E$1+$B13-1),dataMail!$H:$H,">"&(E$1+$B13-1)),"-"),"-") -> 134.41493 | F13: =IF(DAY(EOMONTH(E$1,0))>=$B13, 11-COUNTIFS(dataMail!$C:$C,"<>Annulation",dataMail!$G:$G,"<="&(E$1+$B13-1),dataMail!$H:$H,">"&(E$1+$B13-1)),"-") -> 5 | G13: =IF(DAY(EOMONTH(G$1,0))>=$B13,IFERROR(AVERAGEIFS(dataMail!$P:$P,dataMail!$C:$C,"Confirmation",dataMail!$G:$G,"<="&(G$1+$B13-1),dataMail!$H:$H,">"&(G$1+$B13-1)),"-"),"-") -> 94.092571 | H13: =IF(DAY(EOMONTH(G$1,0))>=$B13, 11-COUNTIFS(dataMail!$C:$C,"<>Annulation",dataMail!$G:$G,"<="&(G$1+$B13-1),dataMail!$H:$H,">"&(G$1+$B13-1)),"-") -> 4 | I13: =IF(DAY(EOMONTH(I$1,0))>=$B13,IFERROR(AVERAGEIFS(dataMail!$P:$P,dataMail!$C:$C,"Confirmation",dataMail!$G:$G,"<="&(I$1+$B13-1),dataMail!$H:$H,">"&(I$1+$B13-1)),"-"),"-") -> 109.50275 | J13: =IF(DAY(EOMONTH(I$1,0))>=$B13, 11-COUNTIFS(dataMail!$C:$C,"<>Annulation",dataMail!$G:$G,"<="&(I$1+$B13-1),dataMail!$H:$H,">"&(I$1+$B13-1)),"-") -> 2 | K13: =IF(DAY(EOMONTH(K$1,0))>=$B13,IFERROR(AVERAGEIFS(dataMail!$P:$P,dataMail!$C:$C,"Confirmation",dataMail!$G:$G,"<="&(K$1+$B13-1),dataMail!$H:$H,">"&(K$1+$B13-1)),"-"),"-") -> 130.01867 | L13: =IF(DAY(EOMONTH(K$1,0))>=$B13, 11-COUNTIFS(dataMail!$C:$C,"<>Annulation",dataMail!$G:$G,"<="&(K$1+$B13-1),dataMail!$H:$H,">"&(K$1+$B13-1)),"-") -> 4 | M13: =IF(DAY(EOMONTH(M$1,0))>=$B13,IFERROR(AVERAGEIFS(dataMail!$P:$P,dataMail!$C:$C,"Confirmation",dataMail!$G:$G,"<="&(M$1+$B13-1),dataMail!$H:$H,">"&(M$1+$B13-1)),"-"),"-") -> 156.10514 | N13: =IF(DAY(EOMONTH(M$1,0))>=$B13, 11-COUNTIFS(dataMail!$C:$C,"<>Annulation",dataMail!$G:$G,"<="&(M$1+$B13-1),dataMail!$H:$H,">"&(M$1+$B13-1)),"-") -> 3 | O13: =IF(DAY(EOMONTH(O$1,0))>=$B13,IFERROR(AVERAGEIFS(dataMail!$P:$P,dataMail!$C:$C,"Confirmation",dataMail!$G:$G,"<="&(O$1+$B13-1),dataMail!$H:$H,">"&(O$1+$B13-1)),"-"),"-") -> 206.768 | P13: =IF(DAY(EOMONTH(O$1,0))>=$B13, 11-COUNTIFS(dataMail!$C:$C,"<>Annulation",dataMail!$G:$G,"<="&(O$1+$B13-1),dataMail!$H:$H,">"&(O$1+$B13-1)),"-") -> 7 | Q13: =IF(DAY(EOMONTH(Q$1,0))>=$B13,IFERROR(AVERAGEIFS(dataMail!$P:$P,dataMail!$C:$C,"Confirmation",dataMail!$G:$G,"<="&(Q$1+$B13-1),dataMail!$H:$H,">"&(Q$1+$B13-1)),"-"),"-") -> 187.168 | R13: =IF(DAY(EOMONTH(Q$1,0))>=$B13, 11-COUNTIFS(dataMail!$C:$C,"<>Annulation",dataMail!$G:$G,"<="&(Q$1+$B13-1),dataMail!$H:$H,">"&(Q$1+$B13-1)),"-") -> 6 | S13: =IF(DAY(EOMONTH(S$1,0))>=$B13,IFERROR(AVERAGEIFS(dataMail!$P:$P,dataMail!$C:$C,"Confirmation",dataMail!$G:$G,"<="&(S$1+$B13-1),dataMail!$H:$H,">"&(S$1+$B13-1)),"-"),"-") -> - | T13: =IF(DAY(EOMONTH(S$1,0))>=$B13, 11-COUNTIFS(dataMail!$C:$C,"<>Annulation",dataMail!$G:$G,"<="&(S$1+$B13-1),dataMail!$H:$H,">"&(S$1+$B13-1)),"-") -> 10 | U13: =IF(DAY(EOMONTH(U$1,0))>=$B13,IFERROR(AVERAGEIFS(dataMail!$P:$P,dataMail!$C:$C,"Confirmation",dataMail!$G:$G,"<="&(U$1+$B13-1),dataMail!$H:$H,">"&(U$1+$B13-1)),"-"),"-") -> - | V13: =IF(DAY(EOMONTH(U$1,0))>=$B13, 11-COUNTIFS(dataMail!$C:$C,"<>Annulation",dataMail!$G:$G,"<="&(U$1+$B13-1),dataMail!$H:$H,">"&(U$1+$B13-1)),"-") -> 11 | W13: =IF(DAY(EOMONTH(W$1,0))>=$B13,IFERROR(AVERAGEIFS(dataMail!$P:$P,dataMail!$C:$C,"Confirmation",dataMail!$G:$G,"<="&(W$1+$B13-1),dataMail!$H:$H,">"&(W$1+$B13-1)),"-"),"-") -> 146.868 | X13: =IF(DAY(EOMONTH(W$1,0))>=$B13, 11-COUNTIFS(dataMail!$C:$C,"<>Annulation",dataMail!$G:$G,"<="&(W$1+$B13-1),dataMail!$H:$H,">"&(W$1+$B13-1)),"-") -> 9 | Y13: =IF(DAY(EOMONTH(Y$1,0))>=$B13,IFERROR(AVERAGEIFS(dataMail!$P:$P,dataMail!$C:$C,"Confirmation",dataMail!$G:$G,"<="&(Y$1+$B13-1),dataMail!$H:$H,">"&(Y$1+$B13-1)),"-"),"-") -> - | Z13: =IF(DAY(EOMONTH(Y$1,0))>=$B13, 11-COUNTIFS(dataMail!$C:$C,"<>Annulation",dataMail!$G:$G,"<="&(Y$1+$B13-1),dataMail!$H:$H,">"&(Y$1+$B13-1)),"-") -> 11 | AA13: =IF(DAY(EOMONTH(AA$1,0))>=$B13,IFERROR(AVERAGEIFS(dataMail!$P:$P,dataMail!$C:$C,"Confirmation",dataMail!$G:$G,"<="&(AA$1+$B13-1),dataMail!$H:$H,">"&(AA$1+$B13-1)),"-"),"-") -> 94.8 | AB13: =IF(DAY(EOMONTH(AA$1,0))>=$B13, 11-COUNTIFS(dataMail!$C:$C,"<>Annulation",dataMail!$G:$G,"<="&(AA$1+$B13-1),dataMail!$H:$H,">"&(AA$1+$B13-1)),"-") -> 9 | AC13: =IF(DAY(EOMONTH(AC$1,0))>=$B13,IFERROR(AVERAGEIFS(dataMail!$P:$P,dataMail!$C:$C,"Confirmation",dataMail!$G:$G,"<="&(AC$1+$B13-1),dataMail!$H:$H,">"&(AC$1+$B13-1)),"-"),"-") -> - | AD13: =IF(DAY(EOMONTH(AC$1,0))>=$B13, 11-COUNTIFS(dataMail!$C:$C,"<>Annulation",dataMail!$G:$G,"<="&(AC$1+$B13-1),dataMail!$H:$H,">"&(AC$1+$B13-1)),"-") -> 11 | AE13: =IF(DAY(EOMONTH(AE$1,0))>=$B13,IFERROR(AVERAGEIFS(dataMail!$P:$P,dataMail!$C:$C,"Confirmation",dataMail!$G:$G,"<="&(AE$1+$B13-1),dataMail!$H:$H,">"&(AE$1+$B13-1)),"-"),"-") -> - | AF13: =IF(DAY(EOMONTH(AE$1,0))>=$B13, 11-COUNTIFS(dataMail!$C:$C,"<>Annulation",dataMail!$G:$G,"<="&(AE$1+$B13-1),dataMail!$H:$H,">"&(AE$1+$B13-1)),"-") -> 11 | AG13: =IF(DAY(EOMONTH(AG$1,0))>=$B13,IFERROR(AVERAGEIFS(dataMail!$P:$P,dataMail!$C:$C,"Confirmation",dataMail!$G:$G,"<="&(AG$1+$B13-1),dataMail!$H:$H,">"&(AG$1+$B13-1)),"-"),"-") -> - | AH13: =IF(DAY(EOMONTH(AG$1,0))>=$B13, 11-COUNTIFS(dataMail!$C:$C,"<>Annulation",dataMail!$G:$G,"<="&(AG$1+$B13-1),dataMail!$H:$H,">"&(AG$1+$B13-1)),"-") -> 11
B14: 4 | C14: =IF(DAY(EOMONTH(C$1,0))>=$B14,IFERROR(AVERAGEIFS(dataMail!$P:$P,dataMail!$C:$C,"Confirmation",dataMail!$G:$G,"<="&(C$1+$B14-1),dataMail!$H:$H,">"&(C$1+$B14-1)),"-"),"-") -> 103.50192 | D14: =IF(DAY(EOMONTH(C$1,0))>=$B14, 11-COUNTIFS(dataMail!$C:$C,"<>Annulation",dataMail!$G:$G,"<="&(C$1+$B14-1),dataMail!$H:$H,">"&(C$1+$B14-1)),"-") -> 4 | E14: =IF(DAY(EOMONTH(E$1,0))>=$B14,IFERROR(AVERAGEIFS(dataMail!$P:$P,dataMail!$C:$C,"Confirmation",dataMail!$G:$G,"<="&(E$1+$B14-1),dataMail!$H:$H,">"&(E$1+$B14-1)),"-"),"-") -> 139.0968 | F14: =IF(DAY(EOMONTH(E$1,0))>=$B14, 11-COUNTIFS(dataMail!$C:$C,"<>Annulation",dataMail!$G:$G,"<="&(E$1+$B14-1),dataMail!$H:$H,">"&(E$1+$B14-1)),"-") -> 1 | G14: =IF(DAY(EOMONTH(G$1,0))>=$B14,IFERROR(AVERAGEIFS(dataMail!$P:$P,dataMail!$C:$C,"Confirmation",dataMail!$G:$G,"<="&(G$1+$B14-1),dataMail!$H:$H,">"&(G$1+$B14-1)),"-"),"-") -> 93.4936 | H14: =IF(DAY(EOMONTH(G$1,0))>=$B14, 11-COUNTIFS(dataMail!$C:$C,"<>Annulation",dataMail!$G:$G,"<="&(G$1+$B14-1),dataMail!$H:$H,">"&(G$1+$B14-1)),"-") -> 1 | I14: =IF(DAY(EOMONTH(I$1,0))>=$B14,IFERROR(AVERAGEIFS(dataMail!$P:$P,dataMail!$C:$C,"Confirmation",dataMail!$G:$G,"<="&(I$1+$B14-1),dataMail!$H:$H,">"&(I$1+$B14-1)),"-"),"-") -> 124.812 | J14: =IF(DAY(EOMONTH(I$1,0))>=$B14, 11-COUNTIFS(dataMail!$C:$C,"<>Annulation",dataMail!$G:$G,"<="&(I$1+$B14-1),dataMail!$H:$H,">"&(I$1+$B14-1)),"-") -> 7 | K14: =IF(DAY(EOMONTH(K$1,0))>=$B14,IFERROR(AVERAGEIFS(dataMail!$P:$P,dataMail!$C:$C,"Confirmation",dataMail!$G:$G,"<="&(K$1+$B14-1),dataMail!$H:$H,">"&(K$1+$B14-1)),"-"),"-") -> 135.06795 | L14: =IF(DAY(EOMONTH(K$1,0))>=$B14, 11-COUNTIFS(dataMail!$C:$C,"<>Annulation",dataMail!$G:$G,"<="&(K$1+$B14-1),dataMail!$H:$H,">"&(K$1+$B14-1)),"-") -> -1 | M14: =IF(DAY(EOMONTH(M$1,0))>=$B14,IFERROR(AVERAGEIFS(dataMail!$P:$P,dataMail!$C:$C,"Confirmation",dataMail!$G:$G,"<="&(M$1+$B14-1),dataMail!$H:$H,">"&(M$1+$B14-1)),"-"),"-") -> 165.344 | N14: =IF(DAY(EOMONTH(M$1,0))>=$B14, 11-COUNTIFS(dataMail!$C:$C,"<>Annulation",dataMail!$G:$G,"<="&(M$1+$B14-1),dataMail!$H:$H,">"&(M$1+$B14-1)),"-") -> 4 | O14: =IF(DAY(EOMONTH(O$1,0))>=$B14,IFERROR(AVERAGEIFS(dataMail!$P:$P,dataMail!$C:$C,"Confirmation",dataMail!$G:$G,"<="&(O$1+$B14-1),dataMail!$H:$H,">"&(O$1+$B14-1)),"-"),"-") -> 266.796 | P14: =IF(DAY(EOMONTH(O$1,0))>=$B14, 11-COUNTIFS(dataMail!$C:$C,"<>Annulation",dataMail!$G:$G,"<="&(O$1+$B14-1),dataMail!$H:$H,">"&(O$1+$B14-1)),"-") -> 9 | Q14: =IF(DAY(EOMONTH(Q$1,0))>=$B14,IFERROR(AVERAGEIFS(dataMail!$P:$P,dataMail!$C:$C,"Confirmation",dataMail!$G:$G,"<="&(Q$1+$B14-1),dataMail!$H:$H,">"&(Q$1+$B14-1)),"-"),"-") -> 229.28 | R14: =IF(DAY(EOMONTH(Q$1,0))>=$B14, 11-COUNTIFS(dataMail!$C:$C,"<>Annulation",dataMail!$G:$G,"<="&(Q$1+$B14-1),dataMail!$H:$H,">"&(Q$1+$B14-1)),"-") -> 0 | S14: =IF(DAY(EOMONTH(S$1,0))>=$B14,IFERROR(AVERAGEIFS(dataMail!$P:$P,dataMail!$C:$C,"Confirmation",dataMail!$G:$G,"<="&(S$1+$B14-1),dataMail!$H:$H,">"&(S$1+$B14-1)),"-"),"-") -> - | T14: =IF(DAY(EOMONTH(S$1,0))>=$B14, 11-COUNTIFS(dataMail!$C:$C,"<>Annulation",dataMail!$G:$G,"<="&(S$1+$B14-1),dataMail!$H:$H,">"&(S$1+$B14-1)),"-") -> 10 | U14: =IF(DAY(EOMONTH(U$1,0))>=$B14,IFERROR(AVERAGEIFS(dataMail!$P:$P,dataMail!$C:$C,"Confirmation",dataMail!$G:$G,"<="&(U$1+$B14-1),dataMail!$H:$H,">"&(U$1+$B14-1)),"-"),"-") -> 147.096 | V14: =IF(DAY(EOMONTH(U$1,0))>=$B14, 11-COUNTIFS(dataMail!$C:$C,"<>Annulation",dataMail!$G:$G,"<="&(U$1+$B14-1),dataMail!$H:$H,">"&(U$1+$B14-1)),"-") -> 10 | W14: =IF(DAY(EOMONTH(W$1,0))>=$B14,IFERROR(AVERAGEIFS(dataMail!$P:$P,dataMail!$C:$C,"Confirmation",dataMail!$G:$G,"<="&(W$1+$B14-1),dataMail!$H:$H,">"&(W$1+$B14-1)),"-"),"-") -> - | X14: =IF(DAY(EOMONTH(W$1,0))>=$B14, 11-COUNTIFS(dataMail!$C:$C,"<>Annulation",dataMail!$G:$G,"<="&(W$1+$B14-1),dataMail!$H:$H,">"&(W$1+$B14-1)),"-") -> 11 | Y14: =IF(DAY(EOMONTH(Y$1,0))>=$B14,IFERROR(AVERAGEIFS(dataMail!$P:$P,dataMail!$C:$C,"Confirmation",dataMail!$G:$G,"<="&(Y$1+$B14-1),dataMail!$H:$H,">"&(Y$1+$B14-1)),"-"),"-") -> 199.392 | Z14: =IF(DAY(EOMONTH(Y$1,0))>=$B14, 11-COUNTIFS(dataMail!$C:$C,"<>Annulation",dataMail!$G:$G,"<="&(Y$1+$B14-1),dataMail!$H:$H,">"&(Y$1+$B14-1)),"-") -> 9 | AA14: =IF(DAY(EOMONTH(AA$1,0))>=$B14,IFERROR(AVERAGEIFS(dataMail!$P:$P,dataMail!$C:$C,"Confirmation",dataMail!$G:$G,"<="&(AA$1+$B14-1),dataMail!$H:$H,">"&(AA$1+$B14-1)),"-"),"-") -> 94.8 | AB14: =IF(DAY(EOMONTH(AA$1,0))>=$B14, 11-COUNTIFS(dataMail!$C:$C,"<>Annulation",dataMail!$G:$G,"<="&(AA$1+$B14-1),dataMail!$H:$H,">"&(AA$1+$B14-1)),"-") -> 9 | AC14: =IF(DAY(EOMONTH(AC$1,0))>=$B14,IFERROR(AVERAGEIFS(dataMail!$P:$P,dataMail!$C:$C,"Confirmation",dataMail!$G:$G,"<="&(AC$1+$B14-1),dataMail!$H:$H,">"&(AC$1+$B14-1)),"-"),"-") -> - | AD14: =IF(DAY(EOMONTH(AC$1,0))>=$B14, 11-COUNTIFS(dataMail!$C:$C,"<>Annulation",dataMail!$G:$G,"<="&(AC$1+$B14-1),dataMail!$H:$H,">"&(AC$1+$B14-1)),"-") -> 11 | AE14: =IF(DAY(EOMONTH(AE$1,0))>=$B14,IFERROR(AVERAGEIFS(dataMail!$P:$P,dataMail!$C:$C,"Confirmation",dataMail!$G:$G,"<="&(AE$1+$B14-1),dataMail!$H:$H,">"&(AE$1+$B14-1)),"-"),"-") -> 94.624 | AF14: =IF(DAY(EOMONTH(AE$1,0))>=$B14, 11-COUNTIFS(dataMail!$C:$C,"<>Annulation",dataMail!$G:$G,"<="&(AE$1+$B14-1),dataMail!$H:$H,">"&(AE$1+$B14-1)),"-") -> 10 | AG14: =IF(DAY(EOMONTH(AG$1,0))>=$B14,IFERROR(AVERAGEIFS(dataMail!$P:$P,dataMail!$C:$C,"Confirmation",dataMail!$G:$G,"<="&(AG$1+$B14-1),dataMail!$H:$H,">"&(AG$1+$B14-1)),"-"),"-") -> - | AH14: =IF(DAY(EOMONTH(AG$1,0))>=$B14, 11-COUNTIFS(dataMail!$C:$C,"<>Annulation",dataMail!$G:$G,"<="&(AG$1+$B14-1),dataMail!$H:$H,">"&(AG$1+$B14-1)),"-") -> 11
B15: 5 | C15: =IF(DAY(EOMONTH(C$1,0))>=$B15,IFERROR(AVERAGEIFS(dataMail!$P:$P,dataMail!$C:$C,"Confirmation",dataMail!$G:$G,"<="&(C$1+$B15-1),dataMail!$H:$H,">"&(C$1+$B15-1)),"-"),"-") -> 131.9574 | D15: =IF(DAY(EOMONTH(C$1,0))>=$B15, 11-COUNTIFS(dataMail!$C:$C,"<>Annulation",dataMail!$G:$G,"<="&(C$1+$B15-1),dataMail!$H:$H,">"&(C$1+$B15-1)),"-") -> 0 | E15: =IF(DAY(EOMONTH(E$1,0))>=$B15,IFERROR(AVERAGEIFS(dataMail!$P:$P,dataMail!$C:$C,"Confirmation",dataMail!$G:$G,"<="&(E$1+$B15-1),dataMail!$H:$H,">"&(E$1+$B15-1)),"-"),"-") -> 142.60711 | F15: =IF(DAY(EOMONTH(E$1,0))>=$B15, 11-COUNTIFS(dataMail!$C:$C,"<>Annulation",dataMail!$G:$G,"<="&(E$1+$B15-1),dataMail!$H:$H,">"&(E$1+$B15-1)),"-") -> 2 | G15: =IF(DAY(EOMONTH(G$1,0))>=$B15,IFERROR(AVERAGEIFS(dataMail!$P:$P,dataMail!$C:$C,"Confirmation",dataMail!$G:$G,"<="&(G$1+$B15-1),dataMail!$H:$H,">"&(G$1+$B15-1)),"-"),"-") -> 100.8728 | H15: =IF(DAY(EOMONTH(G$1,0))>=$B15, 11-COUNTIFS(dataMail!$C:$C,"<>Annulation",dataMail!$G:$G,"<="&(G$1+$B15-1),dataMail!$H:$H,">"&(G$1+$B15-1)),"-") -> 1 | I15: =IF(DAY(EOMONTH(I$1,0))>=$B15,IFERROR(AVERAGEIFS(dataMail!$P:$P,dataMail!$C:$C,"Confirmation",dataMail!$G:$G,"<="&(I$1+$B15-1),dataMail!$H:$H,">"&(I$1+$B15-1)),"-"),"-") -> 120.13829 | J15: =IF(DAY(EOMONTH(I$1,0))>=$B15, 11-COUNTIFS(dataMail!$C:$C,"<>Annulation",dataMail!$G:$G,"<="&(I$1+$B15-1),dataMail!$H:$H,">"&(I$1+$B15-1)),"-") -> 2 | K15: =IF(DAY(EOMONTH(K$1,0))>=$B15,IFERROR(AVERAGEIFS(dataMail!$P:$P,dataMail!$C:$C,"Confirmation",dataMail!$G:$G,"<="&(K$1+$B15-1),dataMail!$H:$H,">"&(K$1+$B15-1)),"-"),"-") -> 124.248 | L15: =IF(DAY(EOMONTH(K$1,0))>=$B15, 11-COUNTIFS(dataMail!$C:$C,"<>Annulation",dataMail!$G:$G,"<="&(K$1+$B15-1),dataMail!$H:$H,">"&(K$1+$B15-1)),"-") -> 6 | M15: =IF(DAY(EOMONTH(M$1,0))>=$B15,IFERROR(AVERAGEIFS(dataMail!$P:$P,dataMail!$C:$C,"Confirmation",dataMail!$G:$G,"<="&(M$1+$B15-1),dataMail!$H:$H,">"&(M$1+$B15-1)),"-"),"-") -> 150.97143 | N15: =IF(DAY(EOMONTH(M$1,0))>=$B15, 11-COUNTIFS(dataMail!$C:$C,"<>Annulation",dataMail!$G:$G,"<="&(M$1+$B15-1),dataMail!$H:$H,">"&(M$1+$B15-1)),"-") -> 3 | O15: =IF(DAY(EOMONTH(O$1,0))>=$B15,IFERROR(AVERAGEIFS(dataMail!$P:$P,dataMail!$C:$C,"Confirmation",dataMail!$G:$G,"<="&(O$1+$B15-1),dataMail!$H:$H,">"&(O$1+$B15-1)),"-"),"-") -> 133.84 | P15: =IF(DAY(EOMONTH(O$1,0))>=$B15, 11-COUNTIFS(dataMail!$C:$C,"<>Annulation",dataMail!$G:$G,"<="&(O$1+$B15-1),dataMail!$H:$H,">"&(O$1+$B15-1)),"-") -> 10 | Q15: =IF(DAY(EOMONTH(Q$1,0))>=$B15,IFERROR(AVERAGEIFS(dataMail!$P:$P,dataMail!$C:$C,"Confirmation",dataMail!$G:$G,"<="&(Q$1+$B15-1),dataMail!$H:$H,">"&(Q$1+$B15-1)),"-"),"-") -> 228.706 | R15: =IF(DAY(EOMONTH(Q$1,0))>=$B15, 11-COUNTIFS(dataMail!$C:$C,"<>Annulation",dataMail!$G:$G,"<="&(Q$1+$B15-1),dataMail!$H:$H,">"&(Q$1+$B15-1)),"-") -> -1 | S15: =IF(DAY(EOMONTH(S$1,0))>=$B15,IFERROR(AVERAGEIFS(dataMail!$P:$P,dataMail!$C:$C,"Confirmation",dataMail!$G:$G,"<="&(S$1+$B15-1),dataMail!$H:$H,">"&(S$1+$B15-1)),"-"),"-") -> - | T15: =IF(DAY(EOMONTH(S$1,0))>=$B15, 11-COUNTIFS(dataMail!$C:$C,"<>Annulation",dataMail!$G:$G,"<="&(S$1+$B15-1),dataMail!$H:$H,">"&(S$1+$B15-1)),"-") -> 10 | U15: =IF(DAY(EOMONTH(U$1,0))>=$B15,IFERROR(AVERAGEIFS(dataMail!$P:$P,dataMail!$C:$C,"Confirmation",dataMail!$G:$G,"<="&(U$1+$B15-1),dataMail!$H:$H,">"&(U$1+$B15-1)),"-"),"-") -> 147.096 | V15: =IF(DAY(EOMONTH(U$1,0))>=$B15, 11-COUNTIFS(dataMail!$C:$C,"<>Annulation",dataMail!$G:$G,"<="&(U$1+$B15-1),dataMail!$H:$H,">"&(U$1+$B15-1)),"-") -> 10 | W15: =IF(DAY(EOMONTH(W$1,0))>=$B15,IFERROR(AVERAGEIFS(dataMail!$P:$P,dataMail!$C:$C,"Confirmation",dataMail!$G:$G,"<="&(W$1+$B15-1),dataMail!$H:$H,">"&(W$1+$B15-1)),"-"),"-") -> - | X15: =IF(DAY(EOMONTH(W$1,0))>=$B15, 11-COUNTIFS(dataMail!$C:$C,"<>Annulation",dataMail!$G:$G,"<="&(W$1+$B15-1),dataMail!$H:$H,">"&(W$1+$B15-1)),"-") -> 11 | Y15: =IF(DAY(EOMONTH(Y$1,0))>=$B15,IFERROR(AVERAGEIFS(dataMail!$P:$P,dataMail!$C:$C,"Confirmation",dataMail!$G:$G,"<="&(Y$1+$B15-1),dataMail!$H:$H,">"&(Y$1+$B15-1)),"-"),"-") -> - | Z15: =IF(DAY(EOMONTH(Y$1,0))>=$B15, 11-COUNTIFS(dataMail!$C:$C,"<>Annulation",dataMail!$G:$G,"<="&(Y$1+$B15-1),dataMail!$H:$H,">"&(Y$1+$B15-1)),"-") -> 11 | AA15: =IF(DAY(EOMONTH(AA$1,0))>=$B15,IFERROR(AVERAGEIFS(dataMail!$P:$P,dataMail!$C:$C,"Confirmation",dataMail!$G:$G,"<="&(AA$1+$B15-1),dataMail!$H:$H,">"&(AA$1+$B15-1)),"-"),"-") -> 94.8 | AB15: =IF(DAY(EOMONTH(AA$1,0))>=$B15, 11-COUNTIFS(dataMail!$C:$C,"<>Annulation",dataMail!$G:$G,"<="&(AA$1+$B15-1),dataMail!$H:$H,">"&(AA$1+$B15-1)),"-") -> 9 | AC15: =IF(DAY(EOMONTH(AC$1,0))>=$B15,IFERROR(AVERAGEIFS(dataMail!$P:$P,dataMail!$C:$C,"Confirmation",dataMail!$G:$G,"<="&(AC$1+$B15-1),dataMail!$H:$H,">"&(AC$1+$B15-1)),"-"),"-") -> - | AD15: =IF(DAY(EOMONTH(AC$1,0))>=$B15, 11-COUNTIFS(dataMail!$C:$C,"<>Annulation",dataMail!$G:$G,"<="&(AC$1+$B15-1),dataMail!$H:$H,">"&(AC$1+$B15-1)),"-") -> 11 | AE15: =IF(DAY(EOMONTH(AE$1,0))>=$B15,IFERROR(AVERAGEIFS(dataMail!$P:$P,dataMail!$C:$C,"Confirmation",dataMail!$G:$G,"<="&(AE$1+$B15-1),dataMail!$H:$H,">"&(AE$1+$B15-1)),"-"),"-") -> 94.624 | AF15: =IF(DAY(EOMONTH(AE$1,0))>=$B15, 11-COUNTIFS(dataMail!$C:$C,"<>Annulation",dataMail!$G:$G,"<="&(AE$1+$B15-1),dataMail!$H:$H,">"&(AE$1+$B15-1)),"-") -> 10 | AG15: =IF(DAY(EOMONTH(AG$1,0))>=$B15,IFERROR(AVERAGEIFS(dataMail!$P:$P,dataMail!$C:$C,"Confirmation",dataMail!$G:$G,"<="&(AG$1+$B15-1),dataMail!$H:$H,">"&(AG$1+$B15-1)),"-"),"-") -> - | AH15: =IF(DAY(EOMONTH(AG$1,0))>=$B15, 11-COUNTIFS(dataMail!$C:$C,"<>Annulation",dataMail!$G:$G,"<="&(AG$1+$B15-1),dataMail!$H:$H,">"&(AG$1+$B15-1)),"-") -> 11
B16: 6 | C16: =IF(DAY(EOMONTH(C$1,0))>=$B16,IFERROR(AVERAGEIFS(dataMail!$P:$P,dataMail!$C:$C,"Confirmation",dataMail!$G:$G,"<="&(C$1+$B16-1),dataMail!$H:$H,">"&(C$1+$B16-1)),"-"),"-") -> 125.4208 | D16: =IF(DAY(EOMONTH(C$1,0))>=$B16, 11-COUNTIFS(dataMail!$C:$C,"<>Annulation",dataMail!$G:$G,"<="&(C$1+$B16-1),dataMail!$H:$H,">"&(C$1+$B16-1)),"-") -> 1 | E16: =IF(DAY(EOMONTH(E$1,0))>=$B16,IFERROR(AVERAGEIFS(dataMail!$P:$P,dataMail!$C:$C,"Confirmation",dataMail!$G:$G,"<="&(E$1+$B16-1),dataMail!$H:$H,">"&(E$1+$B16-1)),"-"),"-") -> 152.404 | F16: =IF(DAY(EOMONTH(E$1,0))>=$B16, 11-COUNTIFS(dataMail!$C:$C,"<>Annulation",dataMail!$G:$G,"<="&(E$1+$B16-1),dataMail!$H:$H,">"&(E$1+$B16-1)),"-") -> 3 | G16: =IF(DAY(EOMONTH(G$1,0))>=$B16,IFERROR(AVERAGEIFS(dataMail!$P:$P,dataMail!$C:$C,"Confirmation",dataMail!$G:$G,"<="&(G$1+$B16-1),dataMail!$H:$H,">"&(G$1+$B16-1)),"-"),"-") -> 104.03467 | H16: =IF(DAY(EOMONTH(G$1,0))>=$B16, 11-COUNTIFS(dataMail!$C:$C,"<>Annulation",dataMail!$G:$G,"<="&(G$1+$B16-1),dataMail!$H:$H,">"&(G$1+$B16-1)),"-") -> 2 | I16: =IF(DAY(EOMONTH(I$1,0))>=$B16,IFERROR(AVERAGEIFS(dataMail!$P:$P,dataMail!$C:$C,"Confirmation",dataMail!$G:$G,"<="&(I$1+$B16-1),dataMail!$H:$H,">"&(I$1+$B16-1)),"-"),"-") -> 125.304 | J16: =IF(DAY(EOMONTH(I$1,0))>=$B16, 11-COUNTIFS(dataMail!$C:$C,"<>Annulation",dataMail!$G:$G,"<="&(I$1+$B16-1),dataMail!$H:$H,">"&(I$1+$B16-1)),"-") -> 1 | K16: =IF(DAY(EOMONTH(K$1,0))>=$B16,IFERROR(AVERAGEIFS(dataMail!$P:$P,dataMail!$C:$C,"Confirmation",dataMail!$G:$G,"<="&(K$1+$B16-1),dataMail!$H:$H,">"&(K$1+$B16-1)),"-"),"-") -> 187.4096 | L16: =IF(DAY(EOMONTH(K$1,0))>=$B16, 11-COUNTIFS(dataMail!$C:$C,"<>Annulation",dataMail!$G:$G,"<="&(K$1+$B16-1),dataMail!$H:$H,">"&(K$1+$B16-1)),"-") -> 6 | M16: =IF(DAY(EOMONTH(M$1,0))>=$B16,IFERROR(AVERAGEIFS(dataMail!$P:$P,dataMail!$C:$C,"Confirmation",dataMail!$G:$G,"<="&(M$1+$B16-1),dataMail!$H:$H,">"&(M$1+$B16-1)),"-"),"-") -> 208.27491 | N16: =IF(DAY(EOMONTH(M$1,0))>=$B16, 11-COUNTIFS(dataMail!$C:$C,"<>Annulation",dataMail!$G:$G,"<="&(M$1+$B16-1),dataMail!$H:$H,">"&(M$1+$B16-1)),"-") -> 0 | O16: =IF(DAY(EOMONTH(O$1,0))>=$B16,IFERROR(AVERAGEIFS(dataMail!$P:$P,dataMail!$C:$C,"Confirmation",dataMail!$G:$G,"<="&(O$1+$B16-1),dataMail!$H:$H,">"&(O$1+$B16-1)),"-"),"-") -> - | P16: =IF(DAY(EOMONTH(O$1,0))>=$B16, 11-COUNTIFS(dataMail!$C:$C,"<>Annulation",dataMail!$G:$G,"<="&(O$1+$B16-1),dataMail!$H:$H,">"&(O$1+$B16-1)),"-") -> 11 | Q16: =IF(DAY(EOMONTH(Q$1,0))>=$B16,IFERROR(AVERAGEIFS(dataMail!$P:$P,dataMail!$C:$C,"Confirmation",dataMail!$G:$G,"<="&(Q$1+$B16-1),dataMail!$H:$H,">"&(Q$1+$B16-1)),"-"),"-") -> 234.71709 | R16: =IF(DAY(EOMONTH(Q$1,0))>=$B16, 11-COUNTIFS(dataMail!$C:$C,"<>Annulation",dataMail!$G:$G,"<="&(Q$1+$B16-1),dataMail!$H:$H,">"&(Q$1+$B16-1)),"-") -> 0 | S16: =IF(DAY(EOMONTH(S$1,0))>=$B16,IFERROR(AVERAGEIFS(dataMail!$P:$P,dataMail!$C:$C,"Confirmation",dataMail!$G:$G,"<="&(S$1+$B16-1),dataMail!$H:$H,">"&(S$1+$B16-1)),"-"),"-") -> - | T16: =IF(DAY(EOMONTH(S$1,0))>=$B16, 11-COUNTIFS(dataMail!$C:$C,"<>Annulation",dataMail!$G:$G,"<="&(S$1+$B16-1),dataMail!$H:$H,">"&(S$1+$B16-1)),"-") -> 10 | U16: =IF(DAY(EOMONTH(U$1,0))>=$B16,IFERROR(AVERAGEIFS(dataMail!$P:$P,dataMail!$C:$C,"Confirmation",dataMail!$G:$G,"<="&(U$1+$B16-1),dataMail!$H:$H,">"&(U$1+$B16-1)),"-"),"-") -> 147.096 | V16: =IF(DAY(EOMONTH(U$1,0))>=$B16, 11-COUNTIFS(dataMail!$C:$C,"<>Annulation",dataMail!$G:$G,"<="&(U$1+$B16-1),dataMail!$H:$H,">"&(U$1+$B16-1)),"-") -> 10 | W16: =IF(DAY(EOMONTH(W$1,0))>=$B16,IFERROR(AVERAGEIFS(dataMail!$P:$P,dataMail!$C:$C,"Confirmation",dataMail!$G:$G,"<="&(W$1+$B16-1),dataMail!$H:$H,">"&(W$1+$B16-1)),"-"),"-") -> - | X16: =IF(DAY(EOMONTH(W$1,0))>=$B16, 11-COUNTIFS(dataMail!$C:$C,"<>Annulation",dataMail!$G:$G,"<="&(W$1+$B16-1),dataMail!$H:$H,">"&(W$1+$B16-1)),"-") -> 11 | Y16: =IF(DAY(EOMONTH(Y$1,0))>=$B16,IFERROR(AVERAGEIFS(dataMail!$P:$P,dataMail!$C:$C,"Confirmation",dataMail!$G:$G,"<="&(Y$1+$B16-1),dataMail!$H:$H,">"&(Y$1+$B16-1)),"-"),"-") -> 142.384 | Z16: =IF(DAY(EOMONTH(Y$1,0))>=$B16, 11-COUNTIFS(dataMail!$C:$C,"<>Annulation",dataMail!$G:$G,"<="&(Y$1+$B16-1),dataMail!$H:$H,">"&(Y$1+$B16-1)),"-") -> 9 | AA16: =IF(DAY(EOMONTH(AA$1,0))>=$B16,IFERROR(AVERAGEIFS(dataMail!$P:$P,dataMail!$C:$C,"Confirmation",dataMail!$G:$G,"<="&(AA$1+$B16-1),dataMail!$H:$H,">"&(AA$1+$B16-1)),"-"),"-") -> 94.8 | AB16: =IF(DAY(EOMONTH(AA$1,0))>=$B16, 11-COUNTIFS(dataMail!$C:$C,"<>Annulation",dataMail!$G:$G,"<="&(AA$1+$B16-1),dataMail!$H:$H,">"&(AA$1+$B16-1)),"-") -> 9 | AC16: =IF(DAY(EOMONTH(AC$1,0))>=$B16,IFERROR(AVERAGEIFS(dataMail!$P:$P,dataMail!$C:$C,"Confirmation",dataMail!$G:$G,"<="&(AC$1+$B16-1),dataMail!$H:$H,">"&(AC$1+$B16-1)),"-"),"-") -> - | AD16: =IF(DAY(EOMONTH(AC$1,0))>=$B16, 11-COUNTIFS(dataMail!$C:$C,"<>Annulation",dataMail!$G:$G,"<="&(AC$1+$B16-1),dataMail!$H:$H,">"&(AC$1+$B16-1)),"-") -> 11 | AE16: =IF(DAY(EOMONTH(AE$1,0))>=$B16,IFERROR(AVERAGEIFS(dataMail!$P:$P,dataMail!$C:$C,"Confirmation",dataMail!$G:$G,"<="&(AE$1+$B16-1),dataMail!$H:$H,">"&(AE$1+$B16-1)),"-"),"-") -> 94.624 | AF16: =IF(DAY(EOMONTH(AE$1,0))>=$B16, 11-COUNTIFS(dataMail!$C:$C,"<>Annulation",dataMail!$G:$G,"<="&(AE$1+$B16-1),dataMail!$H:$H,">"&(AE$1+$B16-1)),"-") -> 10 | AG16: =IF(DAY(EOMONTH(AG$1,0))>=$B16,IFERROR(AVERAGEIFS(dataMail!$P:$P,dataMail!$C:$C,"Confirmation",dataMail!$G:$G,"<="&(AG$1+$B16-1),dataMail!$H:$H,">"&(AG$1+$B16-1)),"-"),"-") -> - | AH16: =IF(DAY(EOMONTH(AG$1,0))>=$B16, 11-COUNTIFS(dataMail!$C:$C,"<>Annulation",dataMail!$G:$G,"<="&(AG$1+$B16-1),dataMail!$H:$H,">"&(AG$1+$B16-1)),"-") -> 11
B17: 7 | C17: =IF(DAY(EOMONTH(C$1,0))>=$B17,IFERROR(AVERAGEIFS(dataMail!$P:$P,dataMail!$C:$C,"Confirmation",dataMail!$G:$G,"<="&(C$1+$B17-1),dataMail!$H:$H,">"&(C$1+$B17-1)),"-"),"-") -> 107.83314 | D17: =IF(DAY(EOMONTH(C$1,0))>=$B17, 11-COUNTIFS(dataMail!$C:$C,"<>Annulation",dataMail!$G:$G,"<="&(C$1+$B17-1),dataMail!$H:$H,">"&(C$1+$B17-1)),"-") -> 3 | E17: =IF(DAY(EOMONTH(E$1,0))>=$B17,IFERROR(AVERAGEIFS(dataMail!$P:$P,dataMail!$C:$C,"Confirmation",dataMail!$G:$G,"<="&(E$1+$B17-1),dataMail!$H:$H,">"&(E$1+$B17-1)),"-"),"-") -> 166.69733 | F17: =IF(DAY(EOMONTH(E$1,0))>=$B17, 11-COUNTIFS(dataMail!$C:$C,"<>Annulation",dataMail!$G:$G,"<="&(E$1+$B17-1),dataMail!$H:$H,">"&(E$1+$B17-1)),"-") -> 4 | G17: =IF(DAY(EOMONTH(G$1,0))>=$B17,IFERROR(AVERAGEIFS(dataMail!$P:$P,dataMail!$C:$C,"Confirmation",dataMail!$G:$G,"<="&(G$1+$B17-1),dataMail!$H:$H,">"&(G$1+$B17-1)),"-"),"-") -> 106.959 | H17: =IF(DAY(EOMONTH(G$1,0))>=$B17, 11-COUNTIFS(dataMail!$C:$C,"<>Annulation",dataMail!$G:$G,"<="&(G$1+$B17-1),dataMail!$H:$H,">"&(G$1+$B17-1)),"-") -> 3 | I17: =IF(DAY(EOMONTH(I$1,0))>=$B17,IFERROR(AVERAGEIFS(dataMail!$P:$P,dataMail!$C:$C,"Confirmation",dataMail!$G:$G,"<="&(I$1+$B17-1),dataMail!$H:$H,">"&(I$1+$B17-1)),"-"),"-") -> 118.73257 | J17: =IF(DAY(EOMONTH(I$1,0))>=$B17, 11-COUNTIFS(dataMail!$C:$C,"<>Annulation",dataMail!$G:$G,"<="&(I$1+$B17-1),dataMail!$H:$H,">"&(I$1+$B17-1)),"-") -> 3 | K17: =IF(DAY(EOMONTH(K$1,0))>=$B17,IFERROR(AVERAGEIFS(dataMail!$P:$P,dataMail!$C:$C,"Confirmation",dataMail!$G:$G,"<="&(K$1+$B17-1),dataMail!$H:$H,">"&(K$1+$B17-1)),"-"),"-") -> 168.4352 | L17: =IF(DAY(EOMONTH(K$1,0))>=$B17, 11-COUNTIFS(dataMail!$C:$C,"<>Annulation",dataMail!$G:$G,"<="&(K$1+$B17-1),dataMail!$H:$H,">"&(K$1+$B17-1)),"-") -> 6 | M17: =IF(DAY(EOMONTH(M$1,0))>=$B17,IFERROR(AVERAGEIFS(dataMail!$P:$P,dataMail!$C:$C,"Confirmation",dataMail!$G:$G,"<="&(M$1+$B17-1),dataMail!$H:$H,">"&(M$1+$B17-1)),"-"),"-") -> 131.688 | N17: =IF(DAY(EOMONTH(M$1,0))>=$B17, 11-COUNTIFS(dataMail!$C:$C,"<>Annulation",dataMail!$G:$G,"<="&(M$1+$B17-1),dataMail!$H:$H,">"&(M$1+$B17-1)),"-") -> 6 | O17: =IF(DAY(EOMONTH(O$1,0))>=$B17,IFERROR(AVERAGEIFS(dataMail!$P:$P,dataMail!$C:$C,"Confirmation",dataMail!$G:$G,"<="&(O$1+$B17-1),dataMail!$H:$H,">"&(O$1+$B17-1)),"-"),"-") -> - | P17: =IF(DAY(EOMONTH(O$1,0))>=$B17, 11-COUNTIFS(dataMail!$C:$C,"<>Annulation",dataMail!$G:$G,"<="&(O$1+$B17-1),dataMail!$H:$H,">"&(O$1+$B17-1)),"-") -> 11 | Q17: =IF(DAY(EOMONTH(Q$1,0))>=$B17,IFERROR(AVERAGEIFS(dataMail!$P:$P,dataMail!$C:$C,"Confirmation",dataMail!$G:$G,"<="&(Q$1+$B17-1),dataMail!$H:$H,">"&(Q$1+$B17-1)),"-"),"-") -> 260.21829 | R17: =IF(DAY(EOMONTH(Q$1,0))>=$B17, 11-COUNTIFS(dataMail!$C:$C,"<>Annulation",dataMail!$G:$G,"<="&(Q$1+$B17-1),dataMail!$H:$H,">"&(Q$1+$B17-1)),"-") -> 4 | S17: =IF(DAY(EOMONTH(S$1,0))>=$B17,IFERROR(AVERAGEIFS(dataMail!$P:$P,dataMail!$C:$C,"Confirmation",dataMail!$G:$G,"<="&(S$1+$B17-1),dataMail!$H:$H,">"&(S$1+$B17-1)),"-"),"-") -> - | T17: =IF(DAY(EOMONTH(S$1,0))>=$B17, 11-COUNTIFS(dataMail!$C:$C,"<>Annulation",dataMail!$G:$G,"<="&(S$1+$B17-1),dataMail!$H:$H,">"&(S$1+$B17-1)),"-") -> 11 | U17: =IF(DAY(EOMONTH(U$1,0))>=$B17,IFERROR(AVERAGEIFS(dataMail!$P:$P,dataMail!$C:$C,"Confirmation",dataMail!$G:$G,"<="&(U$1+$B17-1),dataMail!$H:$H,">"&(U$1+$B17-1)),"-"),"-") -> - | V17: =IF(DAY(EOMONTH(U$1,0))>=$B17, 11-COUNTIFS(dataMail!$C:$C,"<>Annulation",dataMail!$G:$G,"<="&(U$1+$B17-1),dataMail!$H:$H,">"&(U$1+$B17-1)),"-") -> 11 | W17: =IF(DAY(EOMONTH(W$1,0))>=$B17,IFERROR(AVERAGEIFS(dataMail!$P:$P,dataMail!$C:$C,"Confirmation",dataMail!$G:$G,"<="&(W$1+$B17-1),dataMail!$H:$H,">"&(W$1+$B17-1)),"-"),"-") -> - | X17: =IF(DAY(EOMONTH(W$1,0))>=$B17, 11-COUNTIFS(dataMail!$C:$C,"<>Annulation",dataMail!$G:$G,"<="&(W$1+$B17-1),dataMail!$H:$H,">"&(W$1+$B17-1)),"-") -> 11 | Y17: =IF(DAY(EOMONTH(Y$1,0))>=$B17,IFERROR(AVERAGEIFS(dataMail!$P:$P,dataMail!$C:$C,"Confirmation",dataMail!$G:$G,"<="&(Y$1+$B17-1),dataMail!$H:$H,">"&(Y$1+$B17-1)),"-"),"-") -> 142.384 | Z17: =IF(DAY(EOMONTH(Y$1,0))>=$B17, 11-COUNTIFS(dataMail!$C:$C,"<>Annulation",dataMail!$G:$G,"<="&(Y$1+$B17-1),dataMail!$H:$H,">"&(Y$1+$B17-1)),"-") -> 9 | AA17: =IF(DAY(EOMONTH(AA$1,0))>=$B17,IFERROR(AVERAGEIFS(dataMail!$P:$P,dataMail!$C:$C,"Confirmation",dataMail!$G:$G,"<="&(AA$1+$B17-1),dataMail!$H:$H,">"&(AA$1+$B17-1)),"-"),"-") -> 92.448 | AB17: =IF(DAY(EOMONTH(AA$1,0))>=$B17, 11-COUNTIFS(dataMail!$C:$C,"<>Annulation",dataMail!$G:$G,"<="&(AA$1+$B17-1),dataMail!$H:$H,">"&(AA$1+$B17-1)),"-") -> 10 | AC17: =IF(DAY(EOMONTH(AC$1,0))>=$B17,IFERROR(AVERAGEIFS(dataMail!$P:$P,dataMail!$C:$C,"Confirmation",dataMail!$G:$G,"<="&(AC$1+$B17-1),dataMail!$H:$H,">"&(AC$1+$B17-1)),"-"),"-") -> - | AD17: =IF(DAY(EOMONTH(AC$1,0))>=$B17, 11-COUNTIFS(dataMail!$C:$C,"<>Annulation",dataMail!$G:$G,"<="&(AC$1+$B17-1),dataMail!$H:$H,">"&(AC$1+$B17-1)),"-") -> 11 | AE17: =IF(DAY(EOMONTH(AE$1,0))>=$B17,IFERROR(AVERAGEIFS(dataMail!$P:$P,dataMail!$C:$C,"Confirmation",dataMail!$G:$G,"<="&(AE$1+$B17-1),dataMail!$H:$H,">"&(AE$1+$B17-1)),"-"),"-") -> 0 | AF17: =IF(DAY(EOMONTH(AE$1,0))>=$B17, 11-COUNTIFS(dataMail!$C:$C,"<>Annulation",dataMail!$G:$G,"<="&(AE$1+$B17-1),dataMail!$H:$H,">"&(AE$1+$B17-1)),"-") -> 10 | AG17: =IF(DAY(EOMONTH(AG$1,0))>=$B17,IFERROR(AVERAGEIFS(dataMail!$P:$P,dataMail!$C:$C,"Confirmation",dataMail!$G:$G,"<="&(AG$1+$B17-1),dataMail!$H:$H,">"&(AG$1+$B17-1)),"-"),"-") -> 128.896 | AH17: =IF(DAY(EOMONTH(AG$1,0))>=$B17, 11-COUNTIFS(dataMail!$C:$C,"<>Annulation",dataMail!$G:$G,"<="&(AG$1+$B17-1),dataMail!$H:$H,">"&(AG$1+$B17-1)),"-") -> 10
B18: 8 | C18: =IF(DAY(EOMONTH(C$1,0))>=$B18,IFERROR(AVERAGEIFS(dataMail!$P:$P,dataMail!$C:$C,"Confirmation",dataMail!$G:$G,"<="&(C$1+$B18-1),dataMail!$H:$H,">"&(C$1+$B18-1)),"-"),"-") -> 139.5328 | D18: =IF(DAY(EOMONTH(C$1,0))>=$B18, 11-COUNTIFS(dataMail!$C:$C,"<>Annulation",dataMail!$G:$G,"<="&(C$1+$B18-1),dataMail!$H:$H,">"&(C$1+$B18-1)),"-") -> 0 | E18: =IF(DAY(EOMONTH(E$1,0))>=$B18,IFERROR(AVERAGEIFS(dataMail!$P:$P,dataMail!$C:$C,"Confirmation",dataMail!$G:$G,"<="&(E$1+$B18-1),dataMail!$H:$H,">"&(E$1+$B18-1)),"-"),"-") -> 188.126 | F18: =IF(DAY(EOMONTH(E$1,0))>=$B18, 11-COUNTIFS(dataMail!$C:$C,"<>Annulation",dataMail!$G:$G,"<="&(E$1+$B18-1),dataMail!$H:$H,">"&(E$1+$B18-1)),"-") -> 6 | G18: =IF(DAY(EOMONTH(G$1,0))>=$B18,IFERROR(AVERAGEIFS(dataMail!$P:$P,dataMail!$C:$C,"Confirmation",dataMail!$G:$G,"<="&(G$1+$B18-1),dataMail!$H:$H,">"&(G$1+$B18-1)),"-"),"-") -> 103.25382 | H18: =IF(DAY(EOMONTH(G$1,0))>=$B18, 11-COUNTIFS(dataMail!$C:$C,"<>Annulation",dataMail!$G:$G,"<="&(G$1+$B18-1),dataMail!$H:$H,">"&(G$1+$B18-1)),"-") -> 0 | I18: =IF(DAY(EOMONTH(I$1,0))>=$B18,IFERROR(AVERAGEIFS(dataMail!$P:$P,dataMail!$C:$C,"Confirmation",dataMail!$G:$G,"<="&(I$1+$B18-1),dataMail!$H:$H,">"&(I$1+$B18-1)),"-"),"-") -> 111.567 | J18: =IF(DAY(EOMONTH(I$1,0))>=$B18, 11-COUNTIFS(dataMail!$C:$C,"<>Annulation",dataMail!$G:$G,"<="&(I$1+$B18-1),dataMail!$H:$H,">"&(I$1+$B18-1)),"-") -> 2 | K18: =IF(DAY(EOMONTH(K$1,0))>=$B18,IFERROR(AVERAGEIFS(dataMail!$P:$P,dataMail!$C:$C,"Confirmation",dataMail!$G:$G,"<="&(K$1+$B18-1),dataMail!$H:$H,">"&(K$1+$B18-1)),"-"),"-") -> 147.1432 | L18: =IF(DAY(EOMONTH(K$1,0))>=$B18, 11-COUNTIFS(dataMail!$C:$C,"<>Annulation",dataMail!$G:$G,"<="&(K$1+$B18-1),dataMail!$H:$H,">"&(K$1+$B18-1)),"-") -> 1 | M18: =IF(DAY(EOMONTH(M$1,0))>=$B18,IFERROR(AVERAGEIFS(dataMail!$P:$P,dataMail!$C:$C,"Confirmation",dataMail!$G:$G,"<="&(M$1+$B18-1),dataMail!$H:$H,">"&(M$1+$B18-1)),"-"),"-") -> 126.59467 | N18: =IF(DAY(EOMONTH(M$1,0))>=$B18, 11-COUNTIFS(dataMail!$C:$C,"<>Annulation",dataMail!$G:$G,"<="&(M$1+$B18-1),dataMail!$H:$H,">"&(M$1+$B18-1)),"-") -> 5 | O18: =IF(DAY(EOMONTH(O$1,0))>=$B18,IFERROR(AVERAGEIFS(dataMail!$P:$P,dataMail!$C:$C,"Confirmation",dataMail!$G:$G,"<="&(O$1+$B18-1),dataMail!$H:$H,">"&(O$1+$B18-1)),"-"),"-") -> 120.576 | P18: =IF(DAY(EOMONTH(O$1,0))>=$B18, 11-COUNTIFS(dataMail!$C:$C,"<>Annulation",dataMail!$G:$G,"<="&(O$1+$B18-1),dataMail!$H:$H,">"&(O$1+$B18-1)),"-") -> 9 | Q18: =IF(DAY(EOMONTH(Q$1,0))>=$B18,IFERROR(AVERAGEIFS(dataMail!$P:$P,dataMail!$C:$C,"Confirmation",dataMail!$G:$G,"<="&(Q$1+$B18-1),dataMail!$H:$H,">"&(Q$1+$B18-1)),"-"),"-") -> 256.74857 | R18: =IF(DAY(EOMONTH(Q$1,0))>=$B18, 11-COUNTIFS(dataMail!$C:$C,"<>Annulation",dataMail!$G:$G,"<="&(Q$1+$B18-1),dataMail!$H:$H,">"&(Q$1+$B18-1)),"-") -> 4 | S18: =IF(DAY(EOMONTH(S$1,0))>=$B18,IFERROR(AVERAGEIFS(dataMail!$P:$P,dataMail!$C:$C,"Confirmation",dataMail!$G:$G,"<="&(S$1+$B18-1),dataMail!$H:$H,">"&(S$1+$B18-1)),"-"),"-") -> 195.96 | T18: =IF(DAY(EOMONTH(S$1,0))>=$B18, 11-COUNTIFS(dataMail!$C:$C,"<>Annulation",dataMail!$G:$G,"<="&(S$1+$B18-1),dataMail!$H:$H,">"&(S$1+$B18-1)),"-") -> 5 | U18: =IF(DAY(EOMONTH(U$1,0))>=$B18,IFERROR(AVERAGEIFS(dataMail!$P:$P,dataMail!$C:$C,"Confirmation",dataMail!$G:$G,"<="&(U$1+$B18-1),dataMail!$H:$H,">"&(U$1+$B18-1)),"-"),"-") -> - | V18: =IF(DAY(EOMONTH(U$1,0))>=$B18, 11-COUNTIFS(dataMail!$C:$C,"<>Annulation",dataMail!$G:$G,"<="&(U$1+$B18-1),dataMail!$H:$H,">"&(U$1+$B18-1)),"-") -> 11 | W18: =IF(DAY(EOMONTH(W$1,0))>=$B18,IFERROR(AVERAGEIFS(dataMail!$P:$P,dataMail!$C:$C,"Confirmation",dataMail!$G:$G,"<="&(W$1+$B18-1),dataMail!$H:$H,">"&(W$1+$B18-1)),"-"),"-") -> - | X18: =IF(DAY(EOMONTH(W$1,0))>=$B18, 11-COUNTIFS(dataMail!$C:$C,"<>Annulation",dataMail!$G:$G,"<="&(W$1+$B18-1),dataMail!$H:$H,">"&(W$1+$B18-1)),"-") -> 11 | Y18: =IF(DAY(EOMONTH(Y$1,0))>=$B18,IFERROR(AVERAGEIFS(dataMail!$P:$P,dataMail!$C:$C,"Confirmation",dataMail!$G:$G,"<="&(Y$1+$B18-1),dataMail!$H:$H,">"&(Y$1+$B18-1)),"-"),"-") -> 142.384 | Z18: =IF(DAY(EOMONTH(Y$1,0))>=$B18, 11-COUNTIFS(dataMail!$C:$C,"<>Annulation",dataMail!$G:$G,"<="&(Y$1+$B18-1),dataMail!$H:$H,">"&(Y$1+$B18-1)),"-") -> 9 | AA18: =IF(DAY(EOMONTH(AA$1,0))>=$B18,IFERROR(AVERAGEIFS(dataMail!$P:$P,dataMail!$C:$C,"Confirmation",dataMail!$G:$G,"<="&(AA$1+$B18-1),dataMail!$H:$H,">"&(AA$1+$B18-1)),"-"),"-") -> - | AB18: =IF(DAY(EOMONTH(AA$1,0))>=$B18, 11-COUNTIFS(dataMail!$C:$C,"<>Annulation",dataMail!$G:$G,"<="&(AA$1+$B18-1),dataMail!$H:$H,">"&(AA$1+$B18-1)),"-") -> 11 | AC18: =IF(DAY(EOMONTH(AC$1,0))>=$B18,IFERROR(AVERAGEIFS(dataMail!$P:$P,dataMail!$C:$C,"Confirmation",dataMail!$G:$G,"<="&(AC$1+$B18-1),dataMail!$H:$H,">"&(AC$1+$B18-1)),"-"),"-") -> - | AD18: =IF(DAY(EOMONTH(AC$1,0))>=$B18, 11-COUNTIFS(dataMail!$C:$C,"<>Annulation",dataMail!$G:$G,"<="&(AC$1+$B18-1),dataMail!$H:$H,">"&(AC$1+$B18-1)),"-") -> 11 | AE18: =IF(DAY(EOMONTH(AE$1,0))>=$B18,IFERROR(AVERAGEIFS(dataMail!$P:$P,dataMail!$C:$C,"Confirmation",dataMail!$G:$G,"<="&(AE$1+$B18-1),dataMail!$H:$H,">"&(AE$1+$B18-1)),"-"),"-") -> 0 | AF18: =IF(DAY(EOMONTH(AE$1,0))>=$B18, 11-COUNTIFS(dataMail!$C:$C,"<>Annulation",dataMail!$G:$G,"<="&(AE$1+$B18-1),dataMail!$H:$H,">"&(AE$1+$B18-1)),"-") -> 10 | AG18: =IF(DAY(EOMONTH(AG$1,0))>=$B18,IFERROR(AVERAGEIFS(dataMail!$P:$P,dataMail!$C:$C,"Confirmation",dataMail!$G:$G,"<="&(AG$1+$B18-1),dataMail!$H:$H,">"&(AG$1+$B18-1)),"-"),"-") -> 128.896 | AH18: =IF(DAY(EOMONTH(AG$1,0))>=$B18, 11-COUNTIFS(dataMail!$C:$C,"<>Annulation",dataMail!$G:$G,"<="&(AG$1+$B18-1),dataMail!$H:$H,">"&(AG$1+$B18-1)),"-") -> 10
B19: 9 | C19: =IF(DAY(EOMONTH(C$1,0))>=$B19,IFERROR(AVERAGEIFS(dataMail!$P:$P,dataMail!$C:$C,"Confirmation",dataMail!$G:$G,"<="&(C$1+$B19-1),dataMail!$H:$H,">"&(C$1+$B19-1)),"-"),"-") -> 146.30836 | D19: =IF(DAY(EOMONTH(C$1,0))>=$B19, 11-COUNTIFS(dataMail!$C:$C,"<>Annulation",dataMail!$G:$G,"<="&(C$1+$B19-1),dataMail!$H:$H,">"&(C$1+$B19-1)),"-") -> 0 | E19: =IF(DAY(EOMONTH(E$1,0))>=$B19,IFERROR(AVERAGEIFS(dataMail!$P:$P,dataMail!$C:$C,"Confirmation",dataMail!$G:$G,"<="&(E$1+$B19-1),dataMail!$H:$H,">"&(E$1+$B19-1)),"-"),"-") -> 138.2704 | F19: =IF(DAY(EOMONTH(E$1,0))>=$B19, 11-COUNTIFS(dataMail!$C:$C,"<>Annulation",dataMail!$G:$G,"<="&(E$1+$B19-1),dataMail!$H:$H,">"&(E$1+$B19-1)),"-") -> 1 | G19: =IF(DAY(EOMONTH(G$1,0))>=$B19,IFERROR(AVERAGEIFS(dataMail!$P:$P,dataMail!$C:$C,"Confirmation",dataMail!$G:$G,"<="&(G$1+$B19-1),dataMail!$H:$H,">"&(G$1+$B19-1)),"-"),"-") -> 105.379 | H19: =IF(DAY(EOMONTH(G$1,0))>=$B19, 11-COUNTIFS(dataMail!$C:$C,"<>Annulation",dataMail!$G:$G,"<="&(G$1+$B19-1),dataMail!$H:$H,">"&(G$1+$B19-1)),"-") -> 3 | I19: =IF(DAY(EOMONTH(I$1,0))>=$B19,IFERROR(AVERAGEIFS(dataMail!$P:$P,dataMail!$C:$C,"Confirmation",dataMail!$G:$G,"<="&(I$1+$B19-1),dataMail!$H:$H,">"&(I$1+$B19-1)),"-"),"-") -> 115.368 | J19: =IF(DAY(EOMONTH(I$1,0))>=$B19, 11-COUNTIFS(dataMail!$C:$C,"<>Annulation",dataMail!$G:$G,"<="&(I$1+$B19-1),dataMail!$H:$H,">"&(I$1+$B19-1)),"-") -> 3 | K19: =IF(DAY(EOMONTH(K$1,0))>=$B19,IFERROR(AVERAGEIFS(dataMail!$P:$P,dataMail!$C:$C,"Confirmation",dataMail!$G:$G,"<="&(K$1+$B19-1),dataMail!$H:$H,">"&(K$1+$B19-1)),"-"),"-") -> 154.851 | L19: =IF(DAY(EOMONTH(K$1,0))>=$B19, 11-COUNTIFS(dataMail!$C:$C,"<>Annulation",dataMail!$G:$G,"<="&(K$1+$B19-1),dataMail!$H:$H,">"&(K$1+$B19-1)),"-") -> 2 | M19: =IF(DAY(EOMONTH(M$1,0))>=$B19,IFERROR(AVERAGEIFS(dataMail!$P:$P,dataMail!$C:$C,"Confirmation",dataMail!$G:$G,"<="&(M$1+$B19-1),dataMail!$H:$H,">"&(M$1+$B19-1)),"-"),"-") -> 134.9936 | N19: =IF(DAY(EOMONTH(M$1,0))>=$B19, 11-COUNTIFS(dataMail!$C:$C,"<>Annulation",dataMail!$G:$G,"<="&(M$1+$B19-1),dataMail!$H:$H,">"&(M$1+$B19-1)),"-") -> 5 | O19: =IF(DAY(EOMONTH(O$1,0))>=$B19,IFERROR(AVERAGEIFS(dataMail!$P:$P,dataMail!$C:$C,"Confirmation",dataMail!$G:$G,"<="&(O$1+$B19-1),dataMail!$H:$H,">"&(O$1+$B19-1)),"-"),"-") -> 130.68293 | P19: =IF(DAY(EOMONTH(O$1,0))>=$B19, 11-COUNTIFS(dataMail!$C:$C,"<>Annulation",dataMail!$G:$G,"<="&(O$1+$B19-1),dataMail!$H:$H,">"&(O$1+$B19-1)),"-") -> 7 | Q19: =IF(DAY(EOMONTH(Q$1,0))>=$B19,IFERROR(AVERAGEIFS(dataMail!$P:$P,dataMail!$C:$C,"Confirmation",dataMail!$G:$G,"<="&(Q$1+$B19-1),dataMail!$H:$H,">"&(Q$1+$B19-1)),"-"),"-") -> 185.708 | R19: =IF(DAY(EOMONTH(Q$1,0))>=$B19, 11-COUNTIFS(dataMail!$C:$C,"<>Annulation",dataMail!$G:$G,"<="&(Q$1+$B19-1),dataMail!$H:$H,">"&(Q$1+$B19-1)),"-") -> 9 | S19: =IF(DAY(EOMONTH(S$1,0))>=$B19,IFERROR(AVERAGEIFS(dataMail!$P:$P,dataMail!$C:$C,"Confirmation",dataMail!$G:$G,"<="&(S$1+$B19-1),dataMail!$H:$H,">"&(S$1+$B19-1)),"-"),"-") -> - | T19: =IF(DAY(EOMONTH(S$1,0))>=$B19, 11-COUNTIFS(dataMail!$C:$C,"<>Annulation",dataMail!$G:$G,"<="&(S$1+$B19-1),dataMail!$H:$H,">"&(S$1+$B19-1)),"-") -> 11 | U19: =IF(DAY(EOMONTH(U$1,0))>=$B19,IFERROR(AVERAGEIFS(dataMail!$P:$P,dataMail!$C:$C,"Confirmation",dataMail!$G:$G,"<="&(U$1+$B19-1),dataMail!$H:$H,">"&(U$1+$B19-1)),"-"),"-") -> - | V19: =IF(DAY(EOMONTH(U$1,0))>=$B19, 11-COUNTIFS(dataMail!$C:$C,"<>Annulation",dataMail!$G:$G,"<="&(U$1+$B19-1),dataMail!$H:$H,">"&(U$1+$B19-1)),"-") -> 11 | W19: =IF(DAY(EOMONTH(W$1,0))>=$B19,IFERROR(AVERAGEIFS(dataMail!$P:$P,dataMail!$C:$C,"Confirmation",dataMail!$G:$G,"<="&(W$1+$B19-1),dataMail!$H:$H,">"&(W$1+$B19-1)),"-"),"-") -> - | X19: =IF(DAY(EOMONTH(W$1,0))>=$B19, 11-COUNTIFS(dataMail!$C:$C,"<>Annulation",dataMail!$G:$G,"<="&(W$1+$B19-1),dataMail!$H:$H,">"&(W$1+$B19-1)),"-") -> 11 | Y19: =IF(DAY(EOMONTH(Y$1,0))>=$B19,IFERROR(AVERAGEIFS(dataMail!$P:$P,dataMail!$C:$C,"Confirmation",dataMail!$G:$G,"<="&(Y$1+$B19-1),dataMail!$H:$H,">"&(Y$1+$B19-1)),"-"),"-") -> 142.384 | Z19: =IF(DAY(EOMONTH(Y$1,0))>=$B19, 11-COUNTIFS(dataMail!$C:$C,"<>Annulation",dataMail!$G:$G,"<="&(Y$1+$B19-1),dataMail!$H:$H,">"&(Y$1+$B19-1)),"-") -> 9 | AA19: =IF(DAY(EOMONTH(AA$1,0))>=$B19,IFERROR(AVERAGEIFS(dataMail!$P:$P,dataMail!$C:$C,"Confirmation",dataMail!$G:$G,"<="&(AA$1+$B19-1),dataMail!$H:$H,">"&(AA$1+$B19-1)),"-"),"-") -> - | AB19: =IF(DAY(EOMONTH(AA$1,0))>=$B19, 11-COUNTIFS(dataMail!$C:$C,"<>Annulation",dataMail!$G:$G,"<="&(AA$1+$B19-1),dataMail!$H:$H,">"&(AA$1+$B19-1)),"-") -> 11 | AC19: =IF(DAY(EOMONTH(AC$1,0))>=$B19,IFERROR(AVERAGEIFS(dataMail!$P:$P,dataMail!$C:$C,"Confirmation",dataMail!$G:$G,"<="&(AC$1+$B19-1),dataMail!$H:$H,">"&(AC$1+$B19-1)),"-"),"-") -> - | AD19: =IF(DAY(EOMONTH(AC$1,0))>=$B19, 11-COUNTIFS(dataMail!$C:$C,"<>Annulation",dataMail!$G:$G,"<="&(AC$1+$B19-1),dataMail!$H:$H,">"&(AC$1+$B19-1)),"-") -> 11 | AE19: =IF(DAY(EOMONTH(AE$1,0))>=$B19,IFERROR(AVERAGEIFS(dataMail!$P:$P,dataMail!$C:$C,"Confirmation",dataMail!$G:$G,"<="&(AE$1+$B19-1),dataMail!$H:$H,">"&(AE$1+$B19-1)),"-"),"-") -> 0 | AF19: =IF(DAY(EOMONTH(AE$1,0))>=$B19, 11-COUNTIFS(dataMail!$C:$C,"<>Annulation",dataMail!$G:$G,"<="&(AE$1+$B19-1),dataMail!$H:$H,">"&(AE$1+$B19-1)),"-") -> 10 | AG19: =IF(DAY(EOMONTH(AG$1,0))>=$B19,IFERROR(AVERAGEIFS(dataMail!$P:$P,dataMail!$C:$C,"Confirmation",dataMail!$G:$G,"<="&(AG$1+$B19-1),dataMail!$H:$H,">"&(AG$1+$B19-1)),"-"),"-") -> 128.896 | AH19: =IF(DAY(EOMONTH(AG$1,0))>=$B19, 11-COUNTIFS(dataMail!$C:$C,"<>Annulation",dataMail!$G:$G,"<="&(AG$1+$B19-1),dataMail!$H:$H,">"&(AG$1+$B19-1)),"-") -> 10
B20: 10 | C20: =IF(DAY(EOMONTH(C$1,0))>=$B20,IFERROR(AVERAGEIFS(dataMail!$P:$P,dataMail!$C:$C,"Confirmation",dataMail!$G:$G,"<="&(C$1+$B20-1),dataMail!$H:$H,">"&(C$1+$B20-1)),"-"),"-") -> 157.86036 | D20: =IF(DAY(EOMONTH(C$1,0))>=$B20, 11-COUNTIFS(dataMail!$C:$C,"<>Annulation",dataMail!$G:$G,"<="&(C$1+$B20-1),dataMail!$H:$H,">"&(C$1+$B20-1)),"-") -> 0 | E20: =IF(DAY(EOMONTH(E$1,0))>=$B20,IFERROR(AVERAGEIFS(dataMail!$P:$P,dataMail!$C:$C,"Confirmation",dataMail!$G:$G,"<="&(E$1+$B20-1),dataMail!$H:$H,">"&(E$1+$B20-1)),"-"),"-") -> 121.988 | F20: =IF(DAY(EOMONTH(E$1,0))>=$B20, 11-COUNTIFS(dataMail!$C:$C,"<>Annulation",dataMail!$G:$G,"<="&(E$1+$B20-1),dataMail!$H:$H,">"&(E$1+$B20-1)),"-") -> 3 | G20: =IF(DAY(EOMONTH(G$1,0))>=$B20,IFERROR(AVERAGEIFS(dataMail!$P:$P,dataMail!$C:$C,"Confirmation",dataMail!$G:$G,"<="&(G$1+$B20-1),dataMail!$H:$H,">"&(G$1+$B20-1)),"-"),"-") -> 105.228 | H20: =IF(DAY(EOMONTH(G$1,0))>=$B20, 11-COUNTIFS(dataMail!$C:$C,"<>Annulation",dataMail!$G:$G,"<="&(G$1+$B20-1),dataMail!$H:$H,">"&(G$1+$B20-1)),"-") -> 5 | I20: =IF(DAY(EOMONTH(I$1,0))>=$B20,IFERROR(AVERAGEIFS(dataMail!$P:$P,dataMail!$C:$C,"Confirmation",dataMail!$G:$G,"<="&(I$1+$B20-1),dataMail!$H:$H,">"&(I$1+$B20-1)),"-"),"-") -> 160.93511 | J20: =IF(DAY(EOMONTH(I$1,0))>=$B20, 11-COUNTIFS(dataMail!$C:$C,"<>Annulation",dataMail!$G:$G,"<="&(I$1+$B20-1),dataMail!$H:$H,">"&(I$1+$B20-1)),"-") -> 2 | K20: =IF(DAY(EOMONTH(K$1,0))>=$B20,IFERROR(AVERAGEIFS(dataMail!$P:$P,dataMail!$C:$C,"Confirmation",dataMail!$G:$G,"<="&(K$1+$B20-1),dataMail!$H:$H,">"&(K$1+$B20-1)),"-"),"-") -> 123.52343 | L20: =IF(DAY(EOMONTH(K$1,0))>=$B20, 11-COUNTIFS(dataMail!$C:$C,"<>Annulation",dataMail!$G:$G,"<="&(K$1+$B20-1),dataMail!$H:$H,">"&(K$1+$B20-1)),"-") -> 3 | M20: =IF(DAY(EOMONTH(M$1,0))>=$B20,IFERROR(AVERAGEIFS(dataMail!$P:$P,dataMail!$C:$C,"Confirmation",dataMail!$G:$G,"<="&(M$1+$B20-1),dataMail!$H:$H,">"&(M$1+$B20-1)),"-"),"-") -> 144.27886 | N20: =IF(DAY(EOMONTH(M$1,0))>=$B20, 11-COUNTIFS(dataMail!$C:$C,"<>Annulation",dataMail!$G:$G,"<="&(M$1+$B20-1),dataMail!$H:$H,">"&(M$1+$B20-1)),"-") -> 2 | O20: =IF(DAY(EOMONTH(O$1,0))>=$B20,IFERROR(AVERAGEIFS(dataMail!$P:$P,dataMail!$C:$C,"Confirmation",dataMail!$G:$G,"<="&(O$1+$B20-1),dataMail!$H:$H,">"&(O$1+$B20-1)),"-"),"-") -> 124.19528 | P20: =IF(DAY(EOMONTH(O$1,0))>=$B20, 11-COUNTIFS(dataMail!$C:$C,"<>Annulation",dataMail!$G:$G,"<="&(O$1+$B20-1),dataMail!$H:$H,">"&(O$1+$B20-1)),"-") -> 5 | Q20: =IF(DAY(EOMONTH(Q$1,0))>=$B20,IFERROR(AVERAGEIFS(dataMail!$P:$P,dataMail!$C:$C,"Confirmation",dataMail!$G:$G,"<="&(Q$1+$B20-1),dataMail!$H:$H,">"&(Q$1+$B20-1)),"-"),"-") -> 185.708 | R20: =IF(DAY(EOMONTH(Q$1,0))>=$B20, 11-COUNTIFS(dataMail!$C:$C,"<>Annulation",dataMail!$G:$G,"<="&(Q$1+$B20-1),dataMail!$H:$H,">"&(Q$1+$B20-1)),"-") -> 9 | S20: =IF(DAY(EOMONTH(S$1,0))>=$B20,IFERROR(AVERAGEIFS(dataMail!$P:$P,dataMail!$C:$C,"Confirmation",dataMail!$G:$G,"<="&(S$1+$B20-1),dataMail!$H:$H,">"&(S$1+$B20-1)),"-"),"-") -> - | T20: =IF(DAY(EOMONTH(S$1,0))>=$B20, 11-COUNTIFS(dataMail!$C:$C,"<>Annulation",dataMail!$G:$G,"<="&(S$1+$B20-1),dataMail!$H:$H,">"&(S$1+$B20-1)),"-") -> 11 | U20: =IF(DAY(EOMONTH(U$1,0))>=$B20,IFERROR(AVERAGEIFS(dataMail!$P:$P,dataMail!$C:$C,"Confirmation",dataMail!$G:$G,"<="&(U$1+$B20-1),dataMail!$H:$H,">"&(U$1+$B20-1)),"-"),"-") -> - | V20: =IF(DAY(EOMONTH(U$1,0))>=$B20, 11-COUNTIFS(dataMail!$C:$C,"<>Annulation",dataMail!$G:$G,"<="&(U$1+$B20-1),dataMail!$H:$H,">"&(U$1+$B20-1)),"-") -> 11 | W20: =IF(DAY(EOMONTH(W$1,0))>=$B20,IFERROR(AVERAGEIFS(dataMail!$P:$P,dataMail!$C:$C,"Confirmation",dataMail!$G:$G,"<="&(W$1+$B20-1),dataMail!$H:$H,">"&(W$1+$B20-1)),"-"),"-") -> - | X20: =IF(DAY(EOMONTH(W$1,0))>=$B20, 11-COUNTIFS(dataMail!$C:$C,"<>Annulation",dataMail!$G:$G,"<="&(W$1+$B20-1),dataMail!$H:$H,">"&(W$1+$B20-1)),"-") -> 11 | Y20: =IF(DAY(EOMONTH(Y$1,0))>=$B20,IFERROR(AVERAGEIFS(dataMail!$P:$P,dataMail!$C:$C,"Confirmation",dataMail!$G:$G,"<="&(Y$1+$B20-1),dataMail!$H:$H,">"&(Y$1+$B20-1)),"-"),"-") -> 142.384 | Z20: =IF(DAY(EOMONTH(Y$1,0))>=$B20, 11-COUNTIFS(dataMail!$C:$C,"<>Annulation",dataMail!$G:$G,"<="&(Y$1+$B20-1),dataMail!$H:$H,">"&(Y$1+$B20-1)),"-") -> 9 | AA20: =IF(DAY(EOMONTH(AA$1,0))>=$B20,IFERROR(AVERAGEIFS(dataMail!$P:$P,dataMail!$C:$C,"Confirmation",dataMail!$G:$G,"<="&(AA$1+$B20-1),dataMail!$H:$H,">"&(AA$1+$B20-1)),"-"),"-") -> - | AB20: =IF(DAY(EOMONTH(AA$1,0))>=$B20, 11-COUNTIFS(dataMail!$C:$C,"<>Annulation",dataMail!$G:$G,"<="&(AA$1+$B20-1),dataMail!$H:$H,">"&(AA$1+$B20-1)),"-") -> 11 | AC20: =IF(DAY(EOMONTH(AC$1,0))>=$B20,IFERROR(AVERAGEIFS(dataMail!$P:$P,dataMail!$C:$C,"Confirmation",dataMail!$G:$G,"<="&(AC$1+$B20-1),dataMail!$H:$H,">"&(AC$1+$B20-1)),"-"),"-") -> - | AD20: =IF(DAY(EOMONTH(AC$1,0))>=$B20, 11-COUNTIFS(dataMail!$C:$C,"<>Annulation",dataMail!$G:$G,"<="&(AC$1+$B20-1),dataMail!$H:$H,">"&(AC$1+$B20-1)),"-") -> 11 | AE20: =IF(DAY(EOMONTH(AE$1,0))>=$B20,IFERROR(AVERAGEIFS(dataMail!$P:$P,dataMail!$C:$C,"Confirmation",dataMail!$G:$G,"<="&(AE$1+$B20-1),dataMail!$H:$H,">"&(AE$1+$B20-1)),"-"),"-") -> - | AF20: =IF(DAY(EOMONTH(AE$1,0))>=$B20, 11-COUNTIFS(dataMail!$C:$C,"<>Annulation",dataMail!$G:$G,"<="&(AE$1+$B20-1),dataMail!$H:$H,">"&(AE$1+$B20-1)),"-") -> 11 | AG20: =IF(DAY(EOMONTH(AG$1,0))>=$B20,IFERROR(AVERAGEIFS(dataMail!$P:$P,dataMail!$C:$C,"Confirmation",dataMail!$G:$G,"<="&(AG$1+$B20-1),dataMail!$H:$H,">"&(AG$1+$B20-1)),"-"),"-") -> 128.896 | AH20: =IF(DAY(EOMONTH(AG$1,0))>=$B20, 11-COUNTIFS(dataMail!$C:$C,"<>Annulation",dataMail!$G:$G,"<="&(AG$1+$B20-1),dataMail!$H:$H,">"&(AG$1+$B20-1)),"-") -> 10
B21: 11 | C21: =IF(DAY(EOMONTH(C$1,0))>=$B21,IFERROR(AVERAGEIFS(dataMail!$P:$P,dataMail!$C:$C,"Confirmation",dataMail!$G:$G,"<="&(C$1+$B21-1),dataMail!$H:$H,">"&(C$1+$B21-1)),"-"),"-") -> 124.49048 | D21: =IF(DAY(EOMONTH(C$1,0))>=$B21, 11-COUNTIFS(dataMail!$C:$C,"<>Annulation",dataMail!$G:$G,"<="&(C$1+$B21-1),dataMail!$H:$H,">"&(C$1+$B21-1)),"-") -> 1 | E21: =IF(DAY(EOMONTH(E$1,0))>=$B21,IFERROR(AVERAGEIFS(dataMail!$P:$P,dataMail!$C:$C,"Confirmation",dataMail!$G:$G,"<="&(E$1+$B21-1),dataMail!$H:$H,">"&(E$1+$B21-1)),"-"),"-") -> 107.09067 | F21: =IF(DAY(EOMONTH(E$1,0))>=$B21, 11-COUNTIFS(dataMail!$C:$C,"<>Annulation",dataMail!$G:$G,"<="&(E$1+$B21-1),dataMail!$H:$H,">"&(E$1+$B21-1)),"-") -> 5 | G21: =IF(DAY(EOMONTH(G$1,0))>=$B21,IFERROR(AVERAGEIFS(dataMail!$P:$P,dataMail!$C:$C,"Confirmation",dataMail!$G:$G,"<="&(G$1+$B21-1),dataMail!$H:$H,">"&(G$1+$B21-1)),"-"),"-") -> 101.80817 | H21: =IF(DAY(EOMONTH(G$1,0))>=$B21, 11-COUNTIFS(dataMail!$C:$C,"<>Annulation",dataMail!$G:$G,"<="&(G$1+$B21-1),dataMail!$H:$H,">"&(G$1+$B21-1)),"-") -> 1 | I21: =IF(DAY(EOMONTH(I$1,0))>=$B21,IFERROR(AVERAGEIFS(dataMail!$P:$P,dataMail!$C:$C,"Confirmation",dataMail!$G:$G,"<="&(I$1+$B21-1),dataMail!$H:$H,">"&(I$1+$B21-1)),"-"),"-") -> 158.96 | J21: =IF(DAY(EOMONTH(I$1,0))>=$B21, 11-COUNTIFS(dataMail!$C:$C,"<>Annulation",dataMail!$G:$G,"<="&(I$1+$B21-1),dataMail!$H:$H,">"&(I$1+$B21-1)),"-") -> 2 | K21: =IF(DAY(EOMONTH(K$1,0))>=$B21,IFERROR(AVERAGEIFS(dataMail!$P:$P,dataMail!$C:$C,"Confirmation",dataMail!$G:$G,"<="&(K$1+$B21-1),dataMail!$H:$H,">"&(K$1+$B21-1)),"-"),"-") -> 124.97486 | L21: =IF(DAY(EOMONTH(K$1,0))>=$B21, 11-COUNTIFS(dataMail!$C:$C,"<>Annulation",dataMail!$G:$G,"<="&(K$1+$B21-1),dataMail!$H:$H,">"&(K$1+$B21-1)),"-") -> 4 | M21: =IF(DAY(EOMONTH(M$1,0))>=$B21,IFERROR(AVERAGEIFS(dataMail!$P:$P,dataMail!$C:$C,"Confirmation",dataMail!$G:$G,"<="&(M$1+$B21-1),dataMail!$H:$H,">"&(M$1+$B21-1)),"-"),"-") -> 147.03067 | N21: =IF(DAY(EOMONTH(M$1,0))>=$B21, 11-COUNTIFS(dataMail!$C:$C,"<>Annulation",dataMail!$G:$G,"<="&(M$1+$B21-1),dataMail!$H:$H,">"&(M$1+$B21-1)),"-") -> 2 | O21: =IF(DAY(EOMONTH(O$1,0))>=$B21,IFERROR(AVERAGEIFS(dataMail!$P:$P,dataMail!$C:$C,"Confirmation",dataMail!$G:$G,"<="&(O$1+$B21-1),dataMail!$H:$H,">"&(O$1+$B21-1)),"-"),"-") -> 124.19528 | P21: =IF(DAY(EOMONTH(O$1,0))>=$B21, 11-COUNTIFS(dataMail!$C:$C,"<>Annulation",dataMail!$G:$G,"<="&(O$1+$B21-1),dataMail!$H:$H,">"&(O$1+$B21-1)),"-") -> 5 | Q21: =IF(DAY(EOMONTH(Q$1,0))>=$B21,IFERROR(AVERAGEIFS(dataMail!$P:$P,dataMail!$C:$C,"Confirmation",dataMail!$G:$G,"<="&(Q$1+$B21-1),dataMail!$H:$H,">"&(Q$1+$B21-1)),"-"),"-") -> 185.708 | R21: =IF(DAY(EOMONTH(Q$1,0))>=$B21, 11-COUNTIFS(dataMail!$C:$C,"<>Annulation",dataMail!$G:$G,"<="&(Q$1+$B21-1),dataMail!$H:$H,">"&(Q$1+$B21-1)),"-") -> 9 | S21: =IF(DAY(EOMONTH(S$1,0))>=$B21,IFERROR(AVERAGEIFS(dataMail!$P:$P,dataMail!$C:$C,"Confirmation",dataMail!$G:$G,"<="&(S$1+$B21-1),dataMail!$H:$H,">"&(S$1+$B21-1)),"-"),"-") -> - | T21: =IF(DAY(EOMONTH(S$1,0))>=$B21, 11-COUNTIFS(dataMail!$C:$C,"<>Annulation",dataMail!$G:$G,"<="&(S$1+$B21-1),dataMail!$H:$H,">"&(S$1+$B21-1)),"-") -> 11 | U21: =IF(DAY(EOMONTH(U$1,0))>=$B21,IFERROR(AVERAGEIFS(dataMail!$P:$P,dataMail!$C:$C,"Confirmation",dataMail!$G:$G,"<="&(U$1+$B21-1),dataMail!$H:$H,">"&(U$1+$B21-1)),"-"),"-") -> 128.352 | V21: =IF(DAY(EOMONTH(U$1,0))>=$B21, 11-COUNTIFS(dataMail!$C:$C,"<>Annulation",dataMail!$G:$G,"<="&(U$1+$B21-1),dataMail!$H:$H,">"&(U$1+$B21-1)),"-") -> 8 | W21: =IF(DAY(EOMONTH(W$1,0))>=$B21,IFERROR(AVERAGEIFS(dataMail!$P:$P,dataMail!$C:$C,"Confirmation",dataMail!$G:$G,"<="&(W$1+$B21-1),dataMail!$H:$H,">"&(W$1+$B21-1)),"-"),"-") -> 108.528 | X21: =IF(DAY(EOMONTH(W$1,0))>=$B21, 11-COUNTIFS(dataMail!$C:$C,"<>Annulation",dataMail!$G:$G,"<="&(W$1+$B21-1),dataMail!$H:$H,">"&(W$1+$B21-1)),"-") -> 10 | Y21: =IF(DAY(EOMONTH(Y$1,0))>=$B21,IFERROR(AVERAGEIFS(dataMail!$P:$P,dataMail!$C:$C,"Confirmation",dataMail!$G:$G,"<="&(Y$1+$B21-1),dataMail!$H:$H,">"&(Y$1+$B21-1)),"-"),"-") -> 124.576 | Z21: =IF(DAY(EOMONTH(Y$1,0))>=$B21, 11-COUNTIFS(dataMail!$C:$C,"<>Annulation",dataMail!$G:$G,"<="&(Y$1+$B21-1),dataMail!$H:$H,">"&(Y$1+$B21-1)),"-") -> 10 | AA21: =IF(DAY(EOMONTH(AA$1,0))>=$B21,IFERROR(AVERAGEIFS(dataMail!$P:$P,dataMail!$C:$C,"Confirmation",dataMail!$G:$G,"<="&(AA$1+$B21-1),dataMail!$H:$H,">"&(AA$1+$B21-1)),"-"),"-") -> - | AB21: =IF(DAY(EOMONTH(AA$1,0))>=$B21, 11-COUNTIFS(dataMail!$C:$C,"<>Annulation",dataMail!$G:$G,"<="&(AA$1+$B21-1),dataMail!$H:$H,">"&(AA$1+$B21-1)),"-") -> 11 | AC21: =IF(DAY(EOMONTH(AC$1,0))>=$B21,IFERROR(AVERAGEIFS(dataMail!$P:$P,dataMail!$C:$C,"Confirmation",dataMail!$G:$G,"<="&(AC$1+$B21-1),dataMail!$H:$H,">"&(AC$1+$B21-1)),"-"),"-") -> - | AD21: =IF(DAY(EOMONTH(AC$1,0))>=$B21, 11-COUNTIFS(dataMail!$C:$C,"<>Annulation",dataMail!$G:$G,"<="&(AC$1+$B21-1),dataMail!$H:$H,">"&(AC$1+$B21-1)),"-") -> 11 | AE21: =IF(DAY(EOMONTH(AE$1,0))>=$B21,IFERROR(AVERAGEIFS(dataMail!$P:$P,dataMail!$C:$C,"Confirmation",dataMail!$G:$G,"<="&(AE$1+$B21-1),dataMail!$H:$H,">"&(AE$1+$B21-1)),"-"),"-") -> - | AF21: =IF(DAY(EOMONTH(AE$1,0))>=$B21, 11-COUNTIFS(dataMail!$C:$C,"<>Annulation",dataMail!$G:$G,"<="&(AE$1+$B21-1),dataMail!$H:$H,">"&(AE$1+$B21-1)),"-") -> 11 | AG21: =IF(DAY(EOMONTH(AG$1,0))>=$B21,IFERROR(AVERAGEIFS(dataMail!$P:$P,dataMail!$C:$C,"Confirmation",dataMail!$G:$G,"<="&(AG$1+$B21-1),dataMail!$H:$H,">"&(AG$1+$B21-1)),"-"),"-") -> 128.896 | AH21: =IF(DAY(EOMONTH(AG$1,0))>=$B21, 11-COUNTIFS(dataMail!$C:$C,"<>Annulation",dataMail!$G:$G,"<="&(AG$1+$B21-1),dataMail!$H:$H,">"&(AG$1+$B21-1)),"-") -> 10
B22: 12 | C22: =IF(DAY(EOMONTH(C$1,0))>=$B22,IFERROR(AVERAGEIFS(dataMail!$P:$P,dataMail!$C:$C,"Confirmation",dataMail!$G:$G,"<="&(C$1+$B22-1),dataMail!$H:$H,">"&(C$1+$B22-1)),"-"),"-") -> 124.2891 | D22: =IF(DAY(EOMONTH(C$1,0))>=$B22, 11-COUNTIFS(dataMail!$C:$C,"<>Annulation",dataMail!$G:$G,"<="&(C$1+$B22-1),dataMail!$H:$H,">"&(C$1+$B22-1)),"-") -> 3 | E22: =IF(DAY(EOMONTH(E$1,0))>=$B22,IFERROR(AVERAGEIFS(dataMail!$P:$P,dataMail!$C:$C,"Confirmation",dataMail!$G:$G,"<="&(E$1+$B22-1),dataMail!$H:$H,">"&(E$1+$B22-1)),"-"),"-") -> 108.781 | F22: =IF(DAY(EOMONTH(E$1,0))>=$B22, 11-COUNTIFS(dataMail!$C:$C,"<>Annulation",dataMail!$G:$G,"<="&(E$1+$B22-1),dataMail!$H:$H,">"&(E$1+$B22-1)),"-") -> 3 | G22: =IF(DAY(EOMONTH(G$1,0))>=$B22,IFERROR(AVERAGEIFS(dataMail!$P:$P,dataMail!$C:$C,"Confirmation",dataMail!$G:$G,"<="&(G$1+$B22-1),dataMail!$H:$H,">"&(G$1+$B22-1)),"-"),"-") -> 118.61673 | H22: =IF(DAY(EOMONTH(G$1,0))>=$B22, 11-COUNTIFS(dataMail!$C:$C,"<>Annulation",dataMail!$G:$G,"<="&(G$1+$B22-1),dataMail!$H:$H,">"&(G$1+$B22-1)),"-") -> 0 | I22: =IF(DAY(EOMONTH(I$1,0))>=$B22,IFERROR(AVERAGEIFS(dataMail!$P:$P,dataMail!$C:$C,"Confirmation",dataMail!$G:$G,"<="&(I$1+$B22-1),dataMail!$H:$H,">"&(I$1+$B22-1)),"-"),"-") -> 154.23636 | J22: =IF(DAY(EOMONTH(I$1,0))>=$B22, 11-COUNTIFS(dataMail!$C:$C,"<>Annulation",dataMail!$G:$G,"<="&(I$1+$B22-1),dataMail!$H:$H,">"&(I$1+$B22-1)),"-") -> 0 | K22: =IF(DAY(EOMONTH(K$1,0))>=$B22,IFERROR(AVERAGEIFS(dataMail!$P:$P,dataMail!$C:$C,"Confirmation",dataMail!$G:$G,"<="&(K$1+$B22-1),dataMail!$H:$H,">"&(K$1+$B22-1)),"-"),"-") -> 120.69333 | L22: =IF(DAY(EOMONTH(K$1,0))>=$B22, 11-COUNTIFS(dataMail!$C:$C,"<>Annulation",dataMail!$G:$G,"<="&(K$1+$B22-1),dataMail!$H:$H,">"&(K$1+$B22-1)),"-") -> 2 | M22: =IF(DAY(EOMONTH(M$1,0))>=$B22,IFERROR(AVERAGEIFS(dataMail!$P:$P,dataMail!$C:$C,"Confirmation",dataMail!$G:$G,"<="&(M$1+$B22-1),dataMail!$H:$H,">"&(M$1+$B22-1)),"-"),"-") -> 178.03067 | N22: =IF(DAY(EOMONTH(M$1,0))>=$B22, 11-COUNTIFS(dataMail!$C:$C,"<>Annulation",dataMail!$G:$G,"<="&(M$1+$B22-1),dataMail!$H:$H,">"&(M$1+$B22-1)),"-") -> 3 | O22: =IF(DAY(EOMONTH(O$1,0))>=$B22,IFERROR(AVERAGEIFS(dataMail!$P:$P,dataMail!$C:$C,"Confirmation",dataMail!$G:$G,"<="&(O$1+$B22-1),dataMail!$H:$H,">"&(O$1+$B22-1)),"-"),"-") -> 114.33867 | P22: =IF(DAY(EOMONTH(O$1,0))>=$B22, 11-COUNTIFS(dataMail!$C:$C,"<>Annulation",dataMail!$G:$G,"<="&(O$1+$B22-1),dataMail!$H:$H,">"&(O$1+$B22-1)),"-") -> 8 | Q22: =IF(DAY(EOMONTH(Q$1,0))>=$B22,IFERROR(AVERAGEIFS(dataMail!$P:$P,dataMail!$C:$C,"Confirmation",dataMail!$G:$G,"<="&(Q$1+$B22-1),dataMail!$H:$H,">"&(Q$1+$B22-1)),"-"),"-") -> 195.744 | R22: =IF(DAY(EOMONTH(Q$1,0))>=$B22, 11-COUNTIFS(dataMail!$C:$C,"<>Annulation",dataMail!$G:$G,"<="&(Q$1+$B22-1),dataMail!$H:$H,">"&(Q$1+$B22-1)),"-") -> 10 | S22: =IF(DAY(EOMONTH(S$1,0))>=$B22,IFERROR(AVERAGEIFS(dataMail!$P:$P,dataMail!$C:$C,"Confirmation",dataMail!$G:$G,"<="&(S$1+$B22-1),dataMail!$H:$H,">"&(S$1+$B22-1)),"-"),"-") -> - | T22: =IF(DAY(EOMONTH(S$1,0))>=$B22, 11-COUNTIFS(dataMail!$C:$C,"<>Annulation",dataMail!$G:$G,"<="&(S$1+$B22-1),dataMail!$H:$H,">"&(S$1+$B22-1)),"-") -> 11 | U22: =IF(DAY(EOMONTH(U$1,0))>=$B22,IFERROR(AVERAGEIFS(dataMail!$P:$P,dataMail!$C:$C,"Confirmation",dataMail!$G:$G,"<="&(U$1+$B22-1),dataMail!$H:$H,">"&(U$1+$B22-1)),"-"),"-") -> 135.368 | V22: =IF(DAY(EOMONTH(U$1,0))>=$B22, 11-COUNTIFS(dataMail!$C:$C,"<>Annulation",dataMail!$G:$G,"<="&(U$1+$B22-1),dataMail!$H:$H,">"&(U$1+$B22-1)),"-") -> 7 | W22: =IF(DAY(EOMONTH(W$1,0))>=$B22,IFERROR(AVERAGEIFS(dataMail!$P:$P,dataMail!$C:$C,"Confirmation",dataMail!$G:$G,"<="&(W$1+$B22-1),dataMail!$H:$H,">"&(W$1+$B22-1)),"-"),"-") -> 277 | X22: =IF(DAY(EOMONTH(W$1,0))>=$B22, 11-COUNTIFS(dataMail!$C:$C,"<>Annulation",dataMail!$G:$G,"<="&(W$1+$B22-1),dataMail!$H:$H,">"&(W$1+$B22-1)),"-") -> 9 | Y22: =IF(DAY(EOMONTH(Y$1,0))>=$B22,IFERROR(AVERAGEIFS(dataMail!$P:$P,dataMail!$C:$C,"Confirmation",dataMail!$G:$G,"<="&(Y$1+$B22-1),dataMail!$H:$H,">"&(Y$1+$B22-1)),"-"),"-") -> 124.576 | Z22: =IF(DAY(EOMONTH(Y$1,0))>=$B22, 11-COUNTIFS(dataMail!$C:$C,"<>Annulation",dataMail!$G:$G,"<="&(Y$1+$B22-1),dataMail!$H:$H,">"&(Y$1+$B22-1)),"-") -> 10 | AA22: =IF(DAY(EOMONTH(AA$1,0))>=$B22,IFERROR(AVERAGEIFS(dataMail!$P:$P,dataMail!$C:$C,"Confirmation",dataMail!$G:$G,"<="&(AA$1+$B22-1),dataMail!$H:$H,">"&(AA$1+$B22-1)),"-"),"-") -> - | AB22: =IF(DAY(EOMONTH(AA$1,0))>=$B22, 11-COUNTIFS(dataMail!$C:$C,"<>Annulation",dataMail!$G:$G,"<="&(AA$1+$B22-1),dataMail!$H:$H,">"&(AA$1+$B22-1)),"-") -> 11 | AC22: =IF(DAY(EOMONTH(AC$1,0))>=$B22,IFERROR(AVERAGEIFS(dataMail!$P:$P,dataMail!$C:$C,"Confirmation",dataMail!$G:$G,"<="&(AC$1+$B22-1),dataMail!$H:$H,">"&(AC$1+$B22-1)),"-"),"-") -> 89.28 | AD22: =IF(DAY(EOMONTH(AC$1,0))>=$B22, 11-COUNTIFS(dataMail!$C:$C,"<>Annulation",dataMail!$G:$G,"<="&(AC$1+$B22-1),dataMail!$H:$H,">"&(AC$1+$B22-1)),"-") -> 10 | AE22: =IF(DAY(EOMONTH(AE$1,0))>=$B22,IFERROR(AVERAGEIFS(dataMail!$P:$P,dataMail!$C:$C,"Confirmation",dataMail!$G:$G,"<="&(AE$1+$B22-1),dataMail!$H:$H,">"&(AE$1+$B22-1)),"-"),"-") -> 75.52 | AF22: =IF(DAY(EOMONTH(AE$1,0))>=$B22, 11-COUNTIFS(dataMail!$C:$C,"<>Annulation",dataMail!$G:$G,"<="&(AE$1+$B22-1),dataMail!$H:$H,">"&(AE$1+$B22-1)),"-") -> 8 | AG22: =IF(DAY(EOMONTH(AG$1,0))>=$B22,IFERROR(AVERAGEIFS(dataMail!$P:$P,dataMail!$C:$C,"Confirmation",dataMail!$G:$G,"<="&(AG$1+$B22-1),dataMail!$H:$H,">"&(AG$1+$B22-1)),"-"),"-") -> - | AH22: =IF(DAY(EOMONTH(AG$1,0))>=$B22, 11-COUNTIFS(dataMail!$C:$C,"<>Annulation",dataMail!$G:$G,"<="&(AG$1+$B22-1),dataMail!$H:$H,">"&(AG$1+$B22-1)),"-") -> 11
... B41: 31 | C41: =IF(DAY(EOMONTH(C$1,0))>=$B41,IFERROR(AVERAGEIFS(dataMail!$P:$P,dataMail!$C:$C,"Confirmation",dataMail!$G:$G,"<="&(C$1+$B41-1),dataMail!$H:$H,">"&(C$1+$B41-1)),"-"),"-") -> - | D41: =IF(DAY(EOMONTH(C$1,0))>=$B41, 11-COUNTIFS(dataMail!$C:$C,"<>Annulation",dataMail!$G:$G,"<="&(C$1+$B41-1),dataMail!$H:$H,">"&(C$1+$B41-1)),"-") -> - | E41: =IF(DAY(EOMONTH(E$1,0))>=$B41,IFERROR(AVERAGEIFS(dataMail!$P:$P,dataMail!$C:$C,"Confirmation",dataMail!$G:$G,"<="&(E$1+$B41-1),dataMail!$H:$H,">"&(E$1+$B41-1)),"-"),"-") -> 108.25778 | F41: =IF(DAY(EOMONTH(E$1,0))>=$B41, 11-COUNTIFS(dataMail!$C:$C,"<>Annulation",dataMail!$G:$G,"<="&(E$1+$B41-1),dataMail!$H:$H,">"&(E$1+$B41-1)),"-") -> 2 | G41: =IF(DAY(EOMONTH(G$1,0))>=$B41,IFERROR(AVERAGEIFS(dataMail!$P:$P,dataMail!$C:$C,"Confirmation",dataMail!$G:$G,"<="&(G$1+$B41-1),dataMail!$H:$H,">"&(G$1+$B41-1)),"-"),"-") -> 107.62829 | H41: =IF(DAY(EOMONTH(G$1,0))>=$B41, 11-COUNTIFS(dataMail!$C:$C,"<>Annulation",dataMail!$G:$G,"<="&(G$1+$B41-1),dataMail!$H:$H,">"&(G$1+$B41-1)),"-") -> 4 | I41: =IF(DAY(EOMONTH(I$1,0))>=$B41,IFERROR(AVERAGEIFS(dataMail!$P:$P,dataMail!$C:$C,"Confirmation",dataMail!$G:$G,"<="&(I$1+$B41-1),dataMail!$H:$H,">"&(I$1+$B41-1)),"-"),"-") -> - | J41: =IF(DAY(EOMONTH(I$1,0))>=$B41, 11-COUNTIFS(dataMail!$C:$C,"<>Annulation",dataMail!$G:$G,"<="&(I$1+$B41-1),dataMail!$H:$H,">"&(I$1+$B41-1)),"-") -> - | K41: =IF(DAY(EOMONTH(K$1,0))>=$B41,IFERROR(AVERAGEIFS(dataMail!$P:$P,dataMail!$C:$C,"Confirmation",dataMail!$G:$G,"<="&(K$1+$B41-1),dataMail!$H:$H,">"&(K$1+$B41-1)),"-"),"-") -> 142.09867 | L41: =IF(DAY(EOMONTH(K$1,0))>=$B41, 11-COUNTIFS(dataMail!$C:$C,"<>Annulation",dataMail!$G:$G,"<="&(K$1+$B41-1),dataMail!$H:$H,">"&(K$1+$B41-1)),"-") -> 2 | M41: =IF(DAY(EOMONTH(M$1,0))>=$B41,IFERROR(AVERAGEIFS(dataMail!$P:$P,dataMail!$C:$C,"Confirmation",dataMail!$G:$G,"<="&(M$1+$B41-1),dataMail!$H:$H,">"&(M$1+$B41-1)),"-"),"-") -> - | N41: =IF(DAY(EOMONTH(M$1,0))>=$B41, 11-COUNTIFS(dataMail!$C:$C,"<>Annulation",dataMail!$G:$G,"<="&(M$1+$B41-1),dataMail!$H:$H,">"&(M$1+$B41-1)),"-") -> - | O41: =IF(DAY(EOMONTH(O$1,0))>=$B41,IFERROR(AVERAGEIFS(dataMail!$P:$P,dataMail!$C:$C,"Confirmation",dataMail!$G:$G,"<="&(O$1+$B41-1),dataMail!$H:$H,">"&(O$1+$B41-1)),"-"),"-") -> 190.13917 | P41: =IF(DAY(EOMONTH(O$1,0))>=$B41, 11-COUNTIFS(dataMail!$C:$C,"<>Annulation",dataMail!$G:$G,"<="&(O$1+$B41-1),dataMail!$H:$H,">"&(O$1+$B41-1)),"-") -> 8 | Q41: =IF(DAY(EOMONTH(Q$1,0))>=$B41,IFERROR(AVERAGEIFS(dataMail!$P:$P,dataMail!$C:$C,"Confirmation",dataMail!$G:$G,"<="&(Q$1+$B41-1),dataMail!$H:$H,">"&(Q$1+$B41-1)),"-"),"-") -> 120.576 | R41: =IF(DAY(EOMONTH(Q$1,0))>=$B41, 11-COUNTIFS(dataMail!$C:$C,"<>Annulation",dataMail!$G:$G,"<="&(Q$1+$B41-1),dataMail!$H:$H,">"&(Q$1+$B41-1)),"-") -> 10 | S41: =IF(DAY(EOMONTH(S$1,0))>=$B41,IFERROR(AVERAGEIFS(dataMail!$P:$P,dataMail!$C:$C,"Confirmation",dataMail!$G:$G,"<="&(S$1+$B41-1),dataMail!$H:$H,">"&(S$1+$B41-1)),"-"),"-") -> - | T41: =IF(DAY(EOMONTH(S$1,0))>=$B41, 11-COUNTIFS(dataMail!$C:$C,"<>Annulation",dataMail!$G:$G,"<="&(S$1+$B41-1),dataMail!$H:$H,">"&(S$1+$B41-1)),"-") -> - | U41: =IF(DAY(EOMONTH(U$1,0))>=$B41,IFERROR(AVERAGEIFS(dataMail!$P:$P,dataMail!$C:$C,"Confirmation",dataMail!$G:$G,"<="&(U$1+$B41-1),dataMail!$H:$H,">"&(U$1+$B41-1)),"-"),"-") -> 146.868 | V41: =IF(DAY(EOMONTH(U$1,0))>=$B41, 11-COUNTIFS(dataMail!$C:$C,"<>Annulation",dataMail!$G:$G,"<="&(U$1+$B41-1),dataMail!$H:$H,">"&(U$1+$B41-1)),"-") -> 9 | W41: =IF(DAY(EOMONTH(W$1,0))>=$B41,IFERROR(AVERAGEIFS(dataMail!$P:$P,dataMail!$C:$C,"Confirmation",dataMail!$G:$G,"<="&(W$1+$B41-1),dataMail!$H:$H,">"&(W$1+$B41-1)),"-"),"-") -> - | X41: =IF(DAY(EOMONTH(W$1,0))>=$B41, 11-COUNTIFS(dataMail!$C:$C,"<>Annulation",dataMail!$G:$G,"<="&(W$1+$B41-1),dataMail!$H:$H,">"&(W$1+$B41-1)),"-") -> - | Y41: =IF(DAY(EOMONTH(Y$1,0))>=$B41,IFERROR(AVERAGEIFS(dataMail!$P:$P,dataMail!$C:$C,"Confirmation",dataMail!$G:$G,"<="&(Y$1+$B41-1),dataMail!$H:$H,">"&(Y$1+$B41-1)),"-"),"-") -> - | Z41: =IF(DAY(EOMONTH(Y$1,0))>=$B41, 11-COUNTIFS(dataMail!$C:$C,"<>Annulation",dataMail!$G:$G,"<="&(Y$1+$B41-1),dataMail!$H:$H,">"&(Y$1+$B41-1)),"-") -> 11 | AA41: =IF(DAY(EOMONTH(AA$1,0))>=$B41,IFERROR(AVERAGEIFS(dataMail!$P:$P,dataMail!$C:$C,"Confirmation",dataMail!$G:$G,"<="&(AA$1+$B41-1),dataMail!$H:$H,">"&(AA$1+$B41-1)),"-"),"-") -> - | AB41: =IF(DAY(EOMONTH(AA$1,0))>=$B41, 11-COUNTIFS(dataMail!$C:$C,"<>Annulation",dataMail!$G:$G,"<="&(AA$1+$B41-1),dataMail!$H:$H,">"&(AA$1+$B41-1)),"-") -> - | AC41: =IF(DAY(EOMONTH(AC$1,0))>=$B41,IFERROR(AVERAGEIFS(dataMail!$P:$P,dataMail!$C:$C,"Confirmation",dataMail!$G:$G,"<="&(AC$1+$B41-1),dataMail!$H:$H,">"&(AC$1+$B41-1)),"-"),"-") -> - | AD41: =IF(DAY(EOMONTH(AC$1,0))>=$B41, 11-COUNTIFS(dataMail!$C:$C,"<>Annulation",dataMail!$G:$G,"<="&(AC$1+$B41-1),dataMail!$H:$H,">"&(AC$1+$B41-1)),"-") -> 11 | AE41: =IF(DAY(EOMONTH(AE$1,0))>=$B41,IFERROR(AVERAGEIFS(dataMail!$P:$P,dataMail!$C:$C,"Confirmation",dataMail!$G:$G,"<="&(AE$1+$B41-1),dataMail!$H:$H,">"&(AE$1+$B41-1)),"-"),"-") -> 115.312 | AF41: =IF(DAY(EOMONTH(AE$1,0))>=$B41, 11-COUNTIFS(dataMail!$C:$C,"<>Annulation",dataMail!$G:$G,"<="&(AE$1+$B41-1),dataMail!$H:$H,">"&(AE$1+$B41-1)),"-") -> 10 | AG41: =IF(DAY(EOMONTH(AG$1,0))>=$B41,IFERROR(AVERAGEIFS(dataMail!$P:$P,dataMail!$C:$C,"Confirmation",dataMail!$G:$G,"<="&(AG$1+$B41-1),dataMail!$H:$H,">"&(AG$1+$B41-1)),"-"),"-") -> - | AH41: =IF(DAY(EOMONTH(AG$1,0))>=$B41, 11-COUNTIFS(dataMail!$C:$C,"<>Annulation",dataMail!$G:$G,"<="&(AG$1+$B41-1),dataMail!$H:$H,">"&(AG$1+$B41-1)),"-") -> -

Sheet TdB par Canal
A1: =IFERROR(__xludf.DUMMYFUNCTION("QUERY(QUERY(dataMail!A1:V4326,""select D,C,I, YEAR(A)*100+(MONTH(A)+1) where C<>'Annulation' ORDER BY A DESC""), "" select Col4, SUM(Col3) GROUP BY Col4 PIVOT Col1"")"),"sum(product(year(Date Rec)100())sum(month(Date Rec)1()))") -> sum(product(year(Date Rec)100())sum(month(Date Rec)1())) | B1: =IFERROR(__xludf.DUMMYFUNCTION("""COMPUTED_VALUE"""),"") | C1: =IFERROR(__xludf.DUMMYFUNCTION("""COMPUTED_VALUE"""),"A-Expedia") -> A-Expedia | D1: =IFERROR(__xludf.DUMMYFUNCTION("""COMPUTED_VALUE"""),"A-Expedia Affiliate Network") -> A-Expedia Affiliate Network | E1: =IFERROR(__xludf.DUMMYFUNCTION("""COMPUTED_VALUE"""),"Agoda2") -> Agoda2 | F1: =IFERROR(__xludf.DUMMYFUNCTION("""COMPUTED_VALUE"""),"American Express Travel") -> American Express Travel | G1: =IFERROR(__xludf.DUMMYFUNCTION("""COMPUTED_VALUE"""),"BookingCom") -> BookingCom | H1: =IFERROR(__xludf.DUMMYFUNCTION("""COMPUTED_VALUE"""),"Ctrip") -> Ctrip | I1: =IFERROR(__xludf.DUMMYFUNCTION("""COMPUTED_VALUE"""),"Expedia") -> Expedia | J1: =IFERROR(__xludf.DUMMYFUNCTION("""COMPUTED_VALUE"""),"Expedia Affiliate Network") -> Expedia Affiliate Network | K1: =IFERROR(__xludf.DUMMYFUNCTION("""COMPUTED_VALUE"""),"HotelBeds") -> HotelBeds | L1: =IFERROR(__xludf.DUMMYFUNCTION("""COMPUTED_VALUE"""),"Hotels.com") -> Hotels.com | M1: =IFERROR(__xludf.DUMMYFUNCTION("""COMPUTED_VALUE"""),"Reseliva") -> Reseliva | N1: =IFERROR(__xludf.DUMMYFUNCTION("""COMPUTED_VALUE"""),"Reseliva Pannel") -> Reseliva Pannel
A3: =IFERROR(__xludf.DUMMYFUNCTION("""COMPUTED_VALUE"""),202503.0) -> 202503 | G3: =IFERROR(__xludf.DUMMYFUNCTION("""COMPUTED_VALUE"""),5.0) -> 5
A4: =IFERROR(__xludf.DUMMYFUNCTION("""COMPUTED_VALUE"""),202504.0) -> 202504 | M4: =IFERROR(__xludf.DUMMYFUNCTION("""COMPUTED_VALUE"""),6.0) -> 6
A5: =IFERROR(__xludf.DUMMYFUNCTION("""COMPUTED_VALUE"""),202505.0) -> 202505 | G5: =IFERROR(__xludf.DUMMYFUNCTION("""COMPUTED_VALUE"""),5.0) -> 5 | J5: =IFERROR(__xludf.DUMMYFUNCTION("""COMPUTED_VALUE"""),1.0) -> 1
A6: =IFERROR(__xludf.DUMMYFUNCTION("""COMPUTED_VALUE"""),202506.0) -> 202506 | D6: =IFERROR(__xludf.DUMMYFUNCTION("""COMPUTED_VALUE"""),5.0) -> 5 | G6: =IFERROR(__xludf.DUMMYFUNCTION("""COMPUTED_VALUE"""),7.0) -> 7 | J6: =IFERROR(__xludf.DUMMYFUNCTION("""COMPUTED_VALUE"""),4.0) -> 4
A7: =IFERROR(__xludf.DUMMYFUNCTION("""COMPUTED_VALUE"""),202507.0) -> 202507 | G7: =IFERROR(__xludf.DUMMYFUNCTION("""COMPUTED_VALUE"""),13.0) -> 13 | M7: =IFERROR(__xludf.DUMMYFUNCTION("""COMPUTED_VALUE"""),5.0) -> 5 | N7: =IFERROR(__xludf.DUMMYFUNCTION("""COMPUTED_VALUE"""),3.0) -> 3
A8: =IFERROR(__xludf.DUMMYFUNCTION("""COMPUTED_VALUE"""),202508.0) -> 202508 | C8: =IFERROR(__xludf.DUMMYFUNCTION("""COMPUTED_VALUE"""),25.0) -> 25 | G8: =IFERROR(__xludf.DUMMYFUNCTION("""COMPUTED_VALUE"""),26.0) -> 26 | J8: =IFERROR(__xludf.DUMMYFUNCTION("""COMPUTED_VALUE"""),1.0) -> 1 | K8: =IFERROR(__xludf.DUMMYFUNCTION("""COMPUTED_VALUE"""),1.0) -> 1 | M8: =IFERROR(__xludf.DUMMYFUNCTION("""COMPUTED_VALUE"""),1.0) -> 1 | N8: =IFERROR(__xludf.DUMMYFUNCTION("""COMPUTED_VALUE"""),5.0) -> 5
A9: =IFERROR(__xludf.DUMMYFUNCTION("""COMPUTED_VALUE"""),202509.0) -> 202509 | G9: =IFERROR(__xludf.DUMMYFUNCTION("""COMPUTED_VALUE"""),70.0) -> 70 | K9: =IFERROR(__xludf.DUMMYFUNCTION("""COMPUTED_VALUE"""),5.0) -> 5 | M9: =IFERROR(__xludf.DUMMYFUNCTION("""COMPUTED_VALUE"""),5.0) -> 5 | N9: =IFERROR(__xludf.DUMMYFUNCTION("""COMPUTED_VALUE"""),1.0) -> 1
A10: =IFERROR(__xludf.DUMMYFUNCTION("""COMPUTED_VALUE"""),202510.0) -> 202510 | E10: =IFERROR(__xludf.DUMMYFUNCTION("""COMPUTED_VALUE"""),8.0) -> 8 | G10: =IFERROR(__xludf.DUMMYFUNCTION("""COMPUTED_VALUE"""),295.0) -> 295 | K10: =IFERROR(__xludf.DUMMYFUNCTION("""COMPUTED_VALUE"""),2.0) -> 2 | M10: =IFERROR(__xludf.DUMMYFUNCTION("""COMPUTED_VALUE"""),21.0) -> 21 | N10: =IFERROR(__xludf.DUMMYFUNCTION("""COMPUTED_VALUE"""),41.0) -> 41
A11: =IFERROR(__xludf.DUMMYFUNCTION("""COMPUTED_VALUE"""),202511.0) -> 202511 | G11: =IFERROR(__xludf.DUMMYFUNCTION("""COMPUTED_VALUE"""),236.0) -> 236 | J11: =IFERROR(__xludf.DUMMYFUNCTION("""COMPUTED_VALUE"""),5.0) -> 5 | L11: =IFERROR(__xludf.DUMMYFUNCTION("""COMPUTED_VALUE"""),1.0) -> 1 | M11: =IFERROR(__xludf.DUMMYFUNCTION("""COMPUTED_VALUE"""),15.0) -> 15 | N11: =IFERROR(__xludf.DUMMYFUNCTION("""COMPUTED_VALUE"""),32.0) -> 32
A12: =IFERROR(__xludf.DUMMYFUNCTION("""COMPUTED_VALUE"""),202512.0) -> 202512 | D12: =IFERROR(__xludf.DUMMYFUNCTION("""COMPUTED_VALUE"""),1.0) -> 1 | G12: =IFERROR(__xludf.DUMMYFUNCTION("""COMPUTED_VALUE"""),203.0) -> 203 | J12: =IFERROR(__xludf.DUMMYFUNCTION("""COMPUTED_VALUE"""),11.0) -> 11 | M12: =IFERROR(__xludf.DUMMYFUNCTION("""COMPUTED_VALUE"""),12.0) -> 12 | N12: =IFERROR(__xludf.DUMMYFUNCTION("""COMPUTED_VALUE"""),41.0) -> 41
A13: =IFERROR(__xludf.DUMMYFUNCTION("""COMPUTED_VALUE"""),202601.0) -> 202601 | E13: =IFERROR(__xludf.DUMMYFUNCTION("""COMPUTED_VALUE"""),5.0) -> 5 | F13: =IFERROR(__xludf.DUMMYFUNCTION("""COMPUTED_VALUE"""),3.0) -> 3 | G13: =IFERROR(__xludf.DUMMYFUNCTION("""COMPUTED_VALUE"""),291.0) -> 291 | I13: =IFERROR(__xludf.DUMMYFUNCTION("""COMPUTED_VALUE"""),3.0) -> 3 | J13: =IFERROR(__xludf.DUMMYFUNCTION("""COMPUTED_VALUE"""),1.0) -> 1 | K13: =IFERROR(__xludf.DUMMYFUNCTION("""COMPUTED_VALUE"""),4.0) -> 4 | M13: =IFERROR(__xludf.DUMMYFUNCTION("""COMPUTED_VALUE"""),15.0) -> 15 | N13: =IFERROR(__xludf.DUMMYFUNCTION("""COMPUTED_VALUE"""),63.0) -> 63
A14: =IFERROR(__xludf.DUMMYFUNCTION("""COMPUTED_VALUE"""),202602.0) -> 202602 | E14: =IFERROR(__xludf.DUMMYFUNCTION("""COMPUTED_VALUE"""),19.0) -> 19 | G14: =IFERROR(__xludf.DUMMYFUNCTION("""COMPUTED_VALUE"""),221.0) -> 221 | J14: =IFERROR(__xludf.DUMMYFUNCTION("""COMPUTED_VALUE"""),6.0) -> 6 | K14: =IFERROR(__xludf.DUMMYFUNCTION("""COMPUTED_VALUE"""),4.0) -> 4 | L14: =IFERROR(__xludf.DUMMYFUNCTION("""COMPUTED_VALUE"""),1.0) -> 1 | M14: =IFERROR(__xludf.DUMMYFUNCTION("""COMPUTED_VALUE"""),2.0) -> 2 | N14: =IFERROR(__xludf.DUMMYFUNCTION("""COMPUTED_VALUE"""),15.0) -> 15
A15: =IFERROR(__xludf.DUMMYFUNCTION("""COMPUTED_VALUE"""),202603.0) -> 202603 | E15: =IFERROR(__xludf.DUMMYFUNCTION("""COMPUTED_VALUE"""),8.0) -> 8 | G15: =IFERROR(__xludf.DUMMYFUNCTION("""COMPUTED_VALUE"""),191.0) -> 191 | J15: =IFERROR(__xludf.DUMMYFUNCTION("""COMPUTED_VALUE"""),9.0) -> 9 | K15: =IFERROR(__xludf.DUMMYFUNCTION("""COMPUTED_VALUE"""),1.0) -> 1 | M15: =IFERROR(__xludf.DUMMYFUNCTION("""COMPUTED_VALUE"""),19.0) -> 19 | N15: =IFERROR(__xludf.DUMMYFUNCTION("""COMPUTED_VALUE"""),17.0) -> 17
A16: =IFERROR(__xludf.DUMMYFUNCTION("""COMPUTED_VALUE"""),202604.0) -> 202604 | E16: =IFERROR(__xludf.DUMMYFUNCTION("""COMPUTED_VALUE"""),2.0) -> 2 | G16: =IFERROR(__xludf.DUMMYFUNCTION("""COMPUTED_VALUE"""),279.0) -> 279 | J16: =IFERROR(__xludf.DUMMYFUNCTION("""COMPUTED_VALUE"""),12.0) -> 12 | K16: =IFERROR(__xludf.DUMMYFUNCTION("""COMPUTED_VALUE"""),4.0) -> 4 | M16: =IFERROR(__xludf.DUMMYFUNCTION("""COMPUTED_VALUE"""),23.0) -> 23 | N16: =IFERROR(__xludf.DUMMYFUNCTION("""COMPUTED_VALUE"""),71.0) -> 71
A17: =IFERROR(__xludf.DUMMYFUNCTION("""COMPUTED_VALUE"""),202605.0) -> 202605 | E17: =IFERROR(__xludf.DUMMYFUNCTION("""COMPUTED_VALUE"""),5.0) -> 5 | G17: =IFERROR(__xludf.DUMMYFUNCTION("""COMPUTED_VALUE"""),256.0) -> 256 | H17: =IFERROR(__xludf.DUMMYFUNCTION("""COMPUTED_VALUE"""),7.0) -> 7 | I17: =IFERROR(__xludf.DUMMYFUNCTION("""COMPUTED_VALUE"""),3.0) -> 3 | J17: =IFERROR(__xludf.DUMMYFUNCTION("""COMPUTED_VALUE"""),1.0) -> 1 | M17: =IFERROR(__xludf.DUMMYFUNCTION("""COMPUTED_VALUE"""),2.0) -> 2 | N17: =IFERROR(__xludf.DUMMYFUNCTION("""COMPUTED_VALUE"""),33.0) -> 33
A18: =IFERROR(__xludf.DUMMYFUNCTION("""COMPUTED_VALUE"""),202606.0) -> 202606 | G18: =IFERROR(__xludf.DUMMYFUNCTION("""COMPUTED_VALUE"""),122.0) -> 122 | M18: =IFERROR(__xludf.DUMMYFUNCTION("""COMPUTED_VALUE"""),10.0) -> 10 | N18: =IFERROR(__xludf.DUMMYFUNCTION("""COMPUTED_VALUE"""),41.0) -> 41
A19: =IFERROR(__xludf.DUMMYFUNCTION("""COMPUTED_VALUE"""),202607.0) -> 202607 | E19: =IFERROR(__xludf.DUMMYFUNCTION("""COMPUTED_VALUE"""),9.0) -> 9 | G19: =IFERROR(__xludf.DUMMYFUNCTION("""COMPUTED_VALUE"""),275.0) -> 275 | H19: =IFERROR(__xludf.DUMMYFUNCTION("""COMPUTED_VALUE"""),9.0) -> 9 | J19: =IFERROR(__xludf.DUMMYFUNCTION("""COMPUTED_VALUE"""),16.0) -> 16 | K19: =IFERROR(__xludf.DUMMYFUNCTION("""COMPUTED_VALUE"""),2.0) -> 2 | M19: =IFERROR(__xludf.DUMMYFUNCTION("""COMPUTED_VALUE"""),13.0) -> 13 | N19: =IFERROR(__xludf.DUMMYFUNCTION("""COMPUTED_VALUE"""),81.0) -> 81
A20: =IFERROR(__xludf.DUMMYFUNCTION("""COMPUTED_VALUE"""),202608.0) -> 202608 | E20: =IFERROR(__xludf.DUMMYFUNCTION("""COMPUTED_VALUE"""),2.0) -> 2 | G20: =IFERROR(__xludf.DUMMYFUNCTION("""COMPUTED_VALUE"""),142.0) -> 142 | H20: =IFERROR(__xludf.DUMMYFUNCTION("""COMPUTED_VALUE"""),6.0) -> 6 | M20: =IFERROR(__xludf.DUMMYFUNCTION("""COMPUTED_VALUE"""),4.0) -> 4 | N20: =IFERROR(__xludf.DUMMYFUNCTION("""COMPUTED_VALUE"""),4.0) -> 4

Sheet Synthèse Vente Nuitée
A1: =TODAY() -> 46250 | D1: Flux Nuitée | E1: prix moyen | F1: Sup | G1: Résa | H1: Annul | I1: CA th
A2: =A1-1 -> 46249 | C2: Vente Hier | D2: =G2-H2 -> 11 | E2: =IFERROR(round(AVERAGEIFS(dataMail!$P:$P, dataMail!$A:$A,$A2, dataMail!$C:$C,"<>Annulation"),1),"-") -> 144.5 | F2: =SUMIFS(dataMail!S:S,dataMail!A:A,A2, dataMail!C:C,"Confirmation") -> 72 | G2: =SUMIFS(dataMail!$I:$I,dataMail!$A:$A,$A2) -> 11 | H2: =SUMIFS(dataMail!$I:$I,dataMail!$V:$V,$A2,dataMail!C:C,"Annulation") -> 0 | I2: =IFERROR(round(D2*E2+F2,1),0) -> 1661.5
A3: =A2-1 -> 46248 | C3: Vente Avant-hier | D3: =G3-H3 -> 20 | E3: =IFERROR(round(AVERAGEIFS(dataMail!$P:$P, dataMail!$A:$A,$A3, dataMail!$C:$C,"<>Annulation"),1),"-") -> 117.9 | F3: =SUMIFS(dataMail!S:S,dataMail!A:A,A3, dataMail!C:C,"Confirmation") -> 252 | G3: =SUMIFS(dataMail!$I:$I,dataMail!$A:$A,$A3) -> 20 | H3: =SUMIFS(dataMail!$I:$I,dataMail!$V:$V,$A3,dataMail!C:C,"Annulation") -> 0 | I3: =IFERROR(round(D3*E3+F3,1),0) -> 2610
A4: =A3-1 -> 46247 | C4: =IFERROR(__xludf.DUMMYFUNCTION("CONCATENATE(""Vente du "",TO_TEXT(A4))"),"Vente du 13/08/2026") -> Vente du 13/08/2026 | D4: =G4-H4 -> 7 | E4: =IFERROR(round(AVERAGEIFS(dataMail!$P:$P, dataMail!$A:$A,$A4, dataMail!$C:$C,"<>Annulation"),1),"-") -> 229.8 | F4: =SUMIFS(dataMail!S:S,dataMail!A:A,A4, dataMail!C:C,"Confirmation") -> 108 | G4: =SUMIFS(dataMail!$I:$I,dataMail!$A:$A,$A4) -> 7 | H4: =SUMIFS(dataMail!$I:$I,dataMail!$V:$V,$A4,dataMail!C:C,"Annulation") -> 0 | I4: =IFERROR(round(D4*E4+F4,1),0) -> 1716.6
A5: =A4-1 -> 46246 | C5: =IFERROR(__xludf.DUMMYFUNCTION("CONCATENATE(""Vente du "",TO_TEXT(A5))"),"Vente du 12/08/2026") -> Vente du 12/08/2026 | D5: =G5-H5 -> 1 | E5: =IFERROR(round(AVERAGEIFS(dataMail!$P:$P, dataMail!$A:$A,$A5, dataMail!$C:$C,"<>Annulation"),1),"-") -> 89.5 | F5: =SUMIFS(dataMail!S:S,dataMail!A:A,A5, dataMail!C:C,"Confirmation") -> 0 | G5: =SUMIFS(dataMail!$I:$I,dataMail!$A:$A,$A5) -> 1 | H5: =SUMIFS(dataMail!$I:$I,dataMail!$V:$V,$A5,dataMail!C:C,"Annulation") -> 0 | I5: =IFERROR(round(D5*E5+F5,1),0) -> 89.5
A6: =A5-1 -> 46245 | C6: =IFERROR(__xludf.DUMMYFUNCTION("CONCATENATE(""Vente du "",TO_TEXT(A6))"),"Vente du 11/08/2026") -> Vente du 11/08/2026 | D6: =G6-H6 -> 12 | E6: =IFERROR(round(AVERAGEIFS(dataMail!$P:$P, dataMail!$A:$A,$A6, dataMail!$C:$C,"<>Annulation"),1),"-") -> 106.3 | F6: =SUMIFS(dataMail!S:S,dataMail!A:A,A6, dataMail!C:C,"Confirmation") -> 0 | G6: =SUMIFS(dataMail!$I:$I,dataMail!$A:$A,$A6) -> 12 | H6: =SUMIFS(dataMail!$I:$I,dataMail!$V:$V,$A6,dataMail!C:C,"Annulation") -> 0 | I6: =IFERROR(round(D6*E6+F6,1),0) -> 1275.6
A7: =A6-1 -> 46244 | C7: =IFERROR(__xludf.DUMMYFUNCTION("CONCATENATE(""Vente du "",TO_TEXT(A7))"),"Vente du 10/08/2026") -> Vente du 10/08/2026 | D7: =G7-H7 -> 0 | E7: =IFERROR(round(AVERAGEIFS(dataMail!$P:$P, dataMail!$A:$A,$A7, dataMail!$C:$C,"<>Annulation"),1),"-") -> 120 | F7: =SUMIFS(dataMail!S:S,dataMail!A:A,A7, dataMail!C:C,"Confirmation") -> 0 | G7: =SUMIFS(dataMail!$I:$I,dataMail!$A:$A,$A7) -> 14 | H7: =SUMIFS(dataMail!$I:$I,dataMail!$V:$V,$A7,dataMail!C:C,"Annulation") -> 14 | I7: =IFERROR(round(D7*E7+F7,1),0) -> 0
A8: =A7-1 -> 46243 | C8: =IFERROR(__xludf.DUMMYFUNCTION("CONCATENATE(""Vente du "",TO_TEXT(A8))"),"Vente du 09/08/2026") -> Vente du 09/08/2026 | D8: =G8-H8 -> 3 | E8: =IFERROR(round(AVERAGEIFS(dataMail!$P:$P, dataMail!$A:$A,$A8, dataMail!$C:$C,"<>Annulation"),1),"-") -> 211.6 | F8: =SUMIFS(dataMail!S:S,dataMail!A:A,A8, dataMail!C:C,"Confirmation") -> 0 | G8: =SUMIFS(dataMail!$I:$I,dataMail!$A:$A,$A8) -> 15 | H8: =SUMIFS(dataMail!$I:$I,dataMail!$V:$V,$A8,dataMail!C:C,"Annulation") -> 12 | I8: =IFERROR(round(D8*E8+F8,1),0) -> 634.8
C10: Total Semaine | D10: =SUM(D2:D8) -> 54 | E10: =round(AVERAGE(E2:E8),1) -> 145.7 | F10: =SUM(F2:F8) -> 432 | G10: =SUM(G2:G8) -> 80 | H10: =SUM(H2:H8) -> 26 | I10: =round(SUM(I2:I8),1) -> 7988
C11: Total 4 semaines | D11: =SUM(D2:D8)+SUM(D78:D98) -> 250 | E11: =round((SUM(E2:E8)+SUM(E78:E98))/28,1) -> 132.3 | F11: =SUM(F2:F8)+SUM(F78:F98) -> 900 | G11: =SUM(G2:G8)+SUM(G78:G98) -> 434 | H11: =SUM(H2:H8)+SUM(H78:H98) -> 184 | I11: =round(SUM(I2:I8)+SUM(I78:I98),1) -> 35492.1
C13: Disponibilité à J+ | D13: 7 | E13: 30 | F13: 90 | G13: 180
A14: =A1 -> 46250 | C14: Etat à J | D14: =calculStock($A14,$A$14,$A$14+D$13) -> 12 (86%) | E14: =calculStock($A14,$A$14,$A$14+E$13) -> 96 (73%) | F14: =calculStock($A14,$A$14,$A$14+F$13) -> 293 (73%) | G14: =calculStock($A14,$A$14,$A$14+G$13) -> 1062 (51%)
A15: =A2 -> 46249 | C15: Etat à J-1 | D15: =calculStock($A15,$A$14,$A$14+D$13) -> 13 (85%) | E15: =calculStock($A15,$A$14,$A$14+E$13) -> 97 (73%) | F15: =calculStock($A15,$A$14,$A$14+F$13) -> 296 (73%) | G15: =calculStock($A15,$A$14,$A$14+G$13) -> 1073 (51%)
A16: =A3 -> 46248 | C16: Etat à J-2 | D16: =calculStock($A16,$A$14,$A$14+D$13) -> 16 (81%) | E16: =calculStock($A16,$A$14,$A$14+E$13) -> 101 (72%) | F16: =calculStock($A16,$A$14,$A$14+F$13) -> 304 (72%) | G16: =calculStock($A16,$A$14,$A$14+G$13) -> 1085 (50%)
A17: =A8 -> 46243 | C17: Etat à J-7 | D17: =calculStock($A17,$A$14,$A$14+D$13) -> 16 (81%) | E17: =calculStock($A17,$A$14,$A$14+E$13) -> 109 (70%) | F17: =calculStock($A17,$A$14,$A$14+F$13) -> 322 (71%) | G17: =calculStock($A17,$A$14,$A$14+G$13) -> 1109 (49%)
A18: =A14-30 -> 46220 | C18: Etat à J-30 | D18: =calculStock($A18,$A$14,$A$14+D$13) -> 46 (45%) | E18: =calculStock($A18,$A$14,$A$14+E$13) -> 180 (50%) | F18: =calculStock($A18,$A$14,$A$14+F$13) -> 443 (59%) | G18: =calculStock($A18,$A$14,$A$14+G$13) -> 1273 (41%)
A19: =A16-90 -> 46158 | C19: Etat à J-90 | D19: =calculStock($A19,$A$14,$A$14+D$13) -> 68 (19%) | E19: =calculStock($A19,$A$14,$A$14+E$13) -> 271 (25%) | F19: =calculStock($A19,$A$14,$A$14+F$13) -> 632 (42%) | G19: =calculStock($A19,$A$14,$A$14+G$13) -> 1525 (30%)
C21: MPAP | D21: 7 | E21: 30 | F21: 90 | G21: 180
A22: =A14-365 -> 45885 | C22: Etat à J | D22: 35 | E22: 140 | F22: 462 | G22: 1225
D23: Resultat dernière semaine | G23: Résultat dernier mois
C24: Nom | D24: nb Nuitée | E24: prix moyen | F24: Montant | G24: nb Nuitée | H24: prix moyen | I24: Montant
A25: =A1 -> 46250 | B25: =A25-7 -> 46243 | C25: HotelBeds | D25: =SUMIFS(dataMail!$I:$I,dataMail!$A:$A,"<"&$A$25,dataMail!$A:$A,">="&$B$25, dataMail!$D:$D,$C25)-SUMIFS(dataMail!$I:$I,dataMail!$C:$C,"Annulation",dataMail!$V:$V,"<"&$A$25,dataMail!$V:$V,">="&$B$25, dataMail!$D:$D,$C25) -> 0 | E25: =round(IFERROR(AVERAGEIFS(dataMail!$P:$P,dataMail!$A:$A,"<"&$A$25,dataMail!$A:$A,">="&$B$25, dataMail!$C:$C,"<>Annulation",dataMail!$D:$D,$C25),"0"),1) -> 0 | F25: =round(D25*E25,1) -> 0 | G25: =SUMIFS(dataMail!$I:$I,dataMail!$A:$A,"<"&$A$26,dataMail!$A:$A,">="&$B$26, dataMail!$D:$D,$C25)-SUMIFS(dataMail!$I:$I,dataMail!$C:$C,"Annulation",dataMail!$V:$V,"<"&$A$26,dataMail!$V:$V,">="&$B$26,dataMail!$D:$D,$C25) -> 2 | H25: =round(IFERROR(AVERAGEIFS(dataMail!$P:$P,dataMail!$A:$A,"<"&$A$26,dataMail!$A:$A,">="&$B$26, dataMail!$C:$C,"<>Annulation",dataMail!$D:$D,$C25),"0"),1) -> 143.9 | I25: =round(G25*H25,1) -> 287.8
A26: =A2 -> 46249 | B26: =A26-28 -> 46221 | C26: BookingCom | D26: =SUMIFS(dataMail!$I:$I,dataMail!$A:$A,"<"&$A$25,dataMail!$A:$A,">="&$B$25, dataMail!$D:$D,$C26)-SUMIFS(dataMail!$I:$I,dataMail!$C:$C,"Annulation",dataMail!$V:$V,"<"&$A$25,dataMail!$V:$V,">="&$B$25, dataMail!$D:$D,$C26) -> 46 | E26: =round(IFERROR(AVERAGEIFS(dataMail!$P:$P,dataMail!$A:$A,"<"&$A$25,dataMail!$A:$A,">="&$B$25, dataMail!$C:$C,"<>Annulation",dataMail!$D:$D,$C26),"0"),1) -> 136.7 | F26: =ROUND(D26*E26,1) -> 6288.2 | G26: =SUMIFS(dataMail!$I:$I,dataMail!$A:$A,"<"&$A$26,dataMail!$A:$A,">="&$B$26, dataMail!$D:$D,$C26)-SUMIFS(dataMail!$I:$I,dataMail!$C:$C,"Annulation",dataMail!$V:$V,"<"&$A$26,dataMail!$V:$V,">="&$B$26,dataMail!$D:$D,$C26) -> 166 | H26: =round(IFERROR(AVERAGEIFS(dataMail!$P:$P,dataMail!$A:$A,"<"&$A$26,dataMail!$A:$A,">="&$B$26, dataMail!$C:$C,"<>Annulation",dataMail!$D:$D,$C26),"0"),1) -> 126 | I26: =round(G26*H26,1) -> 20916
C27: Reseliva | D27: =SUMIFS(dataMail!$I:$I,dataMail!$A:$A,"<"&$A$25,dataMail!$A:$A,">="&$B$25, dataMail!$D:$D,"="&$C27&"*")-SUMIFS(dataMail!$I:$I,dataMail!$C:$C,"Annulation",dataMail!$V:$V,"<"&$A$25,dataMail!$V:$V,">="&$B$25, dataMail!$D:$D,$C27) -> 4 | E27: =round(IFERROR(AVERAGEIFS(dataMail!$P:$P,dataMail!$A:$A,"<"&$A$25,dataMail!$A:$A,">="&$B$25, dataMail!$C:$C,"<>Annulation",dataMail!$D:$D,$C27),"0"),1) -> 201 | F27: =ROUND(D27*E27,1) -> 804 | G27: =SUMIFS(dataMail!$I:$I,dataMail!$A:$A,"<"&$A$26,dataMail!$A:$A,">="&$B$26, dataMail!$D:$D,"="&$C27&"*")-SUMIFS(dataMail!$I:$I,dataMail!$C:$C,"Annulation",dataMail!$V:$V,"<"&$A$26,dataMail!$V:$V,">="&$B$26,dataMail!$D:$D,$C27) -> 90 | H27: =round(IFERROR(AVERAGEIFS(dataMail!$P:$P,dataMail!$A:$A,"<"&$A$26,dataMail!$A:$A,">="&$B$26, dataMail!$C:$C,"<>Annulation",dataMail!$D:$D,$C27),"0"),1) -> 239.4 | I27: =round(G27*H27,1) -> 21546
C28: Autre | D28: =D10-D26-D25-D27 -> 4 | F28: =IF(A28="","",'Détail Extra'!K12) | G28: =D11-G26-G25-G27 -> -8 | I28: =IF(E28="","",'Détail Extra'!N12)
C29: Période de vente | F29: %
C30: =NOW() -> 46250.276 | D30: =SUMIFS(dataMail!$I:$I,dataMail!$A:$A,"<"&$A$25,dataMail!$A:$A,">="&$B$25,dataMail!$G:$G,"<"&$C31)-SUMIFS(dataMail!$I:$I,dataMail!$V:$V,"<"&$A$25,dataMail!$V:$V,">="&$B$25, dataMail!$G:$G,"<"&$C31,dataMail!C:C,"Annulation") -> 10 | E30: =round(IFERROR(AVERAGEIFS(dataMail!$P:$P,dataMail!$A:$A,"<"&$A$25,dataMail!$A:$A,">="&$B$25, dataMail!$C:$C,"<>Annulation",dataMail!$G:$G,"<"&$C31),"0"),1) -> 76.2 | F30: =ROUND(HLOOKUP(C30,TdB!$C$1:$X$4,4),4) -> 0.7527 | G30: =SUMIFS(dataMail!$I:$I,dataMail!$A:$A,"<"&$A$26,dataMail!$A:$A,">="&$B$26,dataMail!$G:$G,"<"&$C31)-SUMIFS(dataMail!$I:$I,dataMail!$V:$V,"<"&$A$26,dataMail!$V:$V,">="&$B$26, dataMail!$G:$G,"<"&$C31,dataMail!C:C,"Annulation") -> 96 | H30: =round(IFERROR(AVERAGEIFS(dataMail!$P:$P,dataMail!$A:$A,"<"&$A$26,dataMail!$A:$A,">="&$B$26, dataMail!$C:$C,"<>Annulation",dataMail!$G:$G,"<"&$C31),"0"),1) -> 95.9
C31: =EOMONTH(C30,0)+1 -> 46266 | D31: =SUMIFS(dataMail!$I:$I,dataMail!$A:$A,"<"&$A$25,dataMail!$A:$A,">="&$B$25, dataMail!$G:$G,">="&$C31,dataMail!$G:$G,"<"&$C32)-SUMIFS(dataMail!$I:$I,dataMail!$V:$V,"<"&$A$25,dataMail!$V:$V,">="&$B$25,dataMail!$G:$G,">="&$C31,dataMail!$G:$G,"<"&$C32,dataMail!C:C,"Annulation") -> 12 | E31: =round(IFERROR(AVERAGEIFS(dataMail!$P:$P,dataMail!$A:$A,"<"&$A$25,dataMail!$A:$A,">="&$B$25, dataMail!$C:$C,"<>Annulation",dataMail!$G:$G,">="&$C31,dataMail!$G:$G,"<"&$C32),"0"),1) -> 112.4 | F31: =ROUND(HLOOKUP(C31,TdB!$C$1:$X$4,4),4) -> 0.6889 | G31: =SUMIFS(dataMail!$I:$I,dataMail!$A:$A,"<"&$A$26,dataMail!$A:$A,">="&$B$26, dataMail!$G:$G,">="&$C31,dataMail!$G:$G,"<"&$C32)-SUMIFS(dataMail!$I:$I,dataMail!$V:$V,"<"&$A$26,dataMail!$V:$V,">="&$B$26, dataMail!$G:$G,">="&$C31,dataMail!$G:$G,"<"&$C32,dataMail!C:C,"Annulation") -> 44 | H31: =round(IFERROR(AVERAGEIFS(dataMail!$P:$P,dataMail!$A:$A,"<"&$A$26,dataMail!$A:$A,">="&$B$26, dataMail!$C:$C,"<>Annulation",dataMail!$G:$G,">="&$C31,dataMail!$G:$G,"<"&$C32),"0"),1) -> 128
C32: =EOMONTH(C31,0)+1 -> 46296 | D32: =SUMIFS(dataMail!$I:$I,dataMail!$A:$A,"<"&$A$25,dataMail!$A:$A,">="&$B$25, dataMail!$G:$G,">="&$C32,dataMail!$G:$G,"<"&$C33)-SUMIFS(dataMail!$I:$I,dataMail!$V:$V,"<"&$A$25,dataMail!$V:$V,">="&$B$25,dataMail!$G:$G,">="&$C32,dataMail!$G:$G,"<"&$C33,dataMail!C:C,"Annulation") -> 5 | E32: =round(IFERROR(AVERAGEIFS(dataMail!$P:$P,dataMail!$A:$A,"<"&$A$25,dataMail!$A:$A,">="&$B$25, dataMail!$C:$C,"<>Annulation",dataMail!$G:$G,">="&$C32,dataMail!$G:$G,"<"&$C33),"0"),1) -> 245.6 | F32: =ROUND(HLOOKUP(C32,TdB!$C$1:$X$4,4),4) -> 0.7392 | G32: =SUMIFS(dataMail!$I:$I,dataMail!$A:$A,"<"&$A$26,dataMail!$A:$A,">="&$B$26, dataMail!$G:$G,">="&$C32,dataMail!$G:$G,"<"&$C33)-SUMIFS(dataMail!$I:$I,dataMail!$V:$V,"<"&$A$26,dataMail!$V:$V,">="&$B$26, dataMail!$G:$G,">="&$C32,dataMail!$G:$G,"<"&$C33,dataMail!C:C,"Annulation") -> 18 | H32: =round(IFERROR(AVERAGEIFS(dataMail!$P:$P,dataMail!$A:$A,"<"&$A$26,dataMail!$A:$A,">="&$B$26, dataMail!$C:$C,"<>Annulation",dataMail!$G:$G,">="&$C32,dataMail!$G:$G,"<"&$C33),"0"),1) -> 209.5
C33: =EOMONTH(C32,0)+1 -> 46327 | D33: =SUMIFS(dataMail!$I:$I,dataMail!$A:$A,"<"&$A$25,dataMail!$A:$A,">="&$B$25, dataMail!$G:$G,">="&$C33,dataMail!$G:$G,"<"&$C34)-SUMIFS(dataMail!$I:$I,dataMail!$V:$V,"<"&$A$25,dataMail!$V:$V,">="&$B$25,dataMail!$G:$G,">="&$C33,dataMail!$G:$G,"<"&$C34,dataMail!C:C,"Annulation") -> 12 | E33: =round(IFERROR(AVERAGEIFS(dataMail!$P:$P,dataMail!$A:$A,"<"&$A$25,dataMail!$A:$A,">="&$B$25, dataMail!$C:$C,"<>Annulation",dataMail!$G:$G,">="&$C33,dataMail!$G:$G,"<"&$C34),"0"),1) -> 140.3 | F33: =ROUND(HLOOKUP(C33,TdB!$C$1:$X$4,4),4) -> 0.5111 | G33: =SUMIFS(dataMail!$I:$I,dataMail!$A:$A,"<"&$A$26,dataMail!$A:$A,">="&$B$26, dataMail!$G:$G,">="&$C33,dataMail!$G:$G,"<"&$C34)-SUMIFS(dataMail!$I:$I,dataMail!$V:$V,"<"&$A$26,dataMail!$V:$V,">="&$B$26, dataMail!$G:$G,">="&$C33,dataMail!$G:$G,"<"&$C34,dataMail!C:C,"Annulation") -> 7 | H33: =round(IFERROR(AVERAGEIFS(dataMail!$P:$P,dataMail!$A:$A,"<"&$A$26,dataMail!$A:$A,">="&$B$26, dataMail!$C:$C,"<>Annulation",dataMail!$G:$G,">="&$C33,dataMail!$G:$G,"<"&$C34),"0"),1) -> 152.7
C34: =EOMONTH(C33,0)+1 -> 46357 | D34: =SUMIFS(dataMail!$I:$I,dataMail!$A:$A,"<"&$A$25,dataMail!$A:$A,">="&$B$25, dataMail!$G:$G,">="&$C34,dataMail!$G:$G,"<"&$C35)-SUMIFS(dataMail!$I:$I,dataMail!$V:$V,"<"&$A$25,dataMail!$V:$V,">="&$B$25,dataMail!$G:$G,">="&$C34,dataMail!$G:$G,"<"&$C35,dataMail!C:C,"Annulation") -> 9 | E34: =round(IFERROR(AVERAGEIFS(dataMail!$P:$P,dataMail!$A:$A,"<"&$A$25,dataMail!$A:$A,">="&$B$25, dataMail!$C:$C,"<>Annulation",dataMail!$G:$G,">="&$C34,dataMail!$G:$G,"<"&$C35),"0"),1) -> 227.6 | F34: =ROUND(HLOOKUP(C34,TdB!$C$1:$X$4,4),4) -> 0.3414 | G34: =SUMIFS(dataMail!$I:$I,dataMail!$A:$A,"<"&$A$26,dataMail!$A:$A,">="&$B$26, dataMail!$G:$G,">="&$C34,dataMail!$G:$G,"<"&$C35)-SUMIFS(dataMail!$I:$I,dataMail!$V:$V,"<"&$A$26,dataMail!$V:$V,">="&$B$26, dataMail!$G:$G,">="&$C34,dataMail!$G:$G,"<"&$C35,dataMail!C:C,"Annulation") -> 22 | H34: =round(IFERROR(AVERAGEIFS(dataMail!$P:$P,dataMail!$A:$A,"<"&$A$26,dataMail!$A:$A,">="&$B$26, dataMail!$C:$C,"<>Annulation",dataMail!$G:$G,">="&$C34,dataMail!$G:$G,"<"&$C35),"0"),1) -> 188.2
C35: =EOMONTH(C34,0)+1 -> 46388 | D35: =SUMIFS(dataMail!$I:$I,dataMail!$A:$A,"<"&$A$25,dataMail!$A:$A,">="&$B$25, dataMail!$G:$G,">="&$C35,dataMail!$G:$G,"<"&$C36)-SUMIFS(dataMail!$I:$I,dataMail!$V:$V,"<"&$A$25,dataMail!$V:$V,">="&$B$25,dataMail!$G:$G,">="&$C35,dataMail!$G:$G,"<"&$C36,dataMail!C:C,"Annulation") -> -2 | E35: =round(IFERROR(AVERAGEIFS(dataMail!$P:$P,dataMail!$A:$A,"<"&$A$25,dataMail!$A:$A,">="&$B$25, dataMail!$C:$C,"<>Annulation",dataMail!$G:$G,">="&$C35,dataMail!$G:$G,"<"&$C36),"0"),1) -> 175.3 | F35: =ROUND(HLOOKUP(C35,TdB!$C$1:$X$4,4),4) -> 0.2016 | G35: =SUMIFS(dataMail!$I:$I,dataMail!$A:$A,"<"&$A$26,dataMail!$A:$A,">="&$B$26, dataMail!$G:$G,">="&$C35,dataMail!$G:$G,"<"&$C36)-SUMIFS(dataMail!$I:$I,dataMail!$V:$V,"<"&$A$26,dataMail!$V:$V,">="&$B$26, dataMail!$G:$G,">="&$C35,dataMail!$G:$G,"<"&$C36,dataMail!C:C,"Annulation") -> 2 | H35: =round(IFERROR(AVERAGEIFS(dataMail!$P:$P,dataMail!$A:$A,"<"&$A$26,dataMail!$A:$A,">="&$B$26, dataMail!$C:$C,"<>Annulation",dataMail!$G:$G,">="&$C35,dataMail!$G:$G,"<"&$C36),"0"),1) -> 175.8
C36: =EOMONTH(C35,0)+1 -> 46419 | D36: =SUMIFS(dataMail!$I:$I,dataMail!$A:$A,"<"&$A$25,dataMail!$A:$A,">="&$B$25, dataMail!$G:$G,">="&$C36,dataMail!$G:$G,"<"&$C37)-SUMIFS(dataMail!$I:$I,dataMail!$V:$V,"<"&$A$25,dataMail!$V:$V,">="&$B$25,dataMail!$G:$G,">="&$C36,dataMail!$G:$G,"<"&$C37,dataMail!C:C,"Annulation") -> 0 | E36: =round(IFERROR(AVERAGEIFS(dataMail!$P:$P,dataMail!$A:$A,"<"&$A$25,dataMail!$A:$A,">="&$B$25, dataMail!$C:$C,"<>Annulation",dataMail!$G:$G,">="&$C36,dataMail!$G:$G,"<"&$C37),"0"),1) -> 0 | F36: =ROUND(HLOOKUP(C36,TdB!$C$1:$X$4,4),4) -> 0.1935 | G36: =SUMIFS(dataMail!$I:$I,dataMail!$A:$A,"<"&$A$26,dataMail!$A:$A,">="&$B$26, dataMail!$G:$G,">="&$C36,dataMail!$G:$G,"<"&$C37)-SUMIFS(dataMail!$I:$I,dataMail!$V:$V,"<"&$A$26,dataMail!$V:$V,">="&$B$26, dataMail!$G:$G,">="&$C36,dataMail!$G:$G,"<"&$C37,dataMail!C:C,"Annulation") -> 15 | H36: =round(IFERROR(AVERAGEIFS(dataMail!$P:$P,dataMail!$A:$A,"<"&$A$26,dataMail!$A:$A,">="&$B$26, dataMail!$C:$C,"<>Annulation",dataMail!$G:$G,">="&$C36,dataMail!$G:$G,"<"&$C37),"0"),1) -> 185.8
C37: =EOMONTH(C36,0)+1 -> 46447 | D37: =SUMIFS(dataMail!$I:$I,dataMail!$A:$A,"<"&$A$25,dataMail!$A:$A,">="&$B$25, dataMail!$G:$G,">="&$C37,dataMail!$G:$G,"<"&$C38)-SUMIFS(dataMail!$I:$I,dataMail!$V:$V,"<"&$A$25,dataMail!$V:$V,">="&$B$25,dataMail!$G:$G,">="&$C37,dataMail!$G:$G,"<"&$C38,dataMail!C:C,"Annulation") -> 0 | E37: =round(IFERROR(AVERAGEIFS(dataMail!$P:$P,dataMail!$A:$A,"<"&$A$25,dataMail!$A:$A,">="&$B$25, dataMail!$C:$C,"<>Annulation",dataMail!$G:$G,">="&$C37,dataMail!$G:$G,"<"&$C38),"0"),1) -> 170.5 | F37: =ROUND(HLOOKUP(C37,TdB!$C$1:$X$4,4),4) -> 0.0968 | G37: =SUMIFS(dataMail!$I:$I,dataMail!$A:$A,"<"&$A$26,dataMail!$A:$A,">="&$B$26, dataMail!$G:$G,">="&$C37,dataMail!$G:$G,"<"&$C38)-SUMIFS(dataMail!$I:$I,dataMail!$V:$V,"<"&$A$26,dataMail!$V:$V,">="&$B$26, dataMail!$G:$G,">="&$C37,dataMail!$G:$G,"<"&$C38,dataMail!C:C,"Annulation") -> 5 | H37: =round(IFERROR(AVERAGEIFS(dataMail!$P:$P,dataMail!$A:$A,"<"&$A$26,dataMail!$A:$A,">="&$B$26, dataMail!$C:$C,"<>Annulation",dataMail!$G:$G,">="&$C37,dataMail!$G:$G,"<"&$C38),"0"),1) -> 85.2
C38: =EOMONTH(C37,0)+1 -> 46478 | D38: =SUMIFS(dataMail!$I:$I,dataMail!$A:$A,"<"&$A$25,dataMail!$A:$A,">="&$B$25, dataMail!$G:$G,">="&$C38)-2*SUMIFS(dataMail!$I:$I,dataMail!$V:$V,"<"&$A$25,dataMail!$V:$V,">="&$B$25, dataMail!$G:$G,">="&$C38,dataMail!C:C,"Annulation") -> 3 | F38: =IF(A38="","",'Détail Extra'!K22) | G38: =SUMIFS(dataMail!$I:$I,dataMail!$A:$A,"<"&$A$26,dataMail!$A:$A,">="&$B$26, dataMail!$G:$G,">="&$C38)-SUMIFS(dataMail!$I:$I,dataMail!$V:$V,"<"&$A$26,dataMail!$V:$V,">="&$B$26, dataMail!$G:$G,">="&$C38,dataMail!C:C,"Annulation") -> 43 | I38: =IF(E38="","",'Détail Extra'!N22)
C40: =IFERROR(__xludf.DUMMYFUNCTION("{QUERY(dataMail!A1:V2660,""select D,F,G,H,R where (C='Confirmation' OR C='Modification') AND A = DATE '""&TEXT(A2,""YYYY-MM-DD"")&""' LABEL D 'Last Booking'"");QUERY(dataMail!B1:V2660,""select D,F,G,H,R where C='Annulation' AND V = DATE '""&TEXT(A2,""YYYY"&"-MM-DD"")&""' LABEL D 'Last Cancel'"")}"),"Last Booking") -> Last Booking | D40: =IFERROR(__xludf.DUMMYFUNCTION("""COMPUTED_VALUE"""),"Nom") -> Nom | E40: =IFERROR(__xludf.DUMMYFUNCTION("""COMPUTED_VALUE"""),"Arrivée") -> Arrivée | F40: =IFERROR(__xludf.DUMMYFUNCTION("""COMPUTED_VALUE"""),"Fin") -> Fin | G40: =IFERROR(__xludf.DUMMYFUNCTION("""COMPUTED_VALUE"""),"Total N") -> Total N
C41: =IFERROR(__xludf.DUMMYFUNCTION("""COMPUTED_VALUE"""),"BookingCom") -> BookingCom | D41: =IFERROR(__xludf.DUMMYFUNCTION("""COMPUTED_VALUE"""),"Kathalyn von Eyb ") -> Kathalyn von Eyb | E41: =IFERROR(__xludf.DUMMYFUNCTION("""COMPUTED_VALUE"""),46379.0) -> 46379 | F41: =IFERROR(__xludf.DUMMYFUNCTION("""COMPUTED_VALUE"""),46382.0) -> 46382 | G41: =IFERROR(__xludf.DUMMYFUNCTION("""COMPUTED_VALUE"""),521.472) -> 521.472
C42: =IFERROR(__xludf.DUMMYFUNCTION("""COMPUTED_VALUE"""),"BookingCom") -> BookingCom | D42: =IFERROR(__xludf.DUMMYFUNCTION("""COMPUTED_VALUE"""),"Kathalyn von Eyb ") -> Kathalyn von Eyb | E42: =IFERROR(__xludf.DUMMYFUNCTION("""COMPUTED_VALUE"""),46379.0) -> 46379 | F42: =IFERROR(__xludf.DUMMYFUNCTION("""COMPUTED_VALUE"""),46382.0) -> 46382 | G42: =IFERROR(__xludf.DUMMYFUNCTION("""COMPUTED_VALUE"""),628.992) -> 628.992
C43: =IFERROR(__xludf.DUMMYFUNCTION("""COMPUTED_VALUE"""),"BookingCom") -> BookingCom | D43: =IFERROR(__xludf.DUMMYFUNCTION("""COMPUTED_VALUE"""),"Delphine Berger ") -> Delphine Berger | E43: =IFERROR(__xludf.DUMMYFUNCTION("""COMPUTED_VALUE"""),46345.0) -> 46345 | F43: =IFERROR(__xludf.DUMMYFUNCTION("""COMPUTED_VALUE"""),46347.0) -> 46347 | G43: =IFERROR(__xludf.DUMMYFUNCTION("""COMPUTED_VALUE"""),273.904) -> 273.904
C44: =IFERROR(__xludf.DUMMYFUNCTION("""COMPUTED_VALUE"""),"BookingCom") -> BookingCom | D44: =IFERROR(__xludf.DUMMYFUNCTION("""COMPUTED_VALUE"""),"Fauser Johannes ") -> Fauser Johannes | E44: =IFERROR(__xludf.DUMMYFUNCTION("""COMPUTED_VALUE"""),46327.0) -> 46327 | F44: =IFERROR(__xludf.DUMMYFUNCTION("""COMPUTED_VALUE"""),46329.0) -> 46329 | G44: =IFERROR(__xludf.DUMMYFUNCTION("""COMPUTED_VALUE"""),262.99199999999996) -> 262.992
C45: =IFERROR(__xludf.DUMMYFUNCTION("""COMPUTED_VALUE"""),"BookingCom") -> BookingCom | D45: =IFERROR(__xludf.DUMMYFUNCTION("""COMPUTED_VALUE"""),"Bertille Praudel ") -> Bertille Praudel | E45: =IFERROR(__xludf.DUMMYFUNCTION("""COMPUTED_VALUE"""),46254.0) -> 46254 | F45: =IFERROR(__xludf.DUMMYFUNCTION("""COMPUTED_VALUE"""),46255.0) -> 46255 | G45: =IFERROR(__xludf.DUMMYFUNCTION("""COMPUTED_VALUE"""),70.32000000000001) -> 70.32
C46: =IFERROR(__xludf.DUMMYFUNCTION("""COMPUTED_VALUE"""),"Last Cancel") -> Last Cancel | D46: =IFERROR(__xludf.DUMMYFUNCTION("""COMPUTED_VALUE"""),"Nom") -> Nom | E46: =IFERROR(__xludf.DUMMYFUNCTION("""COMPUTED_VALUE"""),"Arrivée") -> Arrivée | F46: =IFERROR(__xludf.DUMMYFUNCTION("""COMPUTED_VALUE"""),"Fin") -> Fin | G46: =IFERROR(__xludf.DUMMYFUNCTION("""COMPUTED_VALUE"""),"Total N") -> Total N
A78: =A8-1 -> 46242 | C78: CA J-8 | D78: =G78-H78 -> 20 | E78: =IFERROR(round(AVERAGEIFS(dataMail!$P:$P, dataMail!$A:$A,$A78, dataMail!$C:$C,"<>Annulation"),1),"-") -> 190.3 | F78: =SUMIFS(dataMail!S:S,dataMail!A:A,A78, dataMail!C:C,"Confirmation") -> 0 | G78: =SUMIFS(dataMail!$I:$I,dataMail!$A:$A,$A78) -> 38 | H78: =SUMIFS(dataMail!$I:$I,dataMail!$V:$V,$A78,dataMail!C:C,"Annulation") -> 18 | I78: =D78*E78+F78 -> 3806
A79: =A78-1 -> 46241 | C79: CA J-9 | D79: =G79-H79 -> 7 | E79: =IFERROR(round(AVERAGEIFS(dataMail!$P:$P, dataMail!$A:$A,$A79, dataMail!$C:$C,"<>Annulation"),1),"-") -> 98.3 | F79: =SUMIFS(dataMail!S:S,dataMail!A:A,A79, dataMail!C:C,"Confirmation") -> 0 | G79: =SUMIFS(dataMail!$I:$I,dataMail!$A:$A,$A79) -> 7 | H79: =SUMIFS(dataMail!$I:$I,dataMail!$V:$V,$A79,dataMail!C:C,"Annulation") -> 0 | I79: =D79*E79+F79 -> 688.1
A80: =A79-1 -> 46240 | C80: CA J-10 | D80: =G80-H80 -> 6 | E80: =IFERROR(round(AVERAGEIFS(dataMail!$P:$P, dataMail!$A:$A,$A80, dataMail!$C:$C,"<>Annulation"),1),"-") -> 120.3 | F80: =SUMIFS(dataMail!S:S,dataMail!A:A,A80, dataMail!C:C,"Confirmation") -> 0 | G80: =SUMIFS(dataMail!$I:$I,dataMail!$A:$A,$A80) -> 13 | H80: =SUMIFS(dataMail!$I:$I,dataMail!$V:$V,$A80,dataMail!C:C,"Annulation") -> 7 | I80: =D80*E80+F80 -> 721.8
A81: =A80-1 -> 46239 | C81: CA J-11 | D81: =G81-H81 -> 5 | E81: =IFERROR(round(AVERAGEIFS(dataMail!$P:$P, dataMail!$A:$A,$A81, dataMail!$C:$C,"<>Annulation"),1),"-") -> 120.8 | F81: =SUMIFS(dataMail!S:S,dataMail!A:A,A81, dataMail!C:C,"Confirmation") -> 0 | G81: =SUMIFS(dataMail!$I:$I,dataMail!$A:$A,$A81) -> 9 | H81: =SUMIFS(dataMail!$I:$I,dataMail!$V:$V,$A81,dataMail!C:C,"Annulation") -> 4 | I81: =D81*E81+F81 -> 604
A82: =A81-1 -> 46238 | C82: CA J-12 | D82: =G82-H82 -> 2 | E82: =IFERROR(round(AVERAGEIFS(dataMail!$P:$P, dataMail!$A:$A,$A82, dataMail!$C:$C,"<>Annulation"),1),"-") -> 177 | F82: =SUMIFS(dataMail!S:S,dataMail!A:A,A82, dataMail!C:C,"Confirmation") -> 72 | G82: =SUMIFS(dataMail!$I:$I,dataMail!$A:$A,$A82) -> 8 | H82: =SUMIFS(dataMail!$I:$I,dataMail!$V:$V,$A82,dataMail!C:C,"Annulation") -> 6 | I82: =D82*E82+F82 -> 426
A83: =A82-1 -> 46237 | C83: CA J-13 | D83: =G83-H83 -> 4 | E83: =IFERROR(round(AVERAGEIFS(dataMail!$P:$P, dataMail!$A:$A,$A83, dataMail!$C:$C,"<>Annulation"),1),"-") -> 141 | F83: =SUMIFS(dataMail!S:S,dataMail!A:A,A83, dataMail!C:C,"Confirmation") -> 72 | G83: =SUMIFS(dataMail!$I:$I,dataMail!$A:$A,$A83) -> 12 | H83: =SUMIFS(dataMail!$I:$I,dataMail!$V:$V,$A83,dataMail!C:C,"Annulation") -> 8 | I83: =D83*E83+F83 -> 636
A84: =A83-1 -> 46236 | C84: CA J-14 | D84: =G84-H84 -> 9 | E84: =IFERROR(round(AVERAGEIFS(dataMail!$P:$P, dataMail!$A:$A,$A84, dataMail!$C:$C,"<>Annulation"),1),"-") -> 119.8 | F84: =SUMIFS(dataMail!S:S,dataMail!A:A,A84, dataMail!C:C,"Confirmation") -> 0 | G84: =SUMIFS(dataMail!$I:$I,dataMail!$A:$A,$A84) -> 16 | H84: =SUMIFS(dataMail!$I:$I,dataMail!$V:$V,$A84,dataMail!C:C,"Annulation") -> 7 | I84: =D84*E84+F84 -> 1078.2
A85: =A84-1 -> 46235 | C85: CA J-15 | D85: =G85-H85 -> 2 | E85: =IFERROR(round(AVERAGEIFS(dataMail!$P:$P, dataMail!$A:$A,$A85, dataMail!$C:$C,"<>Annulation"),1),"-") -> 92.6 | F85: =SUMIFS(dataMail!S:S,dataMail!A:A,A85, dataMail!C:C,"Confirmation") -> 0 | G85: =SUMIFS(dataMail!$I:$I,dataMail!$A:$A,$A85) -> 2 | H85: =SUMIFS(dataMail!$I:$I,dataMail!$V:$V,$A85,dataMail!C:C,"Annulation") -> 0 | I85: =D85*E85+F85 -> 185.2
A86: =A85-1 -> 46234 | C86: CA J-16 | D86: =G86-H86 -> 11 | E86: =IFERROR(round(AVERAGEIFS(dataMail!$P:$P, dataMail!$A:$A,$A86, dataMail!$C:$C,"<>Annulation"),1),"-") -> 111.7 | F86: =SUMIFS(dataMail!S:S,dataMail!A:A,A86, dataMail!C:C,"Confirmation") -> 0 | G86: =SUMIFS(dataMail!$I:$I,dataMail!$A:$A,$A86) -> 11 | H86: =SUMIFS(dataMail!$I:$I,dataMail!$V:$V,$A86,dataMail!C:C,"Annulation") -> 0 | I86: =D86*E86+F86 -> 1228.7
A87: =A86-1 -> 46233 | C87: CA J-17 | D87: =G87-H87 -> 1 | E87: =IFERROR(round(AVERAGEIFS(dataMail!$P:$P, dataMail!$A:$A,$A87, dataMail!$C:$C,"<>Annulation"),1),"-") -> 105.4 | F87: =SUMIFS(dataMail!S:S,dataMail!A:A,A87, dataMail!C:C,"Confirmation") -> 0 | G87: =SUMIFS(dataMail!$I:$I,dataMail!$A:$A,$A87) -> 7 | H87: =SUMIFS(dataMail!$I:$I,dataMail!$V:$V,$A87,dataMail!C:C,"Annulation") -> 6 | I87: =D87*E87+F87 -> 105.4
A88: =A87-1 -> 46232 | C88: CA J-18 | D88: =G88-H88 -> 26 | E88: =IFERROR(round(AVERAGEIFS(dataMail!$P:$P, dataMail!$A:$A,$A88, dataMail!$C:$C,"<>Annulation"),1),"-") -> 190.7 | F88: =SUMIFS(dataMail!S:S,dataMail!A:A,A88, dataMail!C:C,"Confirmation") -> 144 | G88: =SUMIFS(dataMail!$I:$I,dataMail!$A:$A,$A88) -> 45 | H88: =SUMIFS(dataMail!$I:$I,dataMail!$V:$V,$A88,dataMail!C:C,"Annulation") -> 19 | I88: =D88*E88+F88 -> 5102.2
A89: =A88-1 -> 46231 | C89: CA J-19 | D89: =G89-H89 -> 31 | E89: =IFERROR(round(AVERAGEIFS(dataMail!$P:$P, dataMail!$A:$A,$A89, dataMail!$C:$C,"<>Annulation"),1),"-") -> 102.4 | F89: =SUMIFS(dataMail!S:S,dataMail!A:A,A89, dataMail!C:C,"Confirmation") -> 0 | G89: =SUMIFS(dataMail!$I:$I,dataMail!$A:$A,$A89) -> 67 | H89: =SUMIFS(dataMail!$I:$I,dataMail!$V:$V,$A89,dataMail!C:C,"Annulation") -> 36 | I89: =D89*E89+F89 -> 3174.4
A90: =A89-1 -> 46230 | C90: CA J-20 | D90: =G90-H90 -> 5 | E90: =IFERROR(round(AVERAGEIFS(dataMail!$P:$P, dataMail!$A:$A,$A90, dataMail!$C:$C,"<>Annulation"),1),"-") -> 119.1 | F90: =SUMIFS(dataMail!S:S,dataMail!A:A,A90, dataMail!C:C,"Confirmation") -> 0 | G90: =SUMIFS(dataMail!$I:$I,dataMail!$A:$A,$A90) -> 8 | H90: =SUMIFS(dataMail!$I:$I,dataMail!$V:$V,$A90,dataMail!C:C,"Annulation") -> 3 | I90: =D90*E90+F90 -> 595.5
... A217: =A216-1 -> 46103 | C217: CA J-147 | D217: =G217-H217 -> 3 | E217: =IFERROR(round(AVERAGEIFS(dataMail!$P:$P, dataMail!$A:$A,$A217, dataMail!$C:$C,"<>Annulation"),1),"-") -> 320.9 | F217: =SUMIFS(dataMail!S:S,dataMail!A:A,A217, dataMail!C:C,"Confirmation") -> 0 | G217: =SUMIFS(dataMail!$I:$I,dataMail!$A:$A,$A217) -> 13 | H217: =SUMIFS(dataMail!$I:$I,dataMail!$V:$V,$A217,dataMail!C:C,"Annulation") -> 10 | I217: =D217*E217+F217 -> 962.7

Sheet Graphique
C1: Flux | G1: Resa | I1: Annul
A2: ='Synthèse Vente Nuitée'!A2 -> 46249 | B2: ='Synthèse Vente Nuitée'!D2 -> 11 | C2: =AVERAGE(B2:B8) -> 7.7142857 | D2: ='Synthèse Vente Nuitée'!E2 -> 144.5 | E2: =AVERAGE(D2:D8) -> 145.65714 | F2: ='Synthèse Vente Nuitée'!G2 -> 11 | G2: =AVERAGE(F2:F8) -> 11.428571 | H2: ='Synthèse Vente Nuitée'!H2 -> 0 | I2: =AVERAGE(H2:H8) -> 3.7142857
A3: ='Synthèse Vente Nuitée'!A3 -> 46248 | B3: ='Synthèse Vente Nuitée'!D3 -> 20 | C3: =AVERAGE(B3:B9) -> 9 | D3: ='Synthèse Vente Nuitée'!E3 -> 117.9 | E3: =AVERAGE(D3:D9) -> 152.2 | F3: ='Synthèse Vente Nuitée'!G3 -> 20 | G3: =AVERAGE(F3:F9) -> 15.285714 | H3: ='Synthèse Vente Nuitée'!H3 -> 0 | I3: =AVERAGE(H3:H9) -> 6.2857143
A4: ='Synthèse Vente Nuitée'!A4 -> 46247 | B4: ='Synthèse Vente Nuitée'!D4 -> 7 | C4: =AVERAGE(B4:B10) -> 7.1428571 | D4: ='Synthèse Vente Nuitée'!E4 -> 229.8 | E4: =AVERAGE(D4:D10) -> 149.4 | F4: ='Synthèse Vente Nuitée'!G4 -> 7 | G4: =AVERAGE(F4:F10) -> 13.428571 | H4: ='Synthèse Vente Nuitée'!H4 -> 0 | I4: =AVERAGE(H4:H10) -> 6.2857143
A5: ='Synthèse Vente Nuitée'!A5 -> 46246 | B5: ='Synthèse Vente Nuitée'!D5 -> 1 | C5: =AVERAGE(B5:B11) -> 7 | D5: ='Synthèse Vente Nuitée'!E5 -> 89.5 | E5: =AVERAGE(D5:D11) -> 133.75714 | F5: ='Synthèse Vente Nuitée'!G5 -> 1 | G5: =AVERAGE(F5:F11) -> 14.285714 | H5: ='Synthèse Vente Nuitée'!H5 -> 0 | I5: =AVERAGE(H5:H11) -> 7.2857143
A6: ='Synthèse Vente Nuitée'!A6 -> 46245 | B6: ='Synthèse Vente Nuitée'!D6 -> 12 | C6: =AVERAGE(B6:B12) -> 7.5714286 | D6: ='Synthèse Vente Nuitée'!E6 -> 106.3 | E6: =AVERAGE(D6:D12) -> 138.22857 | F6: ='Synthèse Vente Nuitée'!G6 -> 12 | G6: =AVERAGE(F6:F12) -> 15.428571 | H6: ='Synthèse Vente Nuitée'!H6 -> 0 | I6: =AVERAGE(H6:H12) -> 7.8571429
A7: ='Synthèse Vente Nuitée'!A7 -> 46244 | B7: ='Synthèse Vente Nuitée'!D7 -> 0 | C7: =AVERAGE(B7:B13) -> 6.1428571 | D7: ='Synthèse Vente Nuitée'!E7 -> 120 | E7: =AVERAGE(D7:D13) -> 148.32857 | F7: ='Synthèse Vente Nuitée'!G7 -> 14 | G7: =AVERAGE(F7:F13) -> 14.857143 | H7: ='Synthèse Vente Nuitée'!H7 -> 14 | I7: =AVERAGE(H7:H13) -> 8.7142857
A8: ='Synthèse Vente Nuitée'!A8 -> 46243 | B8: ='Synthèse Vente Nuitée'!D8 -> 3 | C8: =AVERAGE(B8:B14) -> 6.7142857 | D8: ='Synthèse Vente Nuitée'!E8 -> 211.6 | E8: =AVERAGE(D8:D14) -> 151.32857 | F8: ='Synthèse Vente Nuitée'!G8 -> 15 | G8: =AVERAGE(F8:F14) -> 14.571429 | H8: ='Synthèse Vente Nuitée'!H8 -> 12 | I8: =AVERAGE(H8:H14) -> 7.8571429
A9: ='Synthèse Vente Nuitée'!A78 -> 46242 | B9: ='Synthèse Vente Nuitée'!D78 -> 20 | C9: =AVERAGE(B9:B15) -> 7.5714286 | D9: ='Synthèse Vente Nuitée'!E78 -> 190.3 | E9: =AVERAGE(D9:D15) -> 138.21429 | F9: ='Synthèse Vente Nuitée'!G78 -> 38 | G9: =AVERAGE(F9:F15) -> 14.714286 | H9: ='Synthèse Vente Nuitée'!H78 -> 18 | I9: =AVERAGE(H9:H15) -> 7.1428571
A10: ='Synthèse Vente Nuitée'!A79 -> 46241 | B10: ='Synthèse Vente Nuitée'!D79 -> 7 | C10: =AVERAGE(B10:B16) -> 5 | D10: ='Synthèse Vente Nuitée'!E79 -> 98.3 | E10: =AVERAGE(D10:D16) -> 124.25714 | F10: ='Synthèse Vente Nuitée'!G79 -> 7 | G10: =AVERAGE(F10:F16) -> 9.5714286 | H10: ='Synthèse Vente Nuitée'!H79 -> 0 | I10: =AVERAGE(H10:H16) -> 4.5714286
A11: ='Synthèse Vente Nuitée'!A80 -> 46240 | B11: ='Synthèse Vente Nuitée'!D80 -> 6 | C11: =AVERAGE(B11:B17) -> 5.5714286 | D11: ='Synthèse Vente Nuitée'!E80 -> 120.3 | E11: =AVERAGE(D11:D17) -> 126.17143 | F11: ='Synthèse Vente Nuitée'!G80 -> 13 | G11: =AVERAGE(F11:F17) -> 10.142857 | H11: ='Synthèse Vente Nuitée'!H80 -> 7 | I11: =AVERAGE(H11:H17) -> 4.5714286
A12: ='Synthèse Vente Nuitée'!A81 -> 46239 | B12: ='Synthèse Vente Nuitée'!D81 -> 5 | C12: =AVERAGE(B12:B18) -> 4.8571429 | D12: ='Synthèse Vente Nuitée'!E81 -> 120.8 | E12: =AVERAGE(D12:D18) -> 124.04286 | F12: ='Synthèse Vente Nuitée'!G81 -> 9 | G12: =AVERAGE(F12:F18) -> 9.2857143 | H12: ='Synthèse Vente Nuitée'!H81 -> 4 | I12: =AVERAGE(H12:H18) -> 4.4285714
A13: ='Synthèse Vente Nuitée'!A82 -> 46238 | B13: ='Synthèse Vente Nuitée'!D82 -> 2 | C13: =AVERAGE(B13:B19) -> 7.8571429 | D13: ='Synthèse Vente Nuitée'!E82 -> 177 | E13: =AVERAGE(D13:D19) -> 134.02857 | F13: ='Synthèse Vente Nuitée'!G82 -> 8 | G13: =AVERAGE(F13:F19) -> 14.428571 | H13: ='Synthèse Vente Nuitée'!H82 -> 6 | I13: =AVERAGE(H13:H19) -> 6.5714286
A14: ='Synthèse Vente Nuitée'!A83 -> 46237 | B14: ='Synthèse Vente Nuitée'!D83 -> 4 | C14: =AVERAGE(B14:B20) -> 12 | D14: ='Synthèse Vente Nuitée'!E83 -> 141 | E14: =AVERAGE(D14:D20) -> 123.37143 | F14: ='Synthèse Vente Nuitée'!G83 -> 12 | G14: =AVERAGE(F14:F20) -> 22.857143 | H14: ='Synthèse Vente Nuitée'!H83 -> 8 | I14: =AVERAGE(H14:H20) -> 10.857143
A15: ='Synthèse Vente Nuitée'!A84 -> 46236 | B15: ='Synthèse Vente Nuitée'!D84 -> 9 | C15: =AVERAGE(B15:B21) -> 12.142857 | D15: ='Synthèse Vente Nuitée'!E84 -> 119.8 | E15: =AVERAGE(D15:D21) -> 120.24286 | F15: ='Synthèse Vente Nuitée'!G84 -> 16 | G15: =AVERAGE(F15:F21) -> 22.285714 | H15: ='Synthèse Vente Nuitée'!H84 -> 7 | I15: =AVERAGE(H15:H21) -> 10.142857
A16: ='Synthèse Vente Nuitée'!A85 -> 46235 | B16: ='Synthèse Vente Nuitée'!D85 -> 2 | C16: =AVERAGE(B16:B22) -> 13.714286 | D16: ='Synthèse Vente Nuitée'!E85 -> 92.6 | E16: =AVERAGE(D16:D22) -> 119 | F16: ='Synthèse Vente Nuitée'!G85 -> 2 | G16: =AVERAGE(F16:F22) -> 22.857143 | H16: ='Synthèse Vente Nuitée'!H85 -> 0 | I16: =AVERAGE(H16:H22) -> 9.1428571
A17: ='Synthèse Vente Nuitée'!A86 -> 46234 | B17: ='Synthèse Vente Nuitée'!D86 -> 11 | C17: =AVERAGE(B17:B23) -> 15.285714 | D17: ='Synthèse Vente Nuitée'!E86 -> 111.7 | E17: =AVERAGE(D17:D23) -> 127.42857 | F17: ='Synthèse Vente Nuitée'!G86 -> 11 | G17: =AVERAGE(F17:F23) -> 25.571429 | H17: ='Synthèse Vente Nuitée'!H86 -> 0 | I17: =AVERAGE(H17:H23) -> 10.285714
A18: ='Synthèse Vente Nuitée'!A87 -> 46233 | B18: ='Synthèse Vente Nuitée'!D87 -> 1 | C18: =AVERAGE(B18:B24) -> 15.714286 | D18: ='Synthèse Vente Nuitée'!E87 -> 105.4 | E18: =AVERAGE(D18:D24) -> 134.1 | F18: ='Synthèse Vente Nuitée'!G87 -> 7 | G18: =AVERAGE(F18:F24) -> 26 | H18: ='Synthèse Vente Nuitée'!H87 -> 6 | I18: =AVERAGE(H18:H24) -> 10.285714
A19: ='Synthèse Vente Nuitée'!A88 -> 46232 | B19: ='Synthèse Vente Nuitée'!D88 -> 26 | C19: =AVERAGE(B19:B25) -> 17.571429 | D19: ='Synthèse Vente Nuitée'!E88 -> 190.7 | E19: =AVERAGE(D19:D25) -> 140.75714 | F19: ='Synthèse Vente Nuitée'!G88 -> 45 | G19: =AVERAGE(F19:F25) -> 27 | H19: ='Synthèse Vente Nuitée'!H88 -> 19 | I19: =AVERAGE(H19:H25) -> 9.4285714
A20: ='Synthèse Vente Nuitée'!A89 -> 46231 | B20: ='Synthèse Vente Nuitée'!D89 -> 31 | C20: =AVERAGE(B20:B26) -> 14.571429 | D20: ='Synthèse Vente Nuitée'!E89 -> 102.4 | E20: =AVERAGE(D20:D26) -> 126.75714 | F20: ='Synthèse Vente Nuitée'!G89 -> 67 | G20: =AVERAGE(F20:F26) -> 21.285714 | H20: ='Synthèse Vente Nuitée'!H89 -> 36 | I20: =AVERAGE(H20:H26) -> 6.7142857
... A71: ='Synthèse Vente Nuitée'!A140 -> 46180 | B71: ='Synthèse Vente Nuitée'!D140 -> 8 | C71: =AVERAGE(B71:B77) -> 5.4285714 | D71: ='Synthèse Vente Nuitée'!E140 -> 277.5 | E71: =AVERAGE(D71:D77) -> 146.45 | F71: ='Synthèse Vente Nuitée'!G140 -> 11 | G71: =AVERAGE(F71:F77) -> 7.4285714 | H71: ='Synthèse Vente Nuitée'!H140 -> 3 | I71: =AVERAGE(H71:H77) -> 10.142857
A72: ='Synthèse Vente Nuitée'!A141 -> 46179 | B72: ='Synthèse Vente Nuitée'!D141 -> 10 | C72: =AVERAGE(B72:B78) -> 4.5714286 | D72: ='Synthèse Vente Nuitée'!E141 -> 135.3 | E72: =AVERAGE(D72:D78) -> 121.75 | F72: ='Synthèse Vente Nuitée'!G141 -> 10 | G72: =AVERAGE(F72:F78) -> 6.4285714 | H72: ='Synthèse Vente Nuitée'!H84 -> 7 | I72: =AVERAGE(H72:H78) -> 10.142857
A73: ='Synthèse Vente Nuitée'!A142 -> 46178 | B73: ='Synthèse Vente Nuitée'!D142 -> 7 | C73: =AVERAGE(B73:B79) -> 3.2857143 | D73: ='Synthèse Vente Nuitée'!E142 -> 121.3 | E73: =AVERAGE(D73:D79) -> 117.58333 | F73: ='Synthèse Vente Nuitée'!G142 -> 7 | G73: =AVERAGE(F73:F79) -> 6.1428571 | H73: ='Synthèse Vente Nuitée'!H85 -> 0 | I73: =AVERAGE(H73:H79) -> 9.1428571
A74: ='Synthèse Vente Nuitée'!A143 -> 46177 | B74: ='Synthèse Vente Nuitée'!D143 -> 10 | C74: =AVERAGE(B74:B80) -> 4.5714286 | D74: ='Synthèse Vente Nuitée'!E143 -> 130.6 | E74: =AVERAGE(D74:D80) -> 117.81667 | F74: ='Synthèse Vente Nuitée'!G143 -> 10 | G74: =AVERAGE(F74:F80) -> 7.8571429 | H74: ='Synthèse Vente Nuitée'!H86 -> 0 | I74: =AVERAGE(H74:H80) -> 10.285714
A75: ='Synthèse Vente Nuitée'!A144 -> 46176 | B75: ='Synthèse Vente Nuitée'!D144 -> 0 | C75: =AVERAGE(B75:B81) -> 4.2857143 | D75: ='Synthèse Vente Nuitée'!E144 -> - | E75: =AVERAGE(D75:D81) -> 119.4 | F75: ='Synthèse Vente Nuitée'!G144 -> 0 | G75: =AVERAGE(F75:F81) -> 7.5714286 | H75: ='Synthèse Vente Nuitée'!H87 -> 6 | I75: =AVERAGE(H75:H81) -> 10.285714
A76: ='Synthèse Vente Nuitée'!A145 -> 46175 | B76: ='Synthèse Vente Nuitée'!D145 -> 2 | C76: =AVERAGE(B76:B82) -> 4.4285714 | D76: ='Synthèse Vente Nuitée'!E145 -> 122.4 | E76: =AVERAGE(D76:D82) -> 117.57143 | F76: ='Synthèse Vente Nuitée'!G145 -> 8 | G76: =AVERAGE(F76:F82) -> 8.1428571 | H76: ='Synthèse Vente Nuitée'!H88 -> 19 | I76: =AVERAGE(H76:H82) -> 9.4285714
A77: ='Synthèse Vente Nuitée'!A146 -> 46174 | B77: ='Synthèse Vente Nuitée'!D146 -> 1 | C77: =AVERAGE(B77:B83) -> 4.7142857 | D77: ='Synthèse Vente Nuitée'!E146 -> 91.6 | E77: =AVERAGE(D77:D83) -> 121.64286 | F77: ='Synthèse Vente Nuitée'!G146 -> 6 | G77: =AVERAGE(F77:F83) -> 8.4285714 | H77: ='Synthèse Vente Nuitée'!H89 -> 36 | I77: =AVERAGE(H77:H83) -> 6.7142857
A78: ='Synthèse Vente Nuitée'!A147 -> 46173 | B78: ='Synthèse Vente Nuitée'!D147 -> 2 | C78: =AVERAGE(B78:B84) -> 6.2857143 | D78: ='Synthèse Vente Nuitée'!E147 -> 129.3 | E78: =AVERAGE(D78:D84) -> 126.45714 | F78: ='Synthèse Vente Nuitée'!G147 -> 4 | G78: =AVERAGE(F78:F84) -> 9.8571429 | H78: ='Synthèse Vente Nuitée'!H90 -> 3 | I78: =AVERAGE(H78:H84) -> 3.2857143
A79: ='Synthèse Vente Nuitée'!A148 -> 46172 | B79: ='Synthèse Vente Nuitée'!D148 -> 1 | C79: =AVERAGE(B79:B85) -> 7.2857143 | D79: ='Synthèse Vente Nuitée'!E148 -> 110.3 | E79: =AVERAGE(D79:D85) -> 127.14286 | F79: ='Synthèse Vente Nuitée'!G148 -> 8 | G79: =AVERAGE(F79:F85) -> 11 | H79: ='Synthèse Vente Nuitée'!H91 -> 0 | I79: =AVERAGE(H79:H85) -> 6.2857143
A80: ='Synthèse Vente Nuitée'!A149 -> 46171 | B80: ='Synthèse Vente Nuitée'!D149 -> 16 | C80: =AVERAGE(B80:B86) -> 9.2857143 | D80: ='Synthèse Vente Nuitée'!E149 -> 122.7 | E80: =AVERAGE(D80:D86) -> 135.04286 | F80: ='Synthèse Vente Nuitée'!G149 -> 19 | G80: =AVERAGE(F80:F86) -> 12.571429 | H80: ='Synthèse Vente Nuitée'!H92 -> 8 | I80: =AVERAGE(H80:H86) -> 6.2857143
A81: ='Synthèse Vente Nuitée'!A150 -> 46170 | B81: ='Synthèse Vente Nuitée'!D150 -> 8 | C81: =AVERAGE(B81:B87) -> 8.2857143 | D81: ='Synthèse Vente Nuitée'!E150 -> 140.1 | E81: =AVERAGE(D81:D87) -> 137.44286 | F81: ='Synthèse Vente Nuitée'!G150 -> 8 | G81: =AVERAGE(F81:F87) -> 11.142857 | H81: ='Synthèse Vente Nuitée'!H93 -> 0 | I81: =AVERAGE(H81:H87) -> 5.5714286
A82: ='Synthèse Vente Nuitée'!A151 -> 46169 | B82: ='Synthèse Vente Nuitée'!D151 -> 1 | C82: =AVERAGE(B82:B88) -> 6.4285714 | D82: ='Synthèse Vente Nuitée'!E151 -> 106.6 | E82: =AVERAGE(D82:D88) -> 129.28571 | F82: ='Synthèse Vente Nuitée'!G151 -> 4 | G82: =AVERAGE(F82:F88) -> 10.857143 | H82: ='Synthèse Vente Nuitée'!H94 -> 0 | I82: =AVERAGE(H82:H88) -> 5.5714286
A83: ='Synthèse Vente Nuitée'!A152 -> 46168 | B83: ='Synthèse Vente Nuitée'!D152 -> 4 | C83: =AVERAGE(B83:B89) -> 7.4285714 | D83: ='Synthèse Vente Nuitée'!E152 -> 150.9 | E83: =AVERAGE(D83:D89) -> 133.95714 | F83: ='Synthèse Vente Nuitée'!G152 -> 10 | G83: =AVERAGE(F83:F89) -> 11.857143 | H83: ='Synthèse Vente Nuitée'!H95 -> 0 | I83: =AVERAGE(H83:H89) -> 5.8571429
... A148: ='Synthèse Vente Nuitée'!A217 -> 46103 | B148: ='Synthèse Vente Nuitée'!D217 -> 3 | C148: =AVERAGE(B148:B154) -> 3 | D148: ='Synthèse Vente Nuitée'!E217 -> 320.9 | E148: =AVERAGE(D148:D154) -> 320.9 | F148: ='Synthèse Vente Nuitée'!G217 -> 13 | G148: =AVERAGE(F148:F154) -> 13 | H148: ='Synthèse Vente Nuitée'!H160 -> 7 | I148: =AVERAGE(H148:H154) -> 7

Sheet dataMail
A1: Date Rec | B1: ref Res | C1: Statut | D1: Source | E1: Ref source | F1: Nom | G1: Arrivée | H1: Fin | I1: nb Nuit | J1: Chambre | K1: Service | L1: Contrat | M1: Pax | N1: promo | O1: Nuitée | P1: Nuitée net | Q1: Sup | R1: Total N | S1: Total S | T1: Total Mail | U1: Info | V1: Dernier Modif
A2: 45900 | B2: 7496325 | C2: Modification | D2: BookingCom | E2: 6277154606 | F2: Nathalie LANGLET | G2: 46022 | H2: 46023 | I2: 1 | J2: DE | K2: BB | L2: STD | M2: 2 | N2: 0.2 | O2: 183.97 | P2: 147.176 | Q2: 0 | R2: 147.176 | S2: 0 | T2: 188.97 | U2: Modification le 07/11/2025/ Contrat :Bed & Breakfast Flex EB Rate PLan (plus de 15 jours Ã l\'avance) genious rate | V2: 45900
A3: 45809 | B3: 7099280 | C3: Confirmation | D3: BookingCom | E3: 6007575514 | F3: Lorena Baroni | G3: 46022 | H3: 46024 | I3: 2 | J3: DE | K3: BB | L3: STD | M3: 2 | N3: 0.2 | O3: 206.94 | P3: 165.552 | Q3: 0 | R3: 331.104 | S3: 0 | T3: 423.88 | U3: / Contrat :BB NRF #new International | V3: 45809
A4: 45913 | B4: 7554269 | C4: Confirmation | D4: BookingCom | E4: 6580205991 | F4: Mandy Wright | G4: 46022 | H4: 46026 | I4: 4 | J4: ST | K4: BB | L4: STD | M4: 2 | N4: 0.2 | O4: 176.11 | P4: 140.888 | Q4: 0 | R4: 563.552 | S4: 0 | T4: 724.44 | U4: / Contrat :Bed & Breakfast Flex EB Rate PLan (plus de 15 jours Ã l\'avance) genious rate | V4: 45913
A5: 45929 | B5: 7623541 | C5: Annulation | D5: BookingCom | E5: 5624453268 | F5: Bouderbala Ahmed Alaa | G5: 46022 | H5: 46023 | I5: 1 | J5: SF | K5: BB | L5: STD | M5: 0 | N5: 0 | O5: 0 | P5: 0 | Q5: 0 | R5: 0 | S5: 0 | T5: 0 | U5: / Contrat :BB NRF #new Early Booker Deal genious rate// Reservation le Mon Sep 29 2025 00:00:00 GMT+0100 (UTC+01:00) | V5: 46022
A6: 46022 | B6: 7976038 | C6: Confirmation | D6: Reseliva Pannel | E6: 7976038 | F6: Bouderbala Ahmed Alaa | G6: 46022 | H6: 46023 | I6: 1 | J6: SF | K6: BB | L6: NRF | M6: 2 | N6: 0 | O6: 599.76 | P6: 599.76 | Q6: 0 | R6: 599.76 | S6: 0 | T6: 604.76 | U6: / Contrat :BB Non Refundable | V6: 46022
A7: 46022 | B7: 7976762 | C7: Confirmation | D7: Reseliva | E7: 7976762 | F7: Stefano Grini | G7: 46022 | H7: 46024 | I7: 2 | J7: DE | K7: BB | L7: NRF | M7: 2 | N7: 0 | O7: 249.84 | P7: 247.3416 | Q7: 0 | R7: 494.6832 | S7: 0 | T7: 509.68 | U7: / Contrat :BB Non Refundable | V7: 46022
A8: 45889 | B8: 7446459 | C8: Annulation | D8: BookingCom | E8: 6353912061 | F8: sun trails | G8: 46023 | H8: 46025 | I8: 2 | J8: ST | K8: BB | L8: STD | M8: 0 | N8: 0 | O8: 0 | P8: 0 | Q8: 0 | R8: 0 | S8: 0 | T8: 0 | U8: / Contrat :Bed & Breakfast Flex EB Rate PLan (plus de 15 jours Ã l\'avance) genious rate// Reservation le Wed Aug 20 2025 00:00:00 GMT+0100 (UTC+01:00) | V8: 45889
A9: 45889 | B9: 7446459 | C9: Annulation | D9: BookingCom | E9: 6353912061 | F9: sun trails | G9: 46023 | H9: 46025 | I9: 2 | J9: DE | K9: BB | L9: STD | M9: 0 | N9: 0 | O9: 0 | P9: 0 | Q9: 0 | R9: 0 | S9: 0 | T9: 0 | U9: / Contrat :Bed & Breakfast Flex EB Rate PLan (plus de 15 jours Ã l\'avance) genious rate// Reservation le Wed Aug 20 2025 00:00:00 GMT+0100 (UTC+01:00) | V9: 45889
A10: 45800 | B10: 7060224 | C10: Confirmation | D10: Expedia Affiliate Network | E10: 2204922438 | F10: MARIA DEL CARMEN RUBIO HIDALGO | G10: 46023 | H10: 46024 | I10: 1 | J10: SF | K10: BB | L10: EXPEDIA | M10: 4 | N10: 0 | O10: 547.57 | P10: 438.056 | Q10: 0 | R10: 438.056 | S10: 0 | T10: 547.57 | U10: / Contrat :Standard Package | V10: 45800
A11: 45935 | B11: 7645947 | C11: Confirmation | D11: BookingCom | E11: 6894769127 | F11: francesca renna | G11: 46023 | H11: 46025 | I11: 2 | J11: DE | K11: BB | L11: STD | M11: 2 | N11: 0.2 | O11: 182.31 | P11: 145.848 | Q11: 0 | R11: 291.696 | S11: 0 | T11: 374.62 | U11: / Contrat :BB NRF #new Early Booker Deal genious rate | V11: 45935
A12: 45968 | B12: 7777362 | C12: Confirmation | D12: BookingCom | E12: 6520635719 | F12: Pierre Verdickt | G12: 46023 | H12: 46024 | I12: 1 | J12: DE | K12: BB | L12: STD | M12: 2 | N12: 0.2 | O12: 191.05 | P12: 152.84 | Q12: 0 | R12: 152.84 | S12: 0 | T12: 196.05 | U12: / Contrat :Bed & Breakfast Flex EB Rate PLan (plus de 15 jours Ã l\'avance) genious rate | V12: 45968
A13: 45936 | B13: 7649484 | C13: Confirmation | D13: Agoda2 | E13: 585819727 | F13: ALBERTO BONETTI | G13: 46023 | H13: 46027 | I13: 4 | J13: SX | K13: BB | L13: NRF | M13: 2 | N13: 0.2 | O13: 265.84 | P13: 212.672 | Q13: 0 | R13: 850.688 | S13: 0 | T13: 1063.36 | U13: / Contrat :Bed & Breakfast NRF - Beds Network - Controlled Exposure | V13: 45936
... A18: 45783 | B18: 6989283 | C18: Annulation | D18: BookingCom | E18: 4483596442 | F18: Stefano Grini | G18: 46024 | H18: 46025 | I18: 1 | J18: DE | K18: BB | L18: STD | M18: 0 | N18: 0 | O18: 0 | P18: 0 | Q18: 0 | R18: 0 | S18: 0 | T18: 0 | U18: Modification le 07/11/2025/ Contrat :BB NRF #new International genious rate// Reservation le Tue May 06 2025 00:00:00 GMT+0100 (UTC+01:00) | V18: 46022
A19: 45922 | B19: 7592910 | C19: Annulation | D19: HotelBeds | E19: 136-3672927 | F19: MANUELA BATALONI | G19: 46024 | H19: 46025 | I19: 1 | J19: DE | K19: BB | L19: GR-BARCOM | M19: 0 | N19: 0 | O19: 0 | P19: 0 | Q19: 0 | R19: 0 | S19: 0 | T19: 0 | U19: *Agency Payment* Child ages for room 1: (8) / Contrat :BED AND BREAKFAST GR-BARCOM// Reservation le Mon Sep 22 2025 00:00:00 GMT+0100 (UTC+01:00) | V19: 45926
A20: 45947 | B20: 7695383 | C20: Confirmation | D20: Reseliva Pannel | E20: 7695383 | F20: No Limited Travel | G20: 46024 | H20: 46025 | I20: 1 | J20: SF | K20: BB | L20: NRF | M20: 2 | N20: 0 | O20: 575.28 | P20: 575.28 | Q20: 0 | R20: 575.28 | S20: 0 | T20: 580.28 | U20: / Contrat :BB Non Refundable | V20: 45947
A21: 45926 | B21: 7607847 | C21: Confirmation | D21: HotelBeds | E21: 136-3674677 | F21: MANUELA BATALONI | G21: 46024 | H21: 46025 | I21: 1 | J21: DE | K21: BB | L21: GR-BARCOM | M21: 3 | N21: 0 | O21: 365.6 | P21: 292.48 | Q21: 0 | R21: 292.48 | S21: 0 | T21: NC | U21: *Agency Payment* Child ages for room 1: (8) / Contrat :BED AND BREAKFAST GR-BARCOM | V21: 45926
A22: 46022 | B22: 7976737 | C22: Confirmation | D22: Reseliva Pannel | E22: 7976737 | F22: Stefano Grini | G22: 46024 | H22: 46025 | I22: 1 | J22: DE | K22: BB | L22: NRF | M22: 2 | N22: 0 | O22: 249.84 | P22: 249.84 | Q22: 0 | R22: 249.84 | S22: 0 | T22: 254.84 | U22: / Contrat :BB Non Refundable | V22: 46022
A23: 45810 | B23: 7100375 | C23: Annulation | D23: A-Expedia Affiliate Network | E23: 2211711908 | F23: Simonetta Colavizza | G23: 46025 | H23: 46030 | I23: 5 | J23: ST | M23: 0 | N23: 0 | O23: 0 | P23: 0 | Q23: 0 | R23: 0 | S23: 0 | T23: 0 | U23: Modification le 02/06/2025/ Contrat :Half board// Reservation le Mon Jun 02 2025 00:00:00 GMT+0100 (GMT+01:00) | V23: 45812
A24: 45812 | B24: 7112016 | C24: Modification | D24: A-Expedia Affiliate Network | E24: 2213775371 | F24: Simonetta Colavizza | G24: 46025 | H24: 46030 | I24: 5 | J24: DE | M24: 2 | N24: 0 | O24: 0 | P24: 0 | Q24: 0 | R24: 0 | S24: 0 | T24: 0 | U24: Modification le 04/06/2025/ Contrat :Half board | V24: 45812
A25: 45942 | B25: 7674402 | C25: Confirmation | D25: BookingCom | E25: 6976566799 | F25: Meekai Johnson | G25: 46025 | H25: 46026 | I25: 1 | J25: DE | K25: BB | L25: STD | M25: 2 | N25: 0.2 | O25: 186.81 | P25: 149.448 | Q25: 0 | R25: 149.448 | S25: 0 | T25: 191.81 | U25: / Contrat :BB NRF #new Early Booker Deal genious rate | V25: 45942
A26: 45947 | B26: 7695386 | C26: Confirmation | D26: Reseliva Pannel | E26: 7695386 | F26: No limited Travel | G26: 46025 | H26: 46027 | I26: 2 | J26: DE | K26: BB | L26: NRF | M26: 2 | N26: 0 | O26: 249.84 | P26: 249.84 | Q26: 0 | R26: 499.68 | S26: 0 | T26: 509.68 | U26: / Contrat :BB Non Refundable | V26: 45947
A27: 45952 | B27: 7717090 | C27: Confirmation | D27: BookingCom | E27: 6274500247 | F27: FRANCESCO MURGANTE | G27: 46025 | H27: 46030 | I27: 5 | J27: SF | K27: BB | L27: STD | M27: 4 | N27: 0.2 | O27: 419.62 | P27: 335.696 | Q27: 0 | R27: 1678.48 | S27: 0 | T27: 2148.1 | U27: / Contrat :Bed & Breakfast Flex EB Rate PLan (plus de 15 jours Ã l\'avance) genious rate | V27: 45952
A28: 45955 | B28: 7729764 | C28: Confirmation | D28: BookingCom | E28: 5457395112 | F28: Tiffany Bernard | G28: 46025 | H28: 46031 | I28: 6 | J28: SX | K28: HALF | L28: STD | M28: 3 | N28: 0.2 | O28: 210.57 | P28: 168.456 | Q28: 54 | R28: 1010.736 | S28: 324 | T28: 1522.62 | U28: / Contrat :HB NRF #new Early Booker Deal genious rate | V28: 45955
A29: 45963 | B29: 7757070 | C29: Confirmation | D29: BookingCom | E29: 6199150316 | F29: Emanuela Moraes | G29: 46025 | H29: 46026 | I29: 1 | J29: DE | K29: BB | L29: STD | M29: 3 | N29: 0.2 | O29: 165.81 | P29: 132.648 | Q29: 0 | R29: 132.648 | S29: 0 | T29: 173.31 | U29: / Contrat :BB NRF #new Early Booker Deal genious rate | V29: 45963
A30: 45988 | B30: 7855729 | C30: Confirmation | D30: BookingCom | E30: 5176796344 | F30: Ruud Koole | G30: 46025 | H30: 46026 | I30: 1 | J30: SU | K30: BB | L30: STD | M30: 2 | N30: 0.2 | O30: 197.82 | P30: 158.256 | Q30: 0 | R30: 158.256 | S30: 0 | T30: 202.82 | U30: / Contrat :Bed & Breakfast Flex EB Rate PLan (plus de 15 jours à l\'avance) genious rate | V30: 45988
A31: 45994 | B31: 7877838 | C31: Annulation | D31: BookingCom | E31: 6800653008 | F31: maraninchi maud | G31: 46025 | H31: 46026 | I31: 1 | J31: SU | K31: BB | L31: STD | M31: 0 | N31: 0 | O31: 0 | P31: 0 | Q31: 0 | R31: 0 | S31: 0 | T31: 0 | U31: / Contrat :Bed & Breakfast Flex EB Rate PLan (plus de 15 jours Ã l\'avance) genious rate// Reservation le Wed Dec 03 2025 00:00:00 GMT+0100 (UTC+01:00) | V31: 46022
A32: 45940 | B32: 7666779 | C32: Confirmation | D32: BookingCom | E32: 5723551950 | F32: Heike Siewert | G32: 46026 | H32: 46033 | I32: 7 | J32: SU | K32: BB | L32: STD | M32: 2 | N32: 0.2 | O32: 195.83 | P32: 156.664 | Q32: 0 | R32: 1096.648 | S32: 0 | T32: 1405.81 | U32: / Contrat :BB NRF #new Early Booker Deal genious rate | V32: 45940
A33: 45952 | B33: 7717168 | C33: Confirmation | D33: BookingCom | E33: 5665036245 | F33: Katrin Ott | G33: 46026 | H33: 46033 | I33: 7 | J33: DE | K33: BB | L33: STD | M33: 2 | N33: 0.2 | O33: 168.08 | P33: 134.464 | Q33: 0 | R33: 941.248 | S33: 0 | T33: 1176.56 | U33: / Contrat :BB NRF #new Early Booker Deal genious rate | V33: 45952
A34: 45955 | B34: 7729232 | C34: Confirmation | D34: BookingCom | E34: 5317537166 | F34: Maria Edeltraud Boxleitner | G34: 46026 | H34: 46033 | I34: 7 | J34: DE | K34: BB | L34: STD | M34: 1 | N34: 0.2 | O34: 168.24 | P34: 134.592 | Q34: 0 | R34: 942.144 | S34: 0 | T34: 1195.18 | U34: / Contrat :BB NRF #new Early Booker Deal genious rate | V34: 45955
A35: 45957 | B35: 7735462 | C35: Confirmation | D35: BookingCom | E35: 6417017923 | F35: Thomas Birner | G35: 46026 | H35: 46027 | I35: 1 | J35: SU | K35: BB | L35: STD | M35: 2 | N35: 0.2 | O35: 192.3 | P35: 153.84 | Q35: 0 | R35: 153.84 | S35: 0 | T35: 197.3 | U35: / Contrat :BB NRF #new Early Booker Deal genious rate | V35: 45957
A36: 45957 | B36: 7735820 | C36: Confirmation | D36: BookingCom | E36: 6996552911 | F36: Alin Cozma | G36: 46026 | H36: 46029 | I36: 3 | J36: ST | K36: BB | L36: STD | M36: 2 | N36: 0.2 | O36: 174.56 | P36: 139.648 | Q36: 0 | R36: 418.944 | S36: 0 | T36: 523.68 | U36: / Contrat :Bed & Breakfast Flex EB Rate PLan (plus de 15 jours Ã l\'avance) genious rate | V36: 45957
... A60: 45973 | B60: 7796000 | C60: Confirmation | D60: BookingCom | E60: 5652155986 | F60: CALIN POPA | G60: 46033 | H60: 46037 | I60: 4 | J60: SU | K60: BB | L60: STD | M60: 2 | N60: 0.2 | O60: 181.19 | P60: 144.952 | Q60: 0 | R60: 579.808 | S60: 0 | T60: 744.76 | U60: / Contrat :BB NRF #new Early Booker Deal genious rate | V60: 45973
A61: 45986 | B61: 7846789 | C61: Confirmation | D61: Expedia Affiliate Network | E61: 2339138161 | F61: Wilhelmus Claessens | G61: 46033 | H61: 46038 | I61: 5 | J61: SU | M61: 2 | N61: 0 | O61: 0 | P61: 0 | Q61: 0 | R61: 0 | S61: 0 | T61: 0 | U61: / Contrat :Half board Package | V61: 45986
A62: 45999 | B62: 7896236 | C62: Confirmation | D62: BookingCom | E62: 5598001869 | F62: Daniel Schreuder | G62: 46033 | H62: 46044 | I62: 11 | J62: DE | K62: BB | L62: STD | M62: 2 | N62: 0.2 | O62: 172.11182 | P62: 137.68945 | Q62: 0 | R62: 1514.584 | S62: 0 | T62: 1948.23 | U62: / Contrat :BB NRF #new Early Booker Deal genious rate | V62: 45999
A63: 46022 | B63: 7975374 | C63: Confirmation | D63: BookingCom | E63: 5331254569 | F63: cristina puscas | G63: 46033 | H63: 46037 | I63: 4 | J63: DE | K63: BB | L63: STD | M63: 2 | N63: 0.2 | O63: 185.51 | P63: 148.408 | Q63: 0 | R63: 593.632 | S63: 0 | T63: 762.04 | U63: / Contrat :BB NRF #new Early Year Deal genious rate | V63: 46022
A64: 45992 | B64: 7871669 | C64: Confirmation | D64: BookingCom | E64: 6135365771 | F64: Jacqueline Woodford | G64: 46034 | H64: 46036 | I64: 2 | J64: DE | K64: BB | L64: STD | M64: 2 | N64: 0.2 | O64: 170.06 | P64: 136.048 | Q64: 0 | R64: 272.096 | S64: 0 | T64: 350.12 | U64: / Contrat :BB NRF #new Early Booker Deal genious rate | V64: 45992
A65: 46014 | B65: 7949146 | C65: Confirmation | D65: BookingCom | E65: 6932432067 | F65: Jeremy Herant | G65: 46034 | H65: 46038 | I65: 4 | J65: SU | K65: BB | L65: STD | M65: 2 | N65: 0.2 | O65: 210.41 | P65: 168.328 | Q65: 0 | R65: 673.312 | S65: 0 | T65: 861.64 | U65: / Contrat :Bed & Breakfast Flex EB Rate PLan (plus de 15 jours Ã l\'avance) genious rate | V65: 46014
A66: 46033 | B66: 8019431 | C66: Confirmation | D66: BookingCom | E66: 5722806341 | F66: Barry Fell | G66: 46034 | H66: 46038 | I66: 4 | J66: DE | K66: BB | L66: STD | M66: 2 | N66: 0.2 | O66: 183.63 | P66: 146.904 | Q66: 0 | R66: 587.616 | S66: 0 | T66: 754.52 | U66: / Contrat :BB NRF #new Early Year Deal genious rate | V66: 46033
A67: 46003 | B67: 7911394 | C67: Annulation | D67: Reseliva Pannel | E67: 7911394 | F67: maryem tarifk | G67: 46035 | H67: 46037 | I67: 2 | J67: SX | K67: BB | L67: NRF | M67: 0 | N67: 0 | O67: 0 | P67: 0 | Q67: 0 | R67: 0 | S67: 0 | T67: 0 | U67: / Contrat :BB Non Refundable // Reservation le Fri Dec 12 2025 00:00:00 GMT+0100 (UTC+01:00) | V67: 46013
A68: 46013 | B68: 7945050 | C68: Confirmation | D68: BookingCom | E68: 6499639364 | F68: Josef Laggner | G68: 46037 | H68: 46042 | I68: 5 | J68: SU | K68: BB | L68: STD | M68: 2 | N68: 0.2 | O68: 210.8 | P68: 168.64 | Q68: 0 | R68: 843.2 | S68: 0 | T68: 1079 | U68: / Contrat :Bed & Breakfast Flex EB Rate PLan (plus de 15 jours Ã l\'avance) genious rate | V68: 46013
A69: 46022 | B69: 7977675 | C69: Modification | D69: BookingCom | E69: 6623019980 | F69: Michael Ellis | G69: 46037 | H69: 46041 | I69: 4 | J69: DE | K69: BB | L69: STD | M69: 2 | N69: 0.2 | O69: 133.84 | P69: 107.072 | Q69: 0 | R69: 428.288 | S69: 0 | T69: 555.36 | U69: Modification le 09/01/2026/ Contrat :BB NRF #new Early Booker Deal genious rate | V69: 46022
A70: 46007 | B70: 7926828 | C70: Confirmation | D70: BookingCom | E70: 5625196407 | F70: Maria Fernandez | G70: 46038 | H70: 46041 | I70: 3 | J70: DE | K70: BB | L70: STD | M70: 2 | N70: 0.2 | O70: 189 | P70: 151.2 | Q70: 0 | R70: 453.6 | S70: 0 | T70: 582 | U70: / Contrat :BB NRF #new Early Booker Deal genious rate | V70: 46007
A71: 46017 | B71: 7961044 | C71: Confirmation | D71: BookingCom | E71: 6797933038 | F71: Laurent Perrin | G71: 46038 | H71: 46040 | I71: 2 | J71: DE | K71: BB | L71: STD | M71: 2 | N71: 0.2 | O71: 205.29 | P71: 164.232 | Q71: 0 | R71: 328.464 | S71: 0 | T71: 420.58 | U71: / Contrat :Bed & Breakfast Flex EB Rate PLan (plus de 15 jours Ã l\'avance) genious rate | V71: 46017
A72: 46025 | B72: 7988254 | C72: Confirmation | D72: BookingCom | E72: 6714955219 | F72: Alessandra Meroni | G72: 46038 | H72: 46040 | I72: 2 | J72: SX | K72: BB | L72: STD | M72: 2 | N72: 0.2 | O72: 261.21 | P72: 208.968 | Q72: 0 | R72: 417.936 | S72: 0 | T72: 1025.98 | U72: / Contrat :BB NRF #new Early Year Deal genious rate | V72: 46025
A73: 46025 | B73: 7988254 | C73: Confirmation | D73: BookingCom | E73: 6714955219 | F73: Alessandra Meroni | G73: 46038 | H73: 46040 | I73: 2 | J73: SU | K73: BB | L73: STD | M73: 3 | N73: 0.2 | O73: 239.28 | P73: 191.424 | Q73: 0 | R73: 382.848 | S73: 0 | T73: 1025.98 | U73: / Contrat :BB NRF #new Early Year Deal genious rate | V73: 46025
... A89: 45893 | B89: 7465906 | C89: Annulation | D89: BookingCom | E89: 6195274914 | F89: Valentina Geria | G89: 46044 | H89: 46045 | I89: 1 | J89: SU | K89: BB | L89: STD | M89: 0 | N89: 0 | O89: 0 | P89: 0 | Q89: 0 | R89: 0 | S89: 0 | T89: 0 | U89: / Contrat :Bed & Breakfast Flex Mobile(App) Rate genious rate// Reservation le Sun Aug 24 2025 00:00:00 GMT+0100 (UTC+01:00) | V89: 46027
A90: 45881 | B90: 7408954 | C90: Confirmation | D90: Expedia Affiliate Network | E90: 2266190463 | F90: Carol Gagnon | G90: 46044 | H90: 46045 | I90: 1 | J90: SU | M90: 2 | N90: 0 | O90: 0 | P90: 0 | Q90: 0 | R90: 0 | S90: 0 | T90: 0 | U90: / Contrat :Half board Package | V90: 45881
A91: 45917 | B91: 7574230 | C91: Annulation | D91: BookingCom | E91: 6271518535 | F91: Ilaria Guarino | G91: 46044 | H91: 46047 | I91: 3 | J91: ST | K91: BB | L91: STD | M91: 0 | N91: 0 | O91: 0 | P91: 0 | Q91: 0 | R91: 0 | S91: 0 | T91: 0 | U91: / Contrat :Bed & Breakfast Flex Mobile(App) Rate genious rate// Reservation le Wed Sep 17 2025 00:00:00 GMT+0100 (UTC+01:00) | V91: 46014
A92: 45952 | B92: 7714911 | C92: Annulation | D92: BookingCom | E92: 6908730201 | F92: Ines Praca | G92: 46044 | H92: 46046 | I92: 2 | J92: DE | K92: BB | L92: STD | M92: 0 | N92: 0 | O92: 0 | P92: 0 | Q92: 0 | R92: 0 | S92: 0 | T92: 0 | U92: / Contrat :BB NRF #new Early Booker Deal genious rate// Reservation le Wed Oct 22 2025 00:00:00 GMT+0100 (UTC+01:00) | V92: 46032
A93: 45968 | B93: 7779224 | C93: Confirmation | D93: Reseliva Pannel | E93: 7779224 | F93: Jean philipe dolmain | G93: 46044 | H93: 46045 | I93: 1 | J93: DE | K93: BB | L93: NRF | M93: 2 | N93: 0 | O93: 239.76 | P93: 239.76 | Q93: 0 | R93: 239.76 | S93: 0 | T93: 244.76 | U93: / Contrat :BB Non Refundable | V93: 45968
A94: 45968 | B94: 7779260 | C94: Confirmation | D94: Reseliva Pannel | E94: 7779260 | F94: Pascal Payraudau | G94: 46044 | H94: 46045 | I94: 1 | J94: DE | K94: BB | L94: NRF | M94: 2 | N94: 0 | O94: 239.76 | P94: 239.76 | Q94: 0 | R94: 239.76 | S94: 0 | T94: 244.76 | U94: / Contrat :BB Non Refundable | V94: 45968
A95: 45990 | B95: 7864220 | C95: Confirmation | D95: BookingCom | E95: 6666552620 | F95: Lidia Martinez Gutierrez | G95: 46044 | H95: 46047 | I95: 3 | J95: DE | K95: BB | L95: STD | M95: 2 | N95: 0.2 | O95: 181.38 | P95: 145.104 | Q95: 0 | R95: 435.312 | S95: 0 | T95: 559.14 | U95: / Contrat :BB NRF #new Early Booker Deal genious rate | V95: 45990
A96: 46019 | B96: 7966317 | C96: Confirmation | D96: BookingCom | E96: 6540931258 | F96: Marcus Howden-Olsbunes | G96: 46044 | H96: 46047 | I96: 3 | J96: SX | K96: BB | L96: STD | M96: 2 | N96: 0.2 | O96: 237.25 | P96: 189.8 | Q96: 0 | R96: 569.4 | S96: 0 | T96: 726.75 | U96: / Contrat :Bed & Breakfast Flex EB Rate PLan (plus de 15 jours Ã l\'avance) genious rate | V96: 46019
A97: 46032 | B97: 8016029 | C97: Confirmation | D97: Reseliva Pannel | E97: 8016029 | F97: Inês Praça | G97: 46044 | H97: 46045 | I97: 1 | J97: DE | K97: BB | L97: NRF | M97: 2 | N97: 0 | O97: 239.76 | P97: 239.76 | Q97: 0 | R97: 239.76 | S97: 0 | T97: 244.76 | U97: / Contrat :BB Non Refundable | V97: 46032
A98: 45988 | B98: 7853773 | C98: Annulation | D98: BookingCom | E98: 5082199989 | F98: Hasan Alsherazi | G98: 46045 | H98: 46047 | I98: 2 | J98: SU | K98: BB | L98: STD | M98: 0 | N98: 0 | O98: 0 | P98: 0 | Q98: 0 | R98: 0 | S98: 0 | T98: 0 | U98: / Contrat :Bed & Breakfast Flex International genious rate// Reservation le Thu Nov 27 2025 00:00:00 GMT+0100 (UTC+01:00) | V98: 46028
A99: 46013 | B99: 7945780 | C99: Confirmation | D99: BookingCom | E99: 6079620404 | F99: Sonia Monteiro | G99: 46045 | H99: 46047 | I99: 2 | J99: DE | K99: BB | L99: STD | M99: 2 | N99: 0.2 | O99: 170.17 | P99: 136.136 | Q99: 0 | R99: 272.272 | S99: 0 | T99: 350.34 | U99: / Contrat :BB NRF #new Early Booker Deal genious rate | V99: 46013
A100: 46017 | B100: 7960958 | C100: Confirmation | D100: Reseliva | E100: 7960958 | F100: Ravjot Virdi | G100: 46045 | H100: 46047 | I100: 2 | J100: ST | K100: BB | L100: NRF | M100: 2 | N100: 0 | O100: 170.82 | P100: 169.1118 | Q100: 0 | R100: 338.2236 | S100: 0 | T100: 351.64 | U100: / Contrat :BB Non Refundable | V100: 46017
A101: 46031 | B101: 8013067 | C101: Confirmation | D101: BookingCom | E101: 5363731924 | F101: Razvan Lica | G101: 46045 | H101: 46048 | I101: 3 | J101: SU | K101: BB | L101: STD | M101: 2 | N101: 0.2 | O101: 208.5 | P101: 166.8 | Q101: 0 | R101: 500.4 | S101: 0 | T101: 640.5 | U101: / Contrat :BB NRF #new Early Year Deal genious rate | V101: 46031
A102: 45895 | B102: 7475314 | C102: Annulation | D102: BookingCom | E102: 5195326566 | F102: Valentina Geria | G102: 46046 | H102: 46047 | I102: 1 | J102: SU | K102: BB | L102: STD | M102: 0 | N102: 0 | O102: 0 | P102: 0 | Q102: 0 | R102: 0 | S102: 0 | T102: 0 | U102: / Contrat :Bed & Breakfast Flex Mobile(App) Rate genious rate// Reservation le Tue Aug 26 2025 00:00:00 GMT+0100 (UTC+01:00) | V102: 46027
... A220: 46011 | B220: 7939392 | C220: Confirmation | D220: BookingCom | E220: 6827242378 | F220: Frederic Chantraine | G220: 46071 | H220: 46075 | I220: 4 | J220: SF | K220: BB | L220: STD | M220: 3 | N220: 0.2 | O220: 387.44 | P220: 309.952 | Q220: 0 | R220: 1239.808 | S220: 0 | T220: 1579.76 | U220: / Contrat :BB NRF #new Early Booker Deal genious rate | V220: 46011
A221: 45946 | B221: 7693301 | C221: Modification | D221: HotelBeds | E221: 136-3684080 | F221: MONICA FARELL CANO | G221: 46072 | H221: 46073 | I221: 1 | J221: Erreur Param :Deluxe DELUXE | K221: BB | L221: GR-BARCOM | M221: 3 | N221: 0.1 | O221: 224.86 | P221: 179.888 | Q221: 0 | R221: 179.888 | S221: 0 | T221: NC | U221: *Agency Payment* Discounts for room 1: NON REFUNDABLE DISCOUNT (G) Notes for room 1: CAMAS SEPARADAS ------------------------------ Before Last Modification: Reservation Date : 2025-10-16 16:36:03 Room Names : Deluxe DELUXE ------------------------------ Modified : 2026-01-14 09:03:07 ------------------------------ Modification le 14/01/2026/ Contrat :BED AND BREAKFAST NRF BAR | V221: 45946
A222: 45946 | B222: 7693312 | C222: Annulation | D222: Agoda2 | E222: 589218239 | F222: MONICA FARELL CANO | G222: 46072 | H222: 46073 | I222: 1 | J222: SX | K222: BB | L222: STD | M222: 0 | N222: 0 | O222: 0 | P222: 0 | Q222: 0 | R222: 0 | S222: 0 | T222: 0 | U222: / Contrat :Bed & Breakfast Flexible - Beds Network - Controlled Exposure// Reservation le Thu Oct 16 2025 00:00:00 GMT+0100 (UTC+01:00) | V222: 46065
A223: 45937 | B223: 7653862 | C223: Annulation | D223: BookingCom | E223: 6071604684 | F223: Sebastian Noethlichs | G223: 46073 | H223: 46074 | I223: 1 | J223: SX | K223: BB | L223: STD | M223: 0 | N223: 0 | O223: 0 | P223: 0 | Q223: 0 | R223: 0 | S223: 0 | T223: 0 | U223: / Contrat :Bed & Breakfast Flex International genious rate// Reservation le Tue Oct 07 2025 00:00:00 GMT+0100 (UTC+01:00) | V223: 46019
A224: 45948 | B224: 7700219 | C224: Confirmation | D224: BookingCom | E224: 6473304827 | F224: Lesley Lee | G224: 46073 | H224: 46077 | I224: 4 | J224: DE | K224: BB | L224: STD | M224: 2 | N224: 0.2 | O224: 154.24 | P224: 123.392 | Q224: 0 | R224: 493.568 | S224: 0 | T224: 636.96 | U224: / Contrat :BB NRF #new International genious rate | V224: 45948
A225: 45953 | B225: 7721112 | C225: Confirmation | D225: BookingCom | E225: 6704632052 | F225: Gallimore Jenna | G225: 46073 | H225: 46076 | I225: 3 | J225: DE | K225: BB | L225: STD | M225: 2 | N225: 0.2 | O225: 151.42 | P225: 121.136 | Q225: 0 | R225: 363.408 | S225: 0 | T225: 469.26 | U225: / Contrat :BB NRF #new Early Booker Deal genious rate | V225: 45953
A226: 45965 | B226: 7766426 | C226: Confirmation | D226: BookingCom | E226: 6425715484 | F226: Mayara Fabricia Pereira | G226: 46073 | H226: 46076 | I226: 3 | J226: DE | K226: BB | L226: STD | M226: 2 | N226: 0.2 | O226: 234.43 | P226: 187.544 | Q226: 0 | R226: 562.632 | S226: 0 | T226: 718.29 | U226: / Contrat :Bed & Breakfast Flex Mobile(App) Rate genious rate | V226: 45965
A227: 45967 | B227: 7776006 | C227: Annulation | D227: BookingCom | E227: 6636273864 | F227: Sara Ayerra Arranz | G227: 46073 | H227: 46075 | I227: 2 | J227: ST | K227: BB | L227: STD | M227: 0 | N227: 0 | O227: 0 | P227: 0 | Q227: 0 | R227: 0 | S227: 0 | T227: 0 | U227: / Contrat :Bed & Breakfast Flex Mobile(App) Rate genious rate// Reservation le Thu Nov 06 2025 00:00:00 GMT+0100 (UTC+01:00) | V227: 45970
A228: 45967 | B228: 7776006 | C228: Annulation | D228: BookingCom | E228: 6636273864 | F228: Sara Ayerra Arranz | G228: 46073 | H228: 46075 | I228: 2 | J228: DE | K228: BB | L228: STD | M228: 0 | N228: 0 | O228: 0 | P228: 0 | Q228: 0 | R228: 0 | S228: 0 | T228: 0 | U228: / Contrat :Bed & Breakfast Flex Mobile(App) Rate genious rate// Reservation le Thu Nov 06 2025 00:00:00 GMT+0100 (UTC+01:00) | V228: 45970
A229: 45992 | B229: 7871523 | C229: Confirmation | D229: BookingCom | E229: 5607022589 | F229: Nathalie Appenzeller | G229: 46073 | H229: 46075 | I229: 2 | J229: DE | K229: BB | L229: STD | M229: 2 | N229: 0.2 | O229: 166.09 | P229: 132.872 | Q229: 0 | R229: 265.744 | S229: 0 | T229: 342.18 | U229: / Contrat :BB NRF #new Early Booker Deal genious rate | V229: 45992
A230: 45917 | B230: 7572950 | C230: Confirmation | D230: HotelBeds | E230: 136-3670938 | F230: VALERIE PAULUS | G230: 46073 | H230: 46077 | I230: 4 | J230: ST | K230: BB | L230: GR-BARCOM | M230: 3 | N230: 0.1 | O230: 202.82 | P230: 162.256 | Q230: 0 | R230: 649.024 | S230: 0 | T230: NC | U230: *Agency Payment* Discounts for room 1: NON REFUNDABLE DISCOUNT (G) / Contrat :BED AND BREAKFAST NRF BAR | V230: 45917
A231: 46009 | B231: 7931969 | C231: Annulation | D231: BookingCom | E231: 6788254095 | F231: Marcia Roos | G231: 46073 | H231: 46074 | I231: 1 | J231: SX | K231: BB | L231: STD | M231: 0 | N231: 0 | O231: 0 | P231: 0 | Q231: 0 | R231: 0 | S231: 0 | T231: 0 | U231: / Contrat :BB NRF #new Early Booker Deal// Reservation le Thu Dec 18 2025 00:00:00 GMT+0100 (UTC+01:00) | V231: 46063
A232: 46062 | B232: 8149031 | C232: Confirmation | D232: BookingCom | E232: 5104424451 | F232: Sebastian Noethlichs | G232: 46073 | H232: 46074 | I232: 1 | J232: SX | K232: BB | L232: STD | M232: 3 | N232: 0.2 | O232: 214.38 | P232: 171.504 | Q232: 0 | R232: 171.504 | S232: 0 | T232: 221.88 | U232: / Contrat :BB NRF #new Early Year Deal genious rate | V232: 46062
A233: 46067 | B233: 8172403 | C233: Confirmation | D233: BookingCom | E233: 5540869351 | F233: Asta Grabliauskiene | G233: 46073 | H233: 46074 | I233: 1 | J233: SX | K233: BB | L233: STD | M233: 1 | N233: 0.2 | O233: 211.38 | P233: 169.104 | Q233: 0 | R233: 169.104 | S233: 0 | T233: 213.88 | U233: / Contrat :BB NRF #new Early Year Deal genious rate | V233: 46067
A234: 45946 | B234: 7693309 | C234: Modification | D234: HotelBeds | E234: 136-3684083 | F234: MONICA FARELL CANO | G234: 46074 | H234: 46075 | I234: 1 | J234: Erreur Param :Deluxe DELUXE | K234: BB | L234: GR-BARCOM | M234: 3 | N234: 0.1 | O234: 224.86 | P234: 179.888 | Q234: 0 | R234: 179.888 | S234: 0 | T234: NC | U234: *Agency Payment* Discounts for room 1: NON REFUNDABLE DISCOUNT (G) Notes for room 1: CAMAS SEPARADAS / Two beds ------------------------------ Before Last Modification: Reservation Date : 2025-10-16 16:39:03 Room Names : Deluxe DELUXE ------------------------------ Modified : 2026-01-14 09:03:06 ------------------------------ Modification le 14/01/2026/ Contrat :BED AND BREAKFAST NRF BAR | V234: 45946
A235: 45946 | B235: 7693313 | C235: Confirmation | D235: Agoda2 | E235: 589218691 | F235: MONICA FARELL CANO | G235: 46074 | H235: 46075 | I235: 1 | J235: SX | K235: BB | L235: STD | M235: 2 | N235: 0.2 | O235: 260.25 | P235: 208.2 | Q235: 0 | R235: 208.2 | S235: 0 | T235: 260.25 | U235: / Contrat :Bed & Breakfast Flexible - Beds Network - Controlled Exposure | V235: 45946
A236: 46009 | B236: 7934390 | C236: Annulation | D236: BookingCom | E236: 5230634802 | F236: KATERYNA YUREVYCH | G236: 46074 | H236: 46077 | I236: 3 | J236: DE | K236: BB | L236: STD | M236: 0 | N236: 0 | O236: 0 | P236: 0 | Q236: 0 | R236: 0 | S236: 0 | T236: 0 | U236: / Contrat :Bed & Breakfast Flex Early Year Deal genious rate// Reservation le Thu Dec 18 2025 00:00:00 GMT+0100 (UTC+01:00) | V236: 46057
A237: 45851 | B237: 7272731 | C237: Modification | D237: BookingCom | E237: 5427327358 | F237: ian ryder | G237: 46075 | H237: 46079 | I237: 4 | J237: ST | K237: BB | L237: STD | M237: 2 | N237: 0.2 | O237: 128.54 | P237: 102.832 | Q237: 0 | R237: 411.328 | S237: 0 | T237: 534.16 | U237: Modification le 13/07/2025/ Contrat :BB NRF #new 40% - EB 2026 genious rate | V237: 45851
A238: 45949 | B238: 7703870 | C238: Confirmation | D238: BookingCom | E238: 5075083714 | F238: Mark Roberts | G238: 46075 | H238: 46079 | I238: 4 | J238: DE | K238: BB | L238: STD | M238: 2 | N238: 0.2 | O238: 137.99 | P238: 110.392 | Q238: 0 | R238: 441.568 | S238: 0 | T238: 571.96 | U238: / Contrat :BB NRF #new Early Booker Deal genious rate | V238: 45949
A239: 46041 | B239: 8056567 | C239: Confirmation | D239: BookingCom | E239: 5295498537 | F239: Camille di CHIARA | G239: 46075 | H239: 46079 | I239: 4 | J239: SF | K239: BB | L239: STD | M239: 4 | N239: 0.2 | O239: 461.65 | P239: 369.32 | Q239: 0 | R239: 1477.28 | S239: 0 | T239: 1886.6 | U239: / Contrat :Bed & Breakfast Flex EB Rate PLan (plus de 15 jours Ã l\'avance) genious rate | V239: 46041
A240: 46057 | B240: 8128046 | C240: Confirmation | D240: BookingCom | E240: 5701894766 | F240: Valerie Cotte | G240: 46075 | H240: 46079 | I240: 4 | J240: DE | K240: HALF | L240: STD | M240: 2 | N240: 0.2 | O240: 231.26 | P240: 185.008 | Q240: 36 | R240: 740.032 | S240: 144 | T240: 1060.24 | U240: / Contrat :HB NRF #new Early Year Deal genious rate | V240: 46057
A241: 45789 | B241: 7011291 | C241: Annulation | D241: BookingCom | E241: 4791651356 | F241: Joseph Murray | G241: 46076 | H241: 46080 | I241: 4 | J241: DE | K241: BB | L241: STD | M241: 0 | N241: 0 | O241: 0 | P241: 0 | Q241: 0 | R241: 0 | S241: 0 | T241: 0 | U241: / Contrat :Bed & Breakfast Flex International genious rate// Reservation le Mon May 12 2025 00:00:00 GMT+0100 (UTC+01:00) | V241: 45898
A242: 46031 | B242: 8013768 | C242: Confirmation | D242: BookingCom | E242: 6835960633 | F242: Briana Seiderman | G242: 46076 | H242: 46077 | I242: 1 | J242: DE | K242: BB | L242: STD | M242: 3 | N242: 0.2 | O242: 221.11 | P242: 176.888 | Q242: 0 | R242: 176.888 | S242: 0 | T242: 228.61 | U242: / Contrat :Bed & Breakfast Flex Early Year Deal genious rate | V242: 46031
A243: 46037 | B243: 8035373 | C243: Confirmation | D243: BookingCom | E243: 5525828260 | F243: John Liston | G243: 46076 | H243: 46079 | I243: 3 | J243: DE | K243: BB | L243: STD | M243: 2 | N243: 0.2 | O243: 191.44 | P243: 153.152 | Q243: 0 | R243: 459.456 | S243: 0 | T243: 574.32 | U243: / Contrat :Bed & Breakfast Flex EB Rate PLan (plus de 15 jours Ã l\'avance) genious rate | V243: 46037
A244: 46052 | B244: 8101483 | C244: Confirmation | D244: Reseliva | E244: 8101483 | F244: Aridani Jesus Marrero Aleman | G244: 46076 | H244: 46077 | I244: 1 | J244: SX | K244: BB | L244: NRF | M244: 2 | N244: 0 | O244: 243.95 | P244: 241.5105 | Q244: 0 | R244: 241.5105 | S244: 0 | T244: 248.95 | U244: / Contrat :BB Non Refundable | V244: 46052
A245: 46028 | B245: 8000885 | C245: Modification | D245: BookingCom | E245: 5436311722 | F245: Eugenie DUPONT | G245: 46077 | H245: 46082 | I245: 5 | J245: SX | K245: BB | L245: STD | M245: 3 | N245: 0.2 | O245: 209.78 | P245: 167.824 | Q245: 0 | R245: 839.12 | S245: 0 | T245: 1086.4 | U245: Modification le 05/02/2026/ Contrat :BB NRF #new Early Booker Deal genious rate | V245: 46028
A246: 46028 | B246: 8000894 | C246: Confirmation | D246: BookingCom | E246: 5465124098 | F246: Lucas Testaniere | G246: 46077 | H246: 46082 | I246: 5 | J246: SX | K246: BB | L246: STD | M246: 2 | N246: 0.2 | O246: 209.78 | P246: 167.824 | Q246: 0 | R246: 839.12 | S246: 0 | T246: 1073.9 | U246: / Contrat :BB NRF #new Early Booker Deal genious rate | V246: 46028
A247: 46029 | B247: 8002464 | C247: Confirmation | D247: Expedia | E247: 2365254057 | F247: Briana Seiderman | G247: 46077 | H247: 46080 | I247: 3 | J247: SU | M247: 3 | N247: 0 | O247: 0 | P247: 0 | Q247: 0 | R247: 0 | S247: 0 | T247: 0 | U247: / Contrat :Half board | V247: 46029
A248: 46067 | B248: 8174194 | C248: Confirmation | D248: Reseliva Pannel | E248: 8174194 | F248: Christelle PILAUD | G248: 46077 | H248: 46080 | I248: 3 | J248: DE | K248: BB | L248: NRF | M248: 2 | N248: 0 | O248: 239.76 | P248: 239.76 | Q248: 0 | R248: 719.28 | S248: 0 | T248: 734.28 | U248: / Contrat :BB Non Refundable | V248: 46067
A249: 45898 | B249: 7489170 | C249: Annulation | D249: BookingCom | E249: 5538765846 | F249: Marianne Nikoo | G249: 46078 | H249: 46083 | I249: 5 | J249: DE | K249: BB | L249: STD | M249: 0 | N249: 0 | O249: 0 | P249: 0 | Q249: 0 | R249: 0 | S249: 0 | T249: 0 | U249: Modification le 31/08/2025/ Contrat :Bed & Breakfast Flex International genious rate// Reservation le Fri Aug 29 2025 00:00:00 GMT+0100 (UTC+01:00) | V249: 46065
A250: 46063 | B250: 8154801 | C250: Confirmation | D250: BookingCom | E250: 6677750516 | F250: Jeroen Schultheis | G250: 46078 | H250: 46079 | I250: 1 | J250: DE | K250: BB | L250: STD | M250: 2 | N250: 0.2 | O250: 169.56 | P250: 135.648 | Q250: 0 | R250: 135.648 | S250: 0 | T250: 174.56 | U250: / Contrat :Bed & Breakfast Flex EB Rate PLan (plus de 15 jours à l\'avance) genious rate | V250: 46063
A251: 45892 | B251: 7459895 | C251: Confirmation | D251: BookingCom | E251: 6790277130 | F251: Omar Bumann | G251: 46079 | H251: 46083 | I251: 4 | J251: DE | K251: BB | L251: STD | M251: 2 | N251: 0.2 | O251: 146.43 | P251: 117.144 | Q251: 0 | R251: 468.576 | S251: 0 | T251: 605.72 | U251: / Contrat :Bed & Breakfast Flex EB Rate PLan (plus de 15 jours Ã l\'avance) genious rate | V251: 45892
A252: 45713 | B252: 6719326 | C252: Annulation | D252: BookingCom | E252: 4730109754 | F252: Stefano Gatti | G252: 46079 | H252: 46082 | I252: 3 | J252: DE | K252: BB | L252: STD | M252: 0 | N252: 0 | O252: 0 | P252: 0 | Q252: 0 | R252: 0 | S252: 0 | T252: 0 | U252: / Contrat :Bed & Breakfast Flex European Economic Area genious rate// Reservation le Tue Feb 25 2025 00:00:00 GMT+0000 (UTC+00:00) | V252: 46062
A253: 45945 | B253: 7689376 | C253: Annulation | D253: BookingCom | E253: 5726610723 | F253: Iago Sabucedo | G253: 46079 | H253: 46082 | I253: 3 | J253: DE | K253: BB | L253: STD | M253: 0 | N253: 0 | O253: 0 | P253: 0 | Q253: 0 | R253: 0 | S253: 0 | T253: 0 | U253: / Contrat :Bed & Breakfast Flex International genious rate// Reservation le Wed Oct 15 2025 00:00:00 GMT+0100 (UTC+01:00) | V253: 46069
A254: 45955 | B254: 7728888 | C254: Confirmation | D254: BookingCom | E254: 6011043856 | F254: Patrick Neyret | G254: 46079 | H254: 46081 | I254: 2 | J254: DE | K254: BB | L254: STD | M254: 3 | N254: 0.2 | O254: 204.17 | P254: 163.336 | Q254: 0 | R254: 326.672 | S254: 0 | T254: 423.34 | U254: / Contrat :Bed & Breakfast Flex International genious rate | V254: 45955
A255: 46018 | B255: 7964313 | C255: Confirmation | D255: BookingCom | E255: 6540953384 | F255: Sandra Leu | G255: 46079 | H255: 46080 | I255: 1 | J255: ST | K255: BB | L255: STD | M255: 2 | N255: 0.2 | O255: 196.22 | P255: 156.976 | Q255: 0 | R255: 156.976 | S255: 0 | T255: 201.22 | U255: / Contrat :Bed & Breakfast Flex Mobile(App) Rate genious rate | V255: 46018
A256: 46054 | B256: 8114237 | C256: Confirmation | D256: BookingCom | E256: 6576769614 | F256: Stephanie Menan | G256: 46079 | H256: 46081 | I256: 2 | J256: SF | K256: BB | L256: STD | M256: 4 | N256: 0.2 | O256: 401.07 | P256: 320.856 | Q256: 0 | R256: 641.712 | S256: 0 | T256: 822.14 | U256: / Contrat :Bed & Breakfast Flex EB Rate PLan (plus de 15 jours à l\'avance) genious rate | V256: 46054
A257: 46065 | B257: 8165967 | C257: Confirmation | D257: BookingCom | E257: 5099678943 | F257: CRISTIAN SCUTURICI | G257: 46079 | H257: 46082 | I257: 3 | J257: DE | K257: BB | L257: STD | M257: 3 | N257: 0.2 | O257: 175.32 | P257: 140.256 | Q257: 0 | R257: 420.768 | S257: 0 | T257: 525.96 | U257: / Contrat :BB NRF #new Early Year Deal genious rate | V257: 46065
A258: 45953 | B258: 7718526 | C258: Confirmation | D258: BookingCom | E258: 6313070537 | F258: Pauline Jeannoel | G258: 46080 | H258: 46084 | I258: 4 | J258: ST | K258: BB | L258: STD | M258: 2 | N258: 0.2 | O258: 113.4 | P258: 90.72 | Q258: 0 | R258: 362.88 | S258: 0 | T258: 473.6 | U258: / Contrat :BB NRF #new Early Booker Deal genious rate | V258: 45953
A259: 45975 | B259: 7805074 | C259: Confirmation | D259: BookingCom | E259: 6827319100 | F259: Silvia Prosdocimi | G259: 46080 | H259: 46083 | I259: 3 | J259: SU | K259: BB | L259: STD | M259: 2 | N259: 0.2 | O259: 254.2 | P259: 203.36 | Q259: 0 | R259: 610.08 | S259: 0 | T259: 762.6 | U259: / Contrat :Bed & Breakfast Flex Mobile(App) Rate genious rate | V259: 45975
...

Sheet Erreur
A1: 45932.461 | B1: 7622559 | C1: TypeError: Cannot read properties of undefined (reading '0')
A2: 45932.498 | B2: 7622559 | C2: TypeError: Cannot read properties of undefined (reading '0')

Sheet dataMail2
A1: =IFERROR(__xludf.DUMMYFUNCTION("QUERY(dataMail!A:Z,""Select B,D,F,G,H,I,M,O,R where C<>'Annulation'"")"),"ref Res") -> ref Res | B1: =IFERROR(__xludf.DUMMYFUNCTION("""COMPUTED_VALUE"""),"Source") -> Source | C1: =IFERROR(__xludf.DUMMYFUNCTION("""COMPUTED_VALUE"""),"Nom") -> Nom | D1: =IFERROR(__xludf.DUMMYFUNCTION("""COMPUTED_VALUE"""),"Arrivée") -> Arrivée | E1: =IFERROR(__xludf.DUMMYFUNCTION("""COMPUTED_VALUE"""),"Fin") -> Fin | F1: =IFERROR(__xludf.DUMMYFUNCTION("""COMPUTED_VALUE"""),"nb Nuit") -> nb Nuit | G1: =IFERROR(__xludf.DUMMYFUNCTION("""COMPUTED_VALUE"""),"Pax") -> Pax | H1: =IFERROR(__xludf.DUMMYFUNCTION("""COMPUTED_VALUE"""),"Nuitée") -> Nuitée | I1: =IFERROR(__xludf.DUMMYFUNCTION("""COMPUTED_VALUE"""),"Total N") -> Total N | J1: Nb Petit dej
A2: =IFERROR(__xludf.DUMMYFUNCTION("""COMPUTED_VALUE"""),7496325.0) -> 7496325 | B2: =IFERROR(__xludf.DUMMYFUNCTION("""COMPUTED_VALUE"""),"BookingCom") -> BookingCom | C2: =IFERROR(__xludf.DUMMYFUNCTION("""COMPUTED_VALUE"""),"Nathalie LANGLET ") -> Nathalie LANGLET | D2: =IFERROR(__xludf.DUMMYFUNCTION("""COMPUTED_VALUE"""),46022.0) -> 46022 | E2: =IFERROR(__xludf.DUMMYFUNCTION("""COMPUTED_VALUE"""),46023.0) -> 46023 | F2: =IFERROR(__xludf.DUMMYFUNCTION("""COMPUTED_VALUE"""),1.0) -> 1 | G2: =IFERROR(__xludf.DUMMYFUNCTION("""COMPUTED_VALUE"""),2.0) -> 2 | H2: =IFERROR(__xludf.DUMMYFUNCTION("""COMPUTED_VALUE"""),183.97) -> 183.97 | I2: =IFERROR(__xludf.DUMMYFUNCTION("""COMPUTED_VALUE"""),147.17600000000002) -> 147.176 | J2: =G2*F2 -> 2
A3: =IFERROR(__xludf.DUMMYFUNCTION("""COMPUTED_VALUE"""),7099280.0) -> 7099280 | B3: =IFERROR(__xludf.DUMMYFUNCTION("""COMPUTED_VALUE"""),"BookingCom") -> BookingCom | C3: =IFERROR(__xludf.DUMMYFUNCTION("""COMPUTED_VALUE"""),"Lorena Baroni ") -> Lorena Baroni | D3: =IFERROR(__xludf.DUMMYFUNCTION("""COMPUTED_VALUE"""),46022.0) -> 46022 | E3: =IFERROR(__xludf.DUMMYFUNCTION("""COMPUTED_VALUE"""),46024.0) -> 46024 | F3: =IFERROR(__xludf.DUMMYFUNCTION("""COMPUTED_VALUE"""),2.0) -> 2 | G3: =IFERROR(__xludf.DUMMYFUNCTION("""COMPUTED_VALUE"""),2.0) -> 2 | H3: =IFERROR(__xludf.DUMMYFUNCTION("""COMPUTED_VALUE"""),206.94) -> 206.94 | I3: =IFERROR(__xludf.DUMMYFUNCTION("""COMPUTED_VALUE"""),331.10400000000004) -> 331.104 | J3: =G3*F3 -> 4
A4: =IFERROR(__xludf.DUMMYFUNCTION("""COMPUTED_VALUE"""),7554269.0) -> 7554269 | B4: =IFERROR(__xludf.DUMMYFUNCTION("""COMPUTED_VALUE"""),"BookingCom") -> BookingCom | C4: =IFERROR(__xludf.DUMMYFUNCTION("""COMPUTED_VALUE"""),"Mandy Wright ") -> Mandy Wright | D4: =IFERROR(__xludf.DUMMYFUNCTION("""COMPUTED_VALUE"""),46022.0) -> 46022 | E4: =IFERROR(__xludf.DUMMYFUNCTION("""COMPUTED_VALUE"""),46026.0) -> 46026 | F4: =IFERROR(__xludf.DUMMYFUNCTION("""COMPUTED_VALUE"""),4.0) -> 4 | G4: =IFERROR(__xludf.DUMMYFUNCTION("""COMPUTED_VALUE"""),2.0) -> 2 | H4: =IFERROR(__xludf.DUMMYFUNCTION("""COMPUTED_VALUE"""),176.11) -> 176.11 | I4: =IFERROR(__xludf.DUMMYFUNCTION("""COMPUTED_VALUE"""),563.552) -> 563.552 | J4: =G4*F4 -> 8
A5: =IFERROR(__xludf.DUMMYFUNCTION("""COMPUTED_VALUE"""),7976038.0) -> 7976038 | B5: =IFERROR(__xludf.DUMMYFUNCTION("""COMPUTED_VALUE"""),"Reseliva Pannel") -> Reseliva Pannel | C5: =IFERROR(__xludf.DUMMYFUNCTION("""COMPUTED_VALUE"""),"Bouderbala Ahmed Alaa ") -> Bouderbala Ahmed Alaa | D5: =IFERROR(__xludf.DUMMYFUNCTION("""COMPUTED_VALUE"""),46022.0) -> 46022 | E5: =IFERROR(__xludf.DUMMYFUNCTION("""COMPUTED_VALUE"""),46023.0) -> 46023 | F5: =IFERROR(__xludf.DUMMYFUNCTION("""COMPUTED_VALUE"""),1.0) -> 1 | G5: =IFERROR(__xludf.DUMMYFUNCTION("""COMPUTED_VALUE"""),2.0) -> 2 | H5: =IFERROR(__xludf.DUMMYFUNCTION("""COMPUTED_VALUE"""),599.76) -> 599.76 | I5: =IFERROR(__xludf.DUMMYFUNCTION("""COMPUTED_VALUE"""),599.76) -> 599.76 | J5: =G5*F5 -> 2
A6: =IFERROR(__xludf.DUMMYFUNCTION("""COMPUTED_VALUE"""),7976762.0) -> 7976762 | B6: =IFERROR(__xludf.DUMMYFUNCTION("""COMPUTED_VALUE"""),"Reseliva") -> Reseliva | C6: =IFERROR(__xludf.DUMMYFUNCTION("""COMPUTED_VALUE"""),"Stefano Grini ") -> Stefano Grini | D6: =IFERROR(__xludf.DUMMYFUNCTION("""COMPUTED_VALUE"""),46022.0) -> 46022 | E6: =IFERROR(__xludf.DUMMYFUNCTION("""COMPUTED_VALUE"""),46024.0) -> 46024 | F6: =IFERROR(__xludf.DUMMYFUNCTION("""COMPUTED_VALUE"""),2.0) -> 2 | G6: =IFERROR(__xludf.DUMMYFUNCTION("""COMPUTED_VALUE"""),2.0) -> 2 | H6: =IFERROR(__xludf.DUMMYFUNCTION("""COMPUTED_VALUE"""),249.84) -> 249.84 | I6: =IFERROR(__xludf.DUMMYFUNCTION("""COMPUTED_VALUE"""),494.6832) -> 494.6832 | J6: =G6*F6 -> 4
A7: =IFERROR(__xludf.DUMMYFUNCTION("""COMPUTED_VALUE"""),7060224.0) -> 7060224 | B7: =IFERROR(__xludf.DUMMYFUNCTION("""COMPUTED_VALUE"""),"Expedia Affiliate Network") -> Expedia Affiliate Network | C7: =IFERROR(__xludf.DUMMYFUNCTION("""COMPUTED_VALUE"""),"MARIA DEL CARMEN RUBIO HIDALGO ") -> MARIA DEL CARMEN RUBIO HIDALGO | D7: =IFERROR(__xludf.DUMMYFUNCTION("""COMPUTED_VALUE"""),46023.0) -> 46023 | E7: =IFERROR(__xludf.DUMMYFUNCTION("""COMPUTED_VALUE"""),46024.0) -> 46024 | F7: =IFERROR(__xludf.DUMMYFUNCTION("""COMPUTED_VALUE"""),1.0) -> 1 | G7: =IFERROR(__xludf.DUMMYFUNCTION("""COMPUTED_VALUE"""),4.0) -> 4 | H7: =IFERROR(__xludf.DUMMYFUNCTION("""COMPUTED_VALUE"""),547.57) -> 547.57 | I7: =IFERROR(__xludf.DUMMYFUNCTION("""COMPUTED_VALUE"""),438.05600000000004) -> 438.056 | J7: =G7*F7 -> 4
A8: =IFERROR(__xludf.DUMMYFUNCTION("""COMPUTED_VALUE"""),7645947.0) -> 7645947 | B8: =IFERROR(__xludf.DUMMYFUNCTION("""COMPUTED_VALUE"""),"BookingCom") -> BookingCom | C8: =IFERROR(__xludf.DUMMYFUNCTION("""COMPUTED_VALUE"""),"francesca renna ") -> francesca renna | D8: =IFERROR(__xludf.DUMMYFUNCTION("""COMPUTED_VALUE"""),46023.0) -> 46023 | E8: =IFERROR(__xludf.DUMMYFUNCTION("""COMPUTED_VALUE"""),46025.0) -> 46025 | F8: =IFERROR(__xludf.DUMMYFUNCTION("""COMPUTED_VALUE"""),2.0) -> 2 | G8: =IFERROR(__xludf.DUMMYFUNCTION("""COMPUTED_VALUE"""),2.0) -> 2 | H8: =IFERROR(__xludf.DUMMYFUNCTION("""COMPUTED_VALUE"""),182.31) -> 182.31 | I8: =IFERROR(__xludf.DUMMYFUNCTION("""COMPUTED_VALUE"""),291.696) -> 291.696 | J8: =G8*F8 -> 4
A9: =IFERROR(__xludf.DUMMYFUNCTION("""COMPUTED_VALUE"""),7777362.0) -> 7777362 | B9: =IFERROR(__xludf.DUMMYFUNCTION("""COMPUTED_VALUE"""),"BookingCom") -> BookingCom | C9: =IFERROR(__xludf.DUMMYFUNCTION("""COMPUTED_VALUE"""),"Pierre Verdickt ") -> Pierre Verdickt | D9: =IFERROR(__xludf.DUMMYFUNCTION("""COMPUTED_VALUE"""),46023.0) -> 46023 | E9: =IFERROR(__xludf.DUMMYFUNCTION("""COMPUTED_VALUE"""),46024.0) -> 46024 | F9: =IFERROR(__xludf.DUMMYFUNCTION("""COMPUTED_VALUE"""),1.0) -> 1 | G9: =IFERROR(__xludf.DUMMYFUNCTION("""COMPUTED_VALUE"""),2.0) -> 2 | H9: =IFERROR(__xludf.DUMMYFUNCTION("""COMPUTED_VALUE"""),191.05) -> 191.05 | I9: =IFERROR(__xludf.DUMMYFUNCTION("""COMPUTED_VALUE"""),152.84) -> 152.84 | J9: =G9*F9 -> 2
A10: =IFERROR(__xludf.DUMMYFUNCTION("""COMPUTED_VALUE"""),7649484.0) -> 7649484 | B10: =IFERROR(__xludf.DUMMYFUNCTION("""COMPUTED_VALUE"""),"Agoda2") -> Agoda2 | C10: =IFERROR(__xludf.DUMMYFUNCTION("""COMPUTED_VALUE"""),"ALBERTO BONETTI ") -> ALBERTO BONETTI | D10: =IFERROR(__xludf.DUMMYFUNCTION("""COMPUTED_VALUE"""),46023.0) -> 46023 | E10: =IFERROR(__xludf.DUMMYFUNCTION("""COMPUTED_VALUE"""),46027.0) -> 46027 | F10: =IFERROR(__xludf.DUMMYFUNCTION("""COMPUTED_VALUE"""),4.0) -> 4 | G10: =IFERROR(__xludf.DUMMYFUNCTION("""COMPUTED_VALUE"""),2.0) -> 2 | H10: =IFERROR(__xludf.DUMMYFUNCTION("""COMPUTED_VALUE"""),265.84) -> 265.84 | I10: =IFERROR(__xludf.DUMMYFUNCTION("""COMPUTED_VALUE"""),850.688) -> 850.688 | J10: =G10*F10 -> 8
A11: =IFERROR(__xludf.DUMMYFUNCTION("""COMPUTED_VALUE"""),7979294.0) -> 7979294 | B11: =IFERROR(__xludf.DUMMYFUNCTION("""COMPUTED_VALUE"""),"Reseliva Pannel") -> Reseliva Pannel | C11: =IFERROR(__xludf.DUMMYFUNCTION("""COMPUTED_VALUE"""),"PINI Marlene ") -> PINI Marlene | D11: =IFERROR(__xludf.DUMMYFUNCTION("""COMPUTED_VALUE"""),46023.0) -> 46023 | E11: =IFERROR(__xludf.DUMMYFUNCTION("""COMPUTED_VALUE"""),46025.0) -> 46025 | F11: =IFERROR(__xludf.DUMMYFUNCTION("""COMPUTED_VALUE"""),2.0) -> 2 | G11: =IFERROR(__xludf.DUMMYFUNCTION("""COMPUTED_VALUE"""),2.0) -> 2 | H11: =IFERROR(__xludf.DUMMYFUNCTION("""COMPUTED_VALUE"""),275.04) -> 275.04 | I11: =IFERROR(__xludf.DUMMYFUNCTION("""COMPUTED_VALUE"""),550.08) -> 550.08 | J11: =G11*F11 -> 4
A12: =IFERROR(__xludf.DUMMYFUNCTION("""COMPUTED_VALUE"""),7350805.0) -> 7350805 | B12: =IFERROR(__xludf.DUMMYFUNCTION("""COMPUTED_VALUE"""),"Reseliva") -> Reseliva | C12: =IFERROR(__xludf.DUMMYFUNCTION("""COMPUTED_VALUE"""),"Meryem x Nancy ") -> Meryem x Nancy | D12: =IFERROR(__xludf.DUMMYFUNCTION("""COMPUTED_VALUE"""),46024.0) -> 46024 | E12: =IFERROR(__xludf.DUMMYFUNCTION("""COMPUTED_VALUE"""),46025.0) -> 46025 | F12: =IFERROR(__xludf.DUMMYFUNCTION("""COMPUTED_VALUE"""),1.0) -> 1 | G12: =IFERROR(__xludf.DUMMYFUNCTION("""COMPUTED_VALUE"""),2.0) -> 2 | H12: =IFERROR(__xludf.DUMMYFUNCTION("""COMPUTED_VALUE"""),249.84) -> 249.84 | I12: =IFERROR(__xludf.DUMMYFUNCTION("""COMPUTED_VALUE"""),247.3416) -> 247.3416 | J12: =G12*F12 -> 2
A13: =IFERROR(__xludf.DUMMYFUNCTION("""COMPUTED_VALUE"""),7350819.0) -> 7350819 | B13: =IFERROR(__xludf.DUMMYFUNCTION("""COMPUTED_VALUE"""),"Reseliva") -> Reseliva | C13: =IFERROR(__xludf.DUMMYFUNCTION("""COMPUTED_VALUE"""),"Meryem x Nancy ") -> Meryem x Nancy | D13: =IFERROR(__xludf.DUMMYFUNCTION("""COMPUTED_VALUE"""),46024.0) -> 46024 | E13: =IFERROR(__xludf.DUMMYFUNCTION("""COMPUTED_VALUE"""),46025.0) -> 46025 | F13: =IFERROR(__xludf.DUMMYFUNCTION("""COMPUTED_VALUE"""),1.0) -> 1 | G13: =IFERROR(__xludf.DUMMYFUNCTION("""COMPUTED_VALUE"""),2.0) -> 2 | H13: =IFERROR(__xludf.DUMMYFUNCTION("""COMPUTED_VALUE"""),249.84) -> 249.84 | I13: =IFERROR(__xludf.DUMMYFUNCTION("""COMPUTED_VALUE"""),247.3416) -> 247.3416 | J13: =G13*F13 -> 2
A14: =IFERROR(__xludf.DUMMYFUNCTION("""COMPUTED_VALUE"""),7269798.0) -> 7269798 | B14: =IFERROR(__xludf.DUMMYFUNCTION("""COMPUTED_VALUE"""),"Reseliva") -> Reseliva | C14: =IFERROR(__xludf.DUMMYFUNCTION("""COMPUTED_VALUE"""),"Jens Dressler ") -> Jens Dressler | D14: =IFERROR(__xludf.DUMMYFUNCTION("""COMPUTED_VALUE"""),46024.0) -> 46024 | E14: =IFERROR(__xludf.DUMMYFUNCTION("""COMPUTED_VALUE"""),46027.0) -> 46027 | F14: =IFERROR(__xludf.DUMMYFUNCTION("""COMPUTED_VALUE"""),3.0) -> 3 | G14: =IFERROR(__xludf.DUMMYFUNCTION("""COMPUTED_VALUE"""),2.0) -> 2 | H14: =IFERROR(__xludf.DUMMYFUNCTION("""COMPUTED_VALUE"""),178.60666666666668) -> 178.60667 | I14: =IFERROR(__xludf.DUMMYFUNCTION("""COMPUTED_VALUE"""),530.4618) -> 530.4618 | J14: =G14*F14 -> 6
A15: =IFERROR(__xludf.DUMMYFUNCTION("""COMPUTED_VALUE"""),7695383.0) -> 7695383 | B15: =IFERROR(__xludf.DUMMYFUNCTION("""COMPUTED_VALUE"""),"Reseliva Pannel") -> Reseliva Pannel | C15: =IFERROR(__xludf.DUMMYFUNCTION("""COMPUTED_VALUE"""),"No Limited Travel ") -> No Limited Travel | D15: =IFERROR(__xludf.DUMMYFUNCTION("""COMPUTED_VALUE"""),46024.0) -> 46024 | E15: =IFERROR(__xludf.DUMMYFUNCTION("""COMPUTED_VALUE"""),46025.0) -> 46025 | F15: =IFERROR(__xludf.DUMMYFUNCTION("""COMPUTED_VALUE"""),1.0) -> 1 | G15: =IFERROR(__xludf.DUMMYFUNCTION("""COMPUTED_VALUE"""),2.0) -> 2 | H15: =IFERROR(__xludf.DUMMYFUNCTION("""COMPUTED_VALUE"""),575.28) -> 575.28 | I15: =IFERROR(__xludf.DUMMYFUNCTION("""COMPUTED_VALUE"""),575.28) -> 575.28 | J15: =G15*F15 -> 2
A16: =IFERROR(__xludf.DUMMYFUNCTION("""COMPUTED_VALUE"""),7607847.0) -> 7607847 | B16: =IFERROR(__xludf.DUMMYFUNCTION("""COMPUTED_VALUE"""),"HotelBeds") -> HotelBeds | C16: =IFERROR(__xludf.DUMMYFUNCTION("""COMPUTED_VALUE"""),"MANUELA BATALONI ") -> MANUELA BATALONI | D16: =IFERROR(__xludf.DUMMYFUNCTION("""COMPUTED_VALUE"""),46024.0) -> 46024 | E16: =IFERROR(__xludf.DUMMYFUNCTION("""COMPUTED_VALUE"""),46025.0) -> 46025 | F16: =IFERROR(__xludf.DUMMYFUNCTION("""COMPUTED_VALUE"""),1.0) -> 1 | G16: =IFERROR(__xludf.DUMMYFUNCTION("""COMPUTED_VALUE"""),3.0) -> 3 | H16: =IFERROR(__xludf.DUMMYFUNCTION("""COMPUTED_VALUE"""),365.6) -> 365.6 | I16: =IFERROR(__xludf.DUMMYFUNCTION("""COMPUTED_VALUE"""),292.48) -> 292.48 | J16: =G16*F16 -> 3
A17: =IFERROR(__xludf.DUMMYFUNCTION("""COMPUTED_VALUE"""),7976737.0) -> 7976737 | B17: =IFERROR(__xludf.DUMMYFUNCTION("""COMPUTED_VALUE"""),"Reseliva Pannel") -> Reseliva Pannel | C17: =IFERROR(__xludf.DUMMYFUNCTION("""COMPUTED_VALUE"""),"Stefano Grini ") -> Stefano Grini | D17: =IFERROR(__xludf.DUMMYFUNCTION("""COMPUTED_VALUE"""),46024.0) -> 46024 | E17: =IFERROR(__xludf.DUMMYFUNCTION("""COMPUTED_VALUE"""),46025.0) -> 46025 | F17: =IFERROR(__xludf.DUMMYFUNCTION("""COMPUTED_VALUE"""),1.0) -> 1 | G17: =IFERROR(__xludf.DUMMYFUNCTION("""COMPUTED_VALUE"""),2.0) -> 2 | H17: =IFERROR(__xludf.DUMMYFUNCTION("""COMPUTED_VALUE"""),249.84) -> 249.84 | I17: =IFERROR(__xludf.DUMMYFUNCTION("""COMPUTED_VALUE"""),249.84) -> 249.84 | J17: =G17*F17 -> 2
A18: =IFERROR(__xludf.DUMMYFUNCTION("""COMPUTED_VALUE"""),7112016.0) -> 7112016 | B18: =IFERROR(__xludf.DUMMYFUNCTION("""COMPUTED_VALUE"""),"A-Expedia Affiliate Network") -> A-Expedia Affiliate Network | C18: =IFERROR(__xludf.DUMMYFUNCTION("""COMPUTED_VALUE"""),"Simonetta Colavizza ") -> Simonetta Colavizza | D18: =IFERROR(__xludf.DUMMYFUNCTION("""COMPUTED_VALUE"""),46025.0) -> 46025 | E18: =IFERROR(__xludf.DUMMYFUNCTION("""COMPUTED_VALUE"""),46030.0) -> 46030 | F18: =IFERROR(__xludf.DUMMYFUNCTION("""COMPUTED_VALUE"""),5.0) -> 5 | G18: =IFERROR(__xludf.DUMMYFUNCTION("""COMPUTED_VALUE"""),2.0) -> 2 | H18: =IFERROR(__xludf.DUMMYFUNCTION("""COMPUTED_VALUE"""),0.0) -> 0 | I18: =IFERROR(__xludf.DUMMYFUNCTION("""COMPUTED_VALUE"""),0.0) -> 0 | J18: =G18*F18 -> 10
A19: =IFERROR(__xludf.DUMMYFUNCTION("""COMPUTED_VALUE"""),7674402.0) -> 7674402 | B19: =IFERROR(__xludf.DUMMYFUNCTION("""COMPUTED_VALUE"""),"BookingCom") -> BookingCom | C19: =IFERROR(__xludf.DUMMYFUNCTION("""COMPUTED_VALUE"""),"Meekai Johnson ") -> Meekai Johnson | D19: =IFERROR(__xludf.DUMMYFUNCTION("""COMPUTED_VALUE"""),46025.0) -> 46025 | E19: =IFERROR(__xludf.DUMMYFUNCTION("""COMPUTED_VALUE"""),46026.0) -> 46026 | F19: =IFERROR(__xludf.DUMMYFUNCTION("""COMPUTED_VALUE"""),1.0) -> 1 | G19: =IFERROR(__xludf.DUMMYFUNCTION("""COMPUTED_VALUE"""),2.0) -> 2 | H19: =IFERROR(__xludf.DUMMYFUNCTION("""COMPUTED_VALUE"""),186.81) -> 186.81 | I19: =IFERROR(__xludf.DUMMYFUNCTION("""COMPUTED_VALUE"""),149.448) -> 149.448 | J19: =G19*F19 -> 2
A20: =IFERROR(__xludf.DUMMYFUNCTION("""COMPUTED_VALUE"""),7695386.0) -> 7695386 | B20: =IFERROR(__xludf.DUMMYFUNCTION("""COMPUTED_VALUE"""),"Reseliva Pannel") -> Reseliva Pannel | C20: =IFERROR(__xludf.DUMMYFUNCTION("""COMPUTED_VALUE"""),"No limited Travel ") -> No limited Travel | D20: =IFERROR(__xludf.DUMMYFUNCTION("""COMPUTED_VALUE"""),46025.0) -> 46025 | E20: =IFERROR(__xludf.DUMMYFUNCTION("""COMPUTED_VALUE"""),46027.0) -> 46027 | F20: =IFERROR(__xludf.DUMMYFUNCTION("""COMPUTED_VALUE"""),2.0) -> 2 | G20: =IFERROR(__xludf.DUMMYFUNCTION("""COMPUTED_VALUE"""),2.0) -> 2 | H20: =IFERROR(__xludf.DUMMYFUNCTION("""COMPUTED_VALUE"""),249.84) -> 249.84 | I20: =IFERROR(__xludf.DUMMYFUNCTION("""COMPUTED_VALUE"""),499.68) -> 499.68 | J20: =G20*F20 -> 4
A21: =IFERROR(__xludf.DUMMYFUNCTION("""COMPUTED_VALUE"""),7717090.0) -> 7717090 | B21: =IFERROR(__xludf.DUMMYFUNCTION("""COMPUTED_VALUE"""),"BookingCom") -> BookingCom | C21: =IFERROR(__xludf.DUMMYFUNCTION("""COMPUTED_VALUE"""),"FRANCESCO MURGANTE ") -> FRANCESCO MURGANTE | D21: =IFERROR(__xludf.DUMMYFUNCTION("""COMPUTED_VALUE"""),46025.0) -> 46025 | E21: =IFERROR(__xludf.DUMMYFUNCTION("""COMPUTED_VALUE"""),46030.0) -> 46030 | F21: =IFERROR(__xludf.DUMMYFUNCTION("""COMPUTED_VALUE"""),5.0) -> 5 | G21: =IFERROR(__xludf.DUMMYFUNCTION("""COMPUTED_VALUE"""),4.0) -> 4 | H21: =IFERROR(__xludf.DUMMYFUNCTION("""COMPUTED_VALUE"""),419.62) -> 419.62 | I21: =IFERROR(__xludf.DUMMYFUNCTION("""COMPUTED_VALUE"""),1678.48) -> 1678.48 | J21: =G21*F21 -> 20
A22: =IFERROR(__xludf.DUMMYFUNCTION("""COMPUTED_VALUE"""),7729764.0) -> 7729764 | B22: =IFERROR(__xludf.DUMMYFUNCTION("""COMPUTED_VALUE"""),"BookingCom") -> BookingCom | C22: =IFERROR(__xludf.DUMMYFUNCTION("""COMPUTED_VALUE"""),"Tiffany Bernard ") -> Tiffany Bernard | D22: =IFERROR(__xludf.DUMMYFUNCTION("""COMPUTED_VALUE"""),46025.0) -> 46025 | E22: =IFERROR(__xludf.DUMMYFUNCTION("""COMPUTED_VALUE"""),46031.0) -> 46031 | F22: =IFERROR(__xludf.DUMMYFUNCTION("""COMPUTED_VALUE"""),6.0) -> 6 | G22: =IFERROR(__xludf.DUMMYFUNCTION("""COMPUTED_VALUE"""),3.0) -> 3 | H22: =IFERROR(__xludf.DUMMYFUNCTION("""COMPUTED_VALUE"""),210.57) -> 210.57 | I22: =IFERROR(__xludf.DUMMYFUNCTION("""COMPUTED_VALUE"""),1010.7360000000001) -> 1010.736 | J22: =G22*F22 -> 18
A23: =IFERROR(__xludf.DUMMYFUNCTION("""COMPUTED_VALUE"""),7757070.0) -> 7757070 | B23: =IFERROR(__xludf.DUMMYFUNCTION("""COMPUTED_VALUE"""),"BookingCom") -> BookingCom | C23: =IFERROR(__xludf.DUMMYFUNCTION("""COMPUTED_VALUE"""),"Emanuela Moraes ") -> Emanuela Moraes | D23: =IFERROR(__xludf.DUMMYFUNCTION("""COMPUTED_VALUE"""),46025.0) -> 46025 | E23: =IFERROR(__xludf.DUMMYFUNCTION("""COMPUTED_VALUE"""),46026.0) -> 46026 | F23: =IFERROR(__xludf.DUMMYFUNCTION("""COMPUTED_VALUE"""),1.0) -> 1 | G23: =IFERROR(__xludf.DUMMYFUNCTION("""COMPUTED_VALUE"""),3.0) -> 3 | H23: =IFERROR(__xludf.DUMMYFUNCTION("""COMPUTED_VALUE"""),165.81) -> 165.81 | I23: =IFERROR(__xludf.DUMMYFUNCTION("""COMPUTED_VALUE"""),132.648) -> 132.648 | J23: =G23*F23 -> 3
A24: =IFERROR(__xludf.DUMMYFUNCTION("""COMPUTED_VALUE"""),7855729.0) -> 7855729 | B24: =IFERROR(__xludf.DUMMYFUNCTION("""COMPUTED_VALUE"""),"BookingCom") -> BookingCom | C24: =IFERROR(__xludf.DUMMYFUNCTION("""COMPUTED_VALUE"""),"Ruud Koole ") -> Ruud Koole | D24: =IFERROR(__xludf.DUMMYFUNCTION("""COMPUTED_VALUE"""),46025.0) -> 46025 | E24: =IFERROR(__xludf.DUMMYFUNCTION("""COMPUTED_VALUE"""),46026.0) -> 46026 | F24: =IFERROR(__xludf.DUMMYFUNCTION("""COMPUTED_VALUE"""),1.0) -> 1 | G24: =IFERROR(__xludf.DUMMYFUNCTION("""COMPUTED_VALUE"""),2.0) -> 2 | H24: =IFERROR(__xludf.DUMMYFUNCTION("""COMPUTED_VALUE"""),197.82) -> 197.82 | I24: =IFERROR(__xludf.DUMMYFUNCTION("""COMPUTED_VALUE"""),158.256) -> 158.256 | J24: =G24*F24 -> 2
A25: =IFERROR(__xludf.DUMMYFUNCTION("""COMPUTED_VALUE"""),7666779.0) -> 7666779 | B25: =IFERROR(__xludf.DUMMYFUNCTION("""COMPUTED_VALUE"""),"BookingCom") -> BookingCom | C25: =IFERROR(__xludf.DUMMYFUNCTION("""COMPUTED_VALUE"""),"Heike Siewert ") -> Heike Siewert | D25: =IFERROR(__xludf.DUMMYFUNCTION("""COMPUTED_VALUE"""),46026.0) -> 46026 | E25: =IFERROR(__xludf.DUMMYFUNCTION("""COMPUTED_VALUE"""),46033.0) -> 46033 | F25: =IFERROR(__xludf.DUMMYFUNCTION("""COMPUTED_VALUE"""),7.0) -> 7 | G25: =IFERROR(__xludf.DUMMYFUNCTION("""COMPUTED_VALUE"""),2.0) -> 2 | H25: =IFERROR(__xludf.DUMMYFUNCTION("""COMPUTED_VALUE"""),195.82999999999998) -> 195.83 | I25: =IFERROR(__xludf.DUMMYFUNCTION("""COMPUTED_VALUE"""),1096.648) -> 1096.648 | J25: =G25*F25 -> 14
A26: =IFERROR(__xludf.DUMMYFUNCTION("""COMPUTED_VALUE"""),7717168.0) -> 7717168 | B26: =IFERROR(__xludf.DUMMYFUNCTION("""COMPUTED_VALUE"""),"BookingCom") -> BookingCom | C26: =IFERROR(__xludf.DUMMYFUNCTION("""COMPUTED_VALUE"""),"Katrin Ott ") -> Katrin Ott | D26: =IFERROR(__xludf.DUMMYFUNCTION("""COMPUTED_VALUE"""),46026.0) -> 46026 | E26: =IFERROR(__xludf.DUMMYFUNCTION("""COMPUTED_VALUE"""),46033.0) -> 46033 | F26: =IFERROR(__xludf.DUMMYFUNCTION("""COMPUTED_VALUE"""),7.0) -> 7 | G26: =IFERROR(__xludf.DUMMYFUNCTION("""COMPUTED_VALUE"""),2.0) -> 2 | H26: =IFERROR(__xludf.DUMMYFUNCTION("""COMPUTED_VALUE"""),168.07999999999998) -> 168.08 | I26: =IFERROR(__xludf.DUMMYFUNCTION("""COMPUTED_VALUE"""),941.248) -> 941.248 | J26: =G26*F26 -> 14
A27: =IFERROR(__xludf.DUMMYFUNCTION("""COMPUTED_VALUE"""),7729232.0) -> 7729232 | B27: =IFERROR(__xludf.DUMMYFUNCTION("""COMPUTED_VALUE"""),"BookingCom") -> BookingCom | C27: =IFERROR(__xludf.DUMMYFUNCTION("""COMPUTED_VALUE"""),"Maria Edeltraud Boxleitner ") -> Maria Edeltraud Boxleitner | D27: =IFERROR(__xludf.DUMMYFUNCTION("""COMPUTED_VALUE"""),46026.0) -> 46026 | E27: =IFERROR(__xludf.DUMMYFUNCTION("""COMPUTED_VALUE"""),46033.0) -> 46033 | F27: =IFERROR(__xludf.DUMMYFUNCTION("""COMPUTED_VALUE"""),7.0) -> 7 | G27: =IFERROR(__xludf.DUMMYFUNCTION("""COMPUTED_VALUE"""),1.0) -> 1 | H27: =IFERROR(__xludf.DUMMYFUNCTION("""COMPUTED_VALUE"""),168.24) -> 168.24 | I27: =IFERROR(__xludf.DUMMYFUNCTION("""COMPUTED_VALUE"""),942.1440000000001) -> 942.144 | J27: =G27*F27 -> 7
A28: =IFERROR(__xludf.DUMMYFUNCTION("""COMPUTED_VALUE"""),7735462.0) -> 7735462 | B28: =IFERROR(__xludf.DUMMYFUNCTION("""COMPUTED_VALUE"""),"BookingCom") -> BookingCom | C28: =IFERROR(__xludf.DUMMYFUNCTION("""COMPUTED_VALUE"""),"Thomas Birner ") -> Thomas Birner | D28: =IFERROR(__xludf.DUMMYFUNCTION("""COMPUTED_VALUE"""),46026.0) -> 46026 | E28: =IFERROR(__xludf.DUMMYFUNCTION("""COMPUTED_VALUE"""),46027.0) -> 46027 | F28: =IFERROR(__xludf.DUMMYFUNCTION("""COMPUTED_VALUE"""),1.0) -> 1 | G28: =IFERROR(__xludf.DUMMYFUNCTION("""COMPUTED_VALUE"""),2.0) -> 2 | H28: =IFERROR(__xludf.DUMMYFUNCTION("""COMPUTED_VALUE"""),192.3) -> 192.3 | I28: =IFERROR(__xludf.DUMMYFUNCTION("""COMPUTED_VALUE"""),153.84000000000003) -> 153.84 | J28: =G28*F28 -> 2
A29: =IFERROR(__xludf.DUMMYFUNCTION("""COMPUTED_VALUE"""),7735820.0) -> 7735820 | B29: =IFERROR(__xludf.DUMMYFUNCTION("""COMPUTED_VALUE"""),"BookingCom") -> BookingCom | C29: =IFERROR(__xludf.DUMMYFUNCTION("""COMPUTED_VALUE"""),"Alin Cozma ") -> Alin Cozma | D29: =IFERROR(__xludf.DUMMYFUNCTION("""COMPUTED_VALUE"""),46026.0) -> 46026 | E29: =IFERROR(__xludf.DUMMYFUNCTION("""COMPUTED_VALUE"""),46029.0) -> 46029 | F29: =IFERROR(__xludf.DUMMYFUNCTION("""COMPUTED_VALUE"""),3.0) -> 3 | G29: =IFERROR(__xludf.DUMMYFUNCTION("""COMPUTED_VALUE"""),2.0) -> 2 | H29: =IFERROR(__xludf.DUMMYFUNCTION("""COMPUTED_VALUE"""),174.55999999999997) -> 174.56 | I29: =IFERROR(__xludf.DUMMYFUNCTION("""COMPUTED_VALUE"""),418.94399999999996) -> 418.944 | J29: =G29*F29 -> 6
A30: =IFERROR(__xludf.DUMMYFUNCTION("""COMPUTED_VALUE"""),7986963.0) -> 7986963 | B30: =IFERROR(__xludf.DUMMYFUNCTION("""COMPUTED_VALUE"""),"Reseliva") -> Reseliva | C30: =IFERROR(__xludf.DUMMYFUNCTION("""COMPUTED_VALUE"""),"Sandra Rizzi ") -> Sandra Rizzi | D30: =IFERROR(__xludf.DUMMYFUNCTION("""COMPUTED_VALUE"""),46026.0) -> 46026 | E30: =IFERROR(__xludf.DUMMYFUNCTION("""COMPUTED_VALUE"""),46027.0) -> 46027 | F30: =IFERROR(__xludf.DUMMYFUNCTION("""COMPUTED_VALUE"""),1.0) -> 1 | G30: =IFERROR(__xludf.DUMMYFUNCTION("""COMPUTED_VALUE"""),2.0) -> 2 | H30: =IFERROR(__xludf.DUMMYFUNCTION("""COMPUTED_VALUE"""),275.04) -> 275.04 | I30: =IFERROR(__xludf.DUMMYFUNCTION("""COMPUTED_VALUE"""),272.2896) -> 272.2896 | J30: =G30*F30 -> 2
A31: =IFERROR(__xludf.DUMMYFUNCTION("""COMPUTED_VALUE"""),7735472.0) -> 7735472 | B31: =IFERROR(__xludf.DUMMYFUNCTION("""COMPUTED_VALUE"""),"BookingCom") -> BookingCom | C31: =IFERROR(__xludf.DUMMYFUNCTION("""COMPUTED_VALUE"""),"Thomas Birner ") -> Thomas Birner | D31: =IFERROR(__xludf.DUMMYFUNCTION("""COMPUTED_VALUE"""),46027.0) -> 46027 | E31: =IFERROR(__xludf.DUMMYFUNCTION("""COMPUTED_VALUE"""),46029.0) -> 46029 | F31: =IFERROR(__xludf.DUMMYFUNCTION("""COMPUTED_VALUE"""),2.0) -> 2 | G31: =IFERROR(__xludf.DUMMYFUNCTION("""COMPUTED_VALUE"""),2.0) -> 2 | H31: =IFERROR(__xludf.DUMMYFUNCTION("""COMPUTED_VALUE"""),212.85) -> 212.85 | I31: =IFERROR(__xludf.DUMMYFUNCTION("""COMPUTED_VALUE"""),340.56) -> 340.56 | J31: =G31*F31 -> 4
A32: =IFERROR(__xludf.DUMMYFUNCTION("""COMPUTED_VALUE"""),7791318.0) -> 7791318 | B32: =IFERROR(__xludf.DUMMYFUNCTION("""COMPUTED_VALUE"""),"BookingCom") -> BookingCom | C32: =IFERROR(__xludf.DUMMYFUNCTION("""COMPUTED_VALUE"""),"Sandra Rizzi ") -> Sandra Rizzi | D32: =IFERROR(__xludf.DUMMYFUNCTION("""COMPUTED_VALUE"""),46027.0) -> 46027 | E32: =IFERROR(__xludf.DUMMYFUNCTION("""COMPUTED_VALUE"""),46028.0) -> 46028 | F32: =IFERROR(__xludf.DUMMYFUNCTION("""COMPUTED_VALUE"""),1.0) -> 1 | G32: =IFERROR(__xludf.DUMMYFUNCTION("""COMPUTED_VALUE"""),2.0) -> 2 | H32: =IFERROR(__xludf.DUMMYFUNCTION("""COMPUTED_VALUE"""),150.95) -> 150.95 | I32: =IFERROR(__xludf.DUMMYFUNCTION("""COMPUTED_VALUE"""),120.75999999999999) -> 120.76 | J32: =G32*F32 -> 2
A33: =IFERROR(__xludf.DUMMYFUNCTION("""COMPUTED_VALUE"""),7820179.0) -> 7820179 | B33: =IFERROR(__xludf.DUMMYFUNCTION("""COMPUTED_VALUE"""),"Reseliva") -> Reseliva | C33: =IFERROR(__xludf.DUMMYFUNCTION("""COMPUTED_VALUE"""),"lejla salkic ") -> lejla salkic | D33: =IFERROR(__xludf.DUMMYFUNCTION("""COMPUTED_VALUE"""),46027.0) -> 46027 | E33: =IFERROR(__xludf.DUMMYFUNCTION("""COMPUTED_VALUE"""),46031.0) -> 46031 | F33: =IFERROR(__xludf.DUMMYFUNCTION("""COMPUTED_VALUE"""),4.0) -> 4 | G33: =IFERROR(__xludf.DUMMYFUNCTION("""COMPUTED_VALUE"""),2.0) -> 2 | H33: =IFERROR(__xludf.DUMMYFUNCTION("""COMPUTED_VALUE"""),249.84) -> 249.84 | I33: =IFERROR(__xludf.DUMMYFUNCTION("""COMPUTED_VALUE"""),989.3664) -> 989.3664 | J33: =G33*F33 -> 8
A34: =IFERROR(__xludf.DUMMYFUNCTION("""COMPUTED_VALUE"""),7688474.0) -> 7688474 | B34: =IFERROR(__xludf.DUMMYFUNCTION("""COMPUTED_VALUE"""),"BookingCom") -> BookingCom | C34: =IFERROR(__xludf.DUMMYFUNCTION("""COMPUTED_VALUE"""),"Matteo Sottana ") -> Matteo Sottana | D34: =IFERROR(__xludf.DUMMYFUNCTION("""COMPUTED_VALUE"""),46029.0) -> 46029 | E34: =IFERROR(__xludf.DUMMYFUNCTION("""COMPUTED_VALUE"""),46032.0) -> 46032 | F34: =IFERROR(__xludf.DUMMYFUNCTION("""COMPUTED_VALUE"""),3.0) -> 3 | G34: =IFERROR(__xludf.DUMMYFUNCTION("""COMPUTED_VALUE"""),2.0) -> 2 | H34: =IFERROR(__xludf.DUMMYFUNCTION("""COMPUTED_VALUE"""),156.83) -> 156.83 | I34: =IFERROR(__xludf.DUMMYFUNCTION("""COMPUTED_VALUE"""),376.39200000000005) -> 376.392 | J34: =G34*F34 -> 6
A35: =IFERROR(__xludf.DUMMYFUNCTION("""COMPUTED_VALUE"""),7853656.0) -> 7853656 | B35: =IFERROR(__xludf.DUMMYFUNCTION("""COMPUTED_VALUE"""),"BookingCom") -> BookingCom | C35: =IFERROR(__xludf.DUMMYFUNCTION("""COMPUTED_VALUE"""),"Daan van Zon ") -> Daan van Zon | D35: =IFERROR(__xludf.DUMMYFUNCTION("""COMPUTED_VALUE"""),46029.0) -> 46029 | E35: =IFERROR(__xludf.DUMMYFUNCTION("""COMPUTED_VALUE"""),46031.0) -> 46031 | F35: =IFERROR(__xludf.DUMMYFUNCTION("""COMPUTED_VALUE"""),2.0) -> 2 | G35: =IFERROR(__xludf.DUMMYFUNCTION("""COMPUTED_VALUE"""),2.0) -> 2 | H35: =IFERROR(__xludf.DUMMYFUNCTION("""COMPUTED_VALUE"""),156.26) -> 156.26 | I35: =IFERROR(__xludf.DUMMYFUNCTION("""COMPUTED_VALUE"""),250.016) -> 250.016 | J35: =G35*F35 -> 4
A36: =IFERROR(__xludf.DUMMYFUNCTION("""COMPUTED_VALUE"""),7860704.0) -> 7860704 | B36: =IFERROR(__xludf.DUMMYFUNCTION("""COMPUTED_VALUE"""),"BookingCom") -> BookingCom | C36: =IFERROR(__xludf.DUMMYFUNCTION("""COMPUTED_VALUE"""),"Shaif Ahmed ") -> Shaif Ahmed | D36: =IFERROR(__xludf.DUMMYFUNCTION("""COMPUTED_VALUE"""),46029.0) -> 46029 | E36: =IFERROR(__xludf.DUMMYFUNCTION("""COMPUTED_VALUE"""),46033.0) -> 46033 | F36: =IFERROR(__xludf.DUMMYFUNCTION("""COMPUTED_VALUE"""),4.0) -> 4 | G36: =IFERROR(__xludf.DUMMYFUNCTION("""COMPUTED_VALUE"""),2.0) -> 2 | H36: =IFERROR(__xludf.DUMMYFUNCTION("""COMPUTED_VALUE"""),210.23) -> 210.23 | I36: =IFERROR(__xludf.DUMMYFUNCTION("""COMPUTED_VALUE"""),672.736) -> 672.736 | J36: =G36*F36 -> 8
A37: =IFERROR(__xludf.DUMMYFUNCTION("""COMPUTED_VALUE"""),7874589.0) -> 7874589 | B37: =IFERROR(__xludf.DUMMYFUNCTION("""COMPUTED_VALUE"""),"BookingCom") -> BookingCom | C37: =IFERROR(__xludf.DUMMYFUNCTION("""COMPUTED_VALUE"""),"Mirjam Blasing ") -> Mirjam Blasing | D37: =IFERROR(__xludf.DUMMYFUNCTION("""COMPUTED_VALUE"""),46029.0) -> 46029 | E37: =IFERROR(__xludf.DUMMYFUNCTION("""COMPUTED_VALUE"""),46031.0) -> 46031 | F37: =IFERROR(__xludf.DUMMYFUNCTION("""COMPUTED_VALUE"""),2.0) -> 2 | G37: =IFERROR(__xludf.DUMMYFUNCTION("""COMPUTED_VALUE"""),2.0) -> 2 | H37: =IFERROR(__xludf.DUMMYFUNCTION("""COMPUTED_VALUE"""),183.6) -> 183.6 | I37: =IFERROR(__xludf.DUMMYFUNCTION("""COMPUTED_VALUE"""),293.76) -> 293.76 | J37: =G37*F37 -> 4
